Workbook

Sheet 2021
C1: Identificador | D1: +1+2+4+32+22-0-0-0-0-0-0-0-0 | E1: 0-+1-0-0-0-0-0-0-0 | F1: 0-+1-+1-0-0-0-0-0-0 | G1: 0-+1-+2-0-0-0-0-0-0 | H1: 0-+2-0-0-0-0-0-0-0 | I1: 32-3-0-0-0-0-0-0-0 | J1: 1-0-0-0-0-0-0-0-0 | K1: 1-1-0-0-0-0-0-0-0 | L1: 0-0-0-0-0-+200-0-0-0 | M1: +1-0-+2-0-0-0-0-0-0 | N1: 0-0-0-0-0-+100-0-0-0 | O1: 1-0-1-0-0-0-0-0-0 | P1: 2-0-0-0-0-0-0-0-0 | Q1: 2-1-0-0-0-0-0-0-0 | R1: 2-1-1-0-0-0-0-0-0 | S1: 2-1-2-0-0-0-0-0-0 | T1: +4-0-0-0-0-0-0-0-0 | U1: 4-0-1-0-0-0-0-0-0 | V1: 4-0-2-0-0-0-0-0-0 | W1: 4-0-0-1-0-0-0-0-0 | X1: 4-1-0-1-0-0-0-0-0 | Y1: 4-1-1-1-0-0-0-0-0 | Z1: 4-1-2-1-0-0-0-0-0 | AA1: +32-3-0-0-0-0-0-0-0 | AB1: 1-1-1-1-1-200-1-1- | AC1: 1-1-1-1-2-200-1-1- | AD1: 1-1-2-1-6-0-1-1- | AE1: 1-1-1-1-7-200-1-2- | AF1: 1-1-2-1-9-0-1-3- | AG1: 1-1-2-1-12-0-1-3- | AH1: 1-1-2-1-13-0-1-3- | AI1: 1-1-1-1-23-200-1-1- | AJ1: 1-1-1-2-30-200-7-3- | AK1: 1-1-1-2-39-200-7-2- | AL1: 1-1-2-2-42-0-7-3- | AM1: 1-2-1-1-43-100-1-2- | AN1: 1-1-1-2-49-200-7-1- | AO1: 1-1-1-1-51-200-6-3- | AP1: 1-1-1-1-52-200-6-3- | AQ1: 1-1-1-1-53-200-6-3- | AR1: 1-1-1-1-54-200-6-3- | AS1: 1-1-1-1-55-200-6-3- | AT1: 1-1-2-1-56-0-6-3- | AU1: 1-1-2-1-57-0-6-3- | AV1: 1-1-1-1-58-200-1-3- | AW1: 1-1-2-1-59-0-1-1- | AX1: 1-1-1-1-60-200-1-1- | AY1: 1-1-1-1-62-200-1-1- | AZ1: 1-1-1-1-63-200-1-1- | BA1: 1-1-2-1-64-0-1-1- | BB1: 1-1-1-1-65-200-1-1- | BC1: 1-1-2-1-66-0-1-1- | BD1: 2-1-1-4-11-0-1-1- | BE1: 2-1-1-4-37-0-1-2- | BF1: 2-1-2-4-42-0-2-0- | BG1: 2-1-1-4-48-0-2-0- | BH1: 2-1-1-4-49-0-2-0- | BI1: 4-1-1-1-8-0-1-1- | BJ1: 4-1-1-1-26-0-1-2- | BK1: 4-1-2-1-31-0-1-3- | BL1: 4-1-1-1-46-0-6-1- | BM1: 4-1-1-1-108-0-1-2- | BN1: 4-1-1-1-117-0-0-3- | BO1: 4-1-2-1-118-0-0-3- | BP1: 4-1-2-1-120-0-0-3- | BQ1: 4-1-1-1-121-0-0-3- | BR1: 4-1-2-1-122-0-0-3- | BS1: 4-1-2-1-123-0-0-3- | BT1: 32-3-1-1-1-0-1-1-300 | BU1: 32-3-1-1-2-0-1-3-300 | BV1: 32-3-1-1-3-0-1-2-300 | BW1: 32-3-1-1-4-0-1-2-300 | BX1: 32-3-1-1-5-0-1-3-300
C2: Tipo | D2: +1+2+4+32+22 | E2: 0 | F2: 0 | G2: 0 | H2: 0 | I2: 32 | J2: 1 | K2: 1 | L2: 0 | M2: +1 | N2: 0 | O2: 1 | P2: 2 | Q2: 2 | R2: 2 | S2: 2 | T2: +4 | U2: 4 | V2: 4 | W2: 4 | X2: 4 | Y2: 4 | Z2: 4 | AA2: +32 | AB2: 1 | AC2: 1 | AD2: 1 | AE2: 1 | AF2: 1 | AG2: 1 | AH2: 1 | AI2: 1 | AJ2: 1 | AK2: 1 | AL2: 1 | AM2: 1 | AN2: 1 | AO2: 1 | AP2: 1 | AQ2: 1 | AR2: 1 | AS2: 1 | AT2: 1 | AU2: 1 | AV2: 1 | AW2: 1 | AX2: 1 | AY2: 1 | AZ2: 1 | BA2: 1 | BB2: 1 | BC2: 1 | BD2: 2 | BE2: 2 | BF2: 2 | BG2: 2 | BH2: 2 | BI2: 4 | BJ2: 4 | BK2: 4 | BL2: 4 | BM2: 4 | BN2: 4 | BO2: 4 | BP2: 4 | BQ2: 4 | BR2: 4 | BS2: 4 | BT2: 32 | BU2: 32 | BV2: 32 | BW2: 32 | BX2: 32
C3: Clase | D3: 0 | E3: +1 | F3: +1 | G3: +1 | H3: +2 | I3: 3 | J3: 0 | K3: 1 | L3: 0 | M3: 0 | N3: 0 | O3: 0 | P3: 0 | Q3: 1 | R3: 1 | S3: 1 | T3: 0 | U3: 0 | V3: 0 | W3: 0 | X3: 1 | Y3: 1 | Z3: 1 | AA3: 3 | AB3: 1 | AC3: 1 | AD3: 1 | AE3: 1 | AF3: 1 | AG3: 1 | AH3: 1 | AI3: 1 | AJ3: 1 | AK3: 1 | AL3: 1 | AM3: 2 | AN3: 1 | AO3: 1 | AP3: 1 | AQ3: 1 | AR3: 1 | AS3: 1 | AT3: 1 | AU3: 1 | AV3: 1 | AW3: 1 | AX3: 1 | AY3: 1 | AZ3: 1 | BA3: 1 | BB3: 1 | BC3: 1 | BD3: 1 | BE3: 1 | BF3: 1 | BG3: 1 | BH3: 1 | BI3: 1 | BJ3: 1 | BK3: 1 | BL3: 1 | BM3: 1 | BN3: 1 | BO3: 1 | BP3: 1 | BQ3: 1 | BR3: 1 | BS3: 1 | BT3: 3 | BU3: 3 | BV3: 3 | BW3: 3 | BX3: 3
C4: Origen | D4: 0 | E4: 0 | F4: +1 | G4: +2 | H4: 0 | I4: 0 | J4: 0 | K4: 0 | L4: 0 | M4: +2 | N4: 0 | O4: 1 | P4: 0 | Q4: 0 | R4: 1 | S4: 2 | T4: 0 | U4: 1 | V4: 2 | W4: 0 | X4: 0 | Y4: 1 | Z4: 2 | AA4: 0 | AB4: 1 | AC4: 1 | AD4: 2 | AE4: 1 | AF4: 2 | AG4: 2 | AH4: 2 | AI4: 1 | AJ4: 1 | AK4: 1 | AL4: 2 | AM4: 1 | AN4: 1 | AO4: 1 | AP4: 1 | AQ4: 1 | AR4: 1 | AS4: 1 | AT4: 2 | AU4: 2 | AV4: 1 | AW4: 2 | AX4: 1 | AY4: 1 | AZ4: 1 | BA4: 2 | BB4: 1 | BC4: 2 | BD4: 1 | BE4: 1 | BF4: 2 | BG4: 1 | BH4: 1 | BI4: 1 | BJ4: 1 | BK4: 2 | BL4: 1 | BM4: 1 | BN4: 1 | BO4: 2 | BP4: 2 | BQ4: 1 | BR4: 2 | BS4: 2 | BT4: 1 | BU4: 1 | BV4: 1 | BW4: 1 | BX4: 1
C5: Categoría | D5: 0 | E5: 0 | F5: 0 | G5: 0 | H5: 0 | I5: 0 | J5: 0 | K5: 0 | L5: 0 | M5: 0 | N5: 0 | O5: 0 | P5: 0 | Q5: 0 | R5: 0 | S5: 0 | T5: 0 | U5: 0 | V5: 0 | W5: 1 | X5: 1 | Y5: 1 | Z5: 1 | AA5: 0 | AB5: 1 | AC5: 1 | AD5: 1 | AE5: 1 | AF5: 1 | AG5: 1 | AH5: 1 | AI5: 1 | AJ5: 2 | AK5: 2 | AL5: 2 | AM5: 1 | AN5: 2 | AO5: 1 | AP5: 1 | AQ5: 1 | AR5: 1 | AS5: 1 | AT5: 1 | AU5: 1 | AV5: 1 | AW5: 1 | AX5: 1 | AY5: 1 | AZ5: 1 | BA5: 1 | BB5: 1 | BC5: 1 | BD5: 4 | BE5: 4 | BF5: 4 | BG5: 4 | BH5: 4 | BI5: 1 | BJ5: 1 | BK5: 1 | BL5: 1 | BM5: 1 | BN5: 1 | BO5: 1 | BP5: 1 | BQ5: 1 | BR5: 1 | BS5: 1 | BT5: 1 | BU5: 1 | BV5: 1 | BW5: 1 | BX5: 1
C6: Código | D6: 0 | E6: 0 | F6: 0 | G6: 0 | H6: 0 | I6: 0 | J6: 0 | K6: 0 | L6: 0 | M6: 0 | N6: 0 | O6: 0 | P6: 0 | Q6: 0 | R6: 0 | S6: 0 | T6: 0 | U6: 0 | V6: 0 | W6: 0 | X6: 0 | Y6: 0 | Z6: 0 | AA6: 0 | AB6: 1 | AC6: 2 | AD6: 6 | AE6: 7 | AF6: 9 | AG6: 12 | AH6: 13 | AI6: 23 | AJ6: 30 | AK6: 39 | AL6: 42 | AM6: 43 | AN6: 49 | AO6: 51 | AP6: 52 | AQ6: 53 | AR6: 54 | AS6: 55 | AT6: 56 | AU6: 57 | AV6: 58 | AW6: 59 | AX6: 60 | AY6: 62 | AZ6: 63 | BA6: 64 | BB6: 65 | BC6: 66 | BD6: 11 | BE6: 37 | BF6: 42 | BG6: 48 | BH6: 49 | BI6: 8 | BJ6: 26 | BK6: 31 | BL6: 46 | BM6: 108 | BN6: 117 | BO6: 118 | BP6: 120 | BQ6: 121 | BR6: 122 | BS6: 123 | BT6: 1 | BU6: 2 | BV6: 3 | BW6: 4 | BX6: 5
C7: Gupo | D7: 0 | E7: 0 | F7: 0 | G7: 0 | H7: 0 | I7: 0 | J7: 0 | K7: 0 | L7: +200 | M7: 0 | N7: +100 | O7: 0 | P7: 0 | Q7: 0 | R7: 0 | S7: 0 | T7: 0 | U7: 0 | V7: 0 | W7: 0 | X7: 0 | Y7: 0 | Z7: 0 | AA7: 0 | AB7: 200 | AC7: 200 | AD7: 0 | AE7: 200 | AF7: 0 | AG7: 0 | AH7: 0 | AI7: 200 | AJ7: 200 | AK7: 200 | AL7: 0 | AM7: 100 | AN7: 200 | AO7: 200 | AP7: 200 | AQ7: 200 | AR7: 200 | AS7: 200 | AT7: 0 | AU7: 0 | AV7: 200 | AW7: 0 | AX7: 200 | AY7: 200 | AZ7: 200 | BA7: 0 | BB7: 200 | BC7: 0 | BD7: 0 | BE7: 0 | BF7: 0 | BG7: 0 | BH7: 0 | BI7: 0 | BJ7: 0 | BK7: 0 | BL7: 0 | BM7: 0 | BN7: 0 | BO7: 0 | BP7: 0 | BQ7: 0 | BR7: 0 | BS7: 0 | BT7: 0 | BU7: 0 | BV7: 0 | BW7: 0 | BX7: 0
C8: Estado | D8: 0 | E8: 0 | F8: 0 | G8: 0 | H8: 0 | I8: 0 | J8: 0 | K8: 0 | L8: 0 | M8: 0 | N8: 0 | O8: 0 | P8: 0 | Q8: 0 | R8: 0 | S8: 0 | T8: 0 | U8: 0 | V8: 0 | W8: 0 | X8: 0 | Y8: 0 | Z8: 0 | AA8: 0 | AB8: 1 | AC8: 1 | AD8: 1 | AE8: 1 | AF8: 1 | AG8: 1 | AH8: 1 | AI8: 1 | AJ8: 7 | AK8: 7 | AL8: 7 | AM8: 1 | AN8: 7 | AO8: 6 | AP8: 6 | AQ8: 6 | AR8: 6 | AS8: 6 | AT8: 6 | AU8: 6 | AV8: 1 | AW8: 1 | AX8: 1 | AY8: 1 | AZ8: 1 | BA8: 1 | BB8: 1 | BC8: 1 | BD8: 1 | BE8: 1 | BF8: 2 | BG8: 2 | BH8: 2 | BI8: 1 | BJ8: 1 | BK8: 1 | BL8: 6 | BM8: 1 | BN8: 0 | BO8: 0 | BP8: 0 | BQ8: 0 | BR8: 0 | BS8: 0 | BT8: 1 | BU8: 1 | BV8: 1 | BW8: 1 | BX8: 1
C9: Delegatura | D9: 0 | E9: 0 | F9: 0 | G9: 0 | H9: 0 | I9: 0 | J9: 0 | K9: 0 | L9: 0 | M9: 0 | N9: 0 | O9: 0 | P9: 0 | Q9: 0 | R9: 0 | S9: 0 | T9: 0 | U9: 0 | V9: 0 | W9: 0 | X9: 0 | Y9: 0 | Z9: 0 | AA9: 0 | AB9: 1 | AC9: 1 | AD9: 1 | AE9: 2 | AF9: 3 | AG9: 3 | AH9: 3 | AI9: 1 | AJ9: 3 | AK9: 2 | AL9: 3 | AM9: 2 | AN9: 1 | AO9: 3 | AP9: 3 | AQ9: 3 | AR9: 3 | AS9: 3 | AT9: 3 | AU9: 3 | AV9: 3 | AW9: 1 | AX9: 1 | AY9: 1 | AZ9: 1 | BA9: 1 | BB9: 1 | BC9: 1 | BD9: 1 | BE9: 2 | BF9: 0 | BG9: 0 | BH9: 0 | BI9: 1 | BJ9: 2 | BK9: 3 | BL9: 1 | BM9: 2 | BN9: 3 | BO9: 3 | BP9: 3 | BQ9: 3 | BR9: 3 | BS9: 3 | BT9: 1 | BU9: 3 | BV9: 2 | BW9: 2 | BX9: 3
C10: Director Técnico | D10: 0 | E10: 0 | F10: 0 | G10: 0 | H10: 0 | I10: 0 | J10: 0 | K10: 0 | L10: 0 | M10: 0 | N10: 0 | O10: 0 | P10: 0 | Q10: 0 | R10: 0 | S10: 0 | T10: 0 | U10: 0 | V10: 0 | W10: 0 | X10: 0 | Y10: 0 | Z10: 0 | AA10: 0 | AB10: 0 | AC10: 0 | AD10: 0 | AE10: 0 | AF10: 0 | AG10: 0 | AH10: 0 | AI10: 0 | AJ10: 0 | AK10: 0 | AL10: 0 | AM10: 0 | AN10: 0 | AO10: 0 | AP10: 0 | AQ10: 0 | AR10: 0 | AS10: 0 | AT10: 0 | AU10: 0 | AV10: 0 | AW10: 0 | AX10: 0 | AY10: 0 | AZ10: 0 | BA10: 0 | BB10: 0 | BC10: 0 | BD10: 0 | BE10: 0 | BF10: 0 | BG10: 0 | BH10: 0 | BI10: 0 | BJ10: 0 | BK10: 0 | BL10: 0 | BM10: 0 | BN10: 0 | BO10: 0 | BP10: 0 | BQ10: 0 | BR10: 0 | BS10: 0 | BT10: 300 | BU10: 300 | BV10: 300 | BW10: 300 | BX10: 300
C11: Nombre de la entidad | D11: Total Entidades Establecimientos de crédito sin IOE'S | E11: Total Sector Privado | F11: Total Sector Privado Nacional | G11: Total Sector Privado Extranjero | H11: Total Sector Público | I11: Total Sector Cooperativas | J11: Total Bancos | K11: Bancos Privados | L11: Bancos Privados Nacionales | M11: Bancos Privados Extranjeros | N11: Bancos Públicos | O11: Bancos Nacionales | P11: Total CFIs | Q11: CFIs Privadas | R11: CFIs Privadas Nacionales | S11: CFIs Privadas Extranjeras | T11: Total CFs | U11: Total CFs Nacionales (Tradicionales+Leasing) | V11: Total CFs Extranjeras (Tradicionales+Leasing) | W11: Total CFs Tradicionales | X11: CFs Privadas | Y11: CFs Privadas Nacionales | Z11: CFs Privadas Extranjeras | AA11: Total Cooperativas | AB11: BANCO DE BOGOTA | AC11: BANCO POPULAR | AD11: ITAÚ CORPBANCA COLOMBIA S.A. | AE11: BANCOLOMBIA | AF11: CITIBANK-COLOMBIA | AG11: GNB SUDAMERIS | AH11: BBVA COLOMBIA | AI11: OCCIDENTE | AJ11: BANCO CAJA SOCIAL | AK11: DAVIVIENDA | AL11: SCOTIABANK COLPATRIA S.A | AM11: BANAGRARIO | AN11: BANCO AV VILLAS | AO11: BANCO CREDIFINANCIERA | AP11: BANCAMIA | AQ11: BANCO W S.A. | AR11: BANCOOMEVA | AS11: BANCO FINANDINA | AT11: BANCO FALABELLA S.A. | AU11: BANCO PICHINCHA S.A. | AV11: COOPCENTRAL | AW11: BANCO SANTANDER DE NEGOCIOS COLOMBIA | AX11: BANCO MUNDO MUJER S.A. | AY11: MIBANCO S.A. | AZ11: BANCO SERFINANZA S.A. | BA11: BANCO J.P: MORGAN COLOMBIA S.A. | BB11: LULO BANK S.A. | BC11: BANCO PTG PACTUAL | BD11: CORFICOLOMBIANA | BE11: B INV BANCOLOMBIA | BF11: BNP PARIBAS COLOMBIA | BG11: CORPORACIÓN FINANCIERA GNB SUDAMERIS S.A | BH11: CORPORACIÓN FINANCIERA DAVIVIENDA | BI11: GIROS Y FINANZAS | BJ11: COMPAÑÍA DE FINANCIAMIENTO TUYA | BK11: GM FINANCIAL COLOMBIA S.A. | BL11: COLTEFINANCIERA | BM11: DANN REGIONAL | BN11: CREDIFAMILIA | BO11: CREZCAMOS S.A. | BP11: LA HIPOTECARIA | BQ11: FINANCIERA JURISCOOP S.A. | BR11: RCI COLOMBIA S.A. | BS11: BANCAR TECNOLOGIA CO S.A. | BT11: COOP FINAN DE ANTIOQUIA | BU11: JFK COOPERATIVA FINANCIERA | BV11: COOP FINAN COOFINEP | BW11: COOP FINAN COTRAFA | BX11: COOP FINAN CONFIAR
C12: Cifras con corte a 24-feb-2022 | D12: dic-21 | E12: dic-21 | F12: dic-21 | G12: dic-21 | H12: dic-21 | I12: dic-21 | J12: dic-21 | K12: dic-21 | L12: dic-21 | M12: dic-21 | N12: dic-21 | O12: dic-21 | P12: dic-21 | Q12: dic-21 | R12: dic-21 | S12: dic-21 | T12: dic-21 | U12: dic-21 | V12: dic-21 | W12: dic-21 | X12: dic-21 | Y12: dic-21 | Z12: dic-21 | AA12: dic-21 | AB12: dic-21 | AC12: dic-21 | AD12: dic-21 | AE12: dic-21 | AF12: dic-21 | AG12: dic-21 | AH12: dic-21 | AI12: dic-21 | AJ12: dic-21 | AK12: dic-21 | AL12: dic-21 | AM12: dic-21 | AN12: dic-21 | AO12: dic-21 | AP12: dic-21 | AQ12: dic-21 | AR12: dic-21 | AS12: dic-21 | AT12: dic-21 | AU12: dic-21 | AV12: dic-21 | AW12: dic-21 | AX12: dic-21 | AY12: dic-21 | AZ12: dic-21 | BA12: dic-21 | BB12: dic-21 | BC12: dic-21 | BD12: dic-21 | BE12: dic-21 | BF12: dic-21 | BG12: dic-21 | BH12: dic-21 | BI12: dic-21 | BJ12: dic-21 | BK12: dic-21 | BL12: dic-21 | BM12: dic-21 | BN12: dic-21 | BO12: dic-21 | BP12: dic-21 | BQ12: dic-21 | BR12: dic-21 | BS12: dic-21 | BT12: dic-21 | BU12: dic-21 | BV12: dic-21 | BW12: dic-21 | BX12: dic-21
A13: BALANCE (cifras en $ millones)
A14: ACTIVOS | D14: 8.6102156e+08 | E14: 8.2435572e+08 | F14: 6.0102194e+08 | G14: 2.2333378e+08 | H14: 32216897 | I14: 4448949.1 | J14: 8.1757085e+08 | K14: 7.8535395e+08 | L14: 5.6825555e+08 | M14: 2.170984e+08 | N14: 32216897 | O14: 6.0047244e+08 | P14: 25217277 | Q14: 25217277 | R14: 24719512 | S14: 497764.6 | T14: 13784490 | U14: 8046878.3 | V14: 5737611.8 | W14: 13784490 | X14: 13784490 | Y14: 8046878.3 | Z14: 5737611.8 | AA14: 4448949.1 | AB14: 1.0863049e+08 | AC14: 29708064 | AD14: 30417280 | AE14: 2.0896007e+08 | AF14: 12366001 | AG14: 35958041 | AH14: 79516659 | AI14: 47147802 | AJ14: 18069652 | AK14: 1.1733175e+08 | AL14: 40258759 | AM14: 32216897 | AN14: 17253831 | AO14: 2050719.5 | AP14: 2056792.6 | AQ14: 2179116.2 | AR14: 4814725.7 | AS14: 2735091.4 | AT14: 6351326.6 | AU14: 3158147.4 | AV14: 1144241.7 | AW14: 5507740.6 | AX14: 2319961.9 | AY14: 1401990 | AZ14: 2294876.3 | BA14: 3462364.7 | BB14: 156363.69 | BC14: 102086.7 | BD14: 21712809 | BE14: 2019367.6 | BF14: 497764.6 | BG14: 754207.35 | BH14: 233128.86 | BI14: 905633.3 | BJ14: 3861357.3 | BK14: 2067923.3 | BL14: 895679.38 | BM14: 522454.61 | BN14: 573600.63 | BO14: 442584.47 | BP14: 357395.62 | BQ14: 1288153.2 | BR14: 2841496.8 | BS14: 28211.61 | BT14: 525872.89 | BU14: 1284334.3 | BV14: 319207.78 | BW14: 1055168.9 | BX14: 1264365.3
B15: DISPONIBLE | D15: 67795668 | E15: 65781171 | F15: 41275624 | G15: 24505546 | H15: 1471059.9 | I15: 543437.88 | J15: 63663067 | K15: 62192007 | L15: 37973359 | M15: 24218649 | N15: 1471059.9 | O15: 39444419 | P15: 2469564.6 | Q15: 2469564.6 | R15: 2464526.1 | S15: 5038.43 | T15: 1119598.5 | U15: 837739.57 | V15: 281858.98 | W15: 1119598.5 | X15: 1119598.5 | Y15: 837739.57 | Z15: 281858.98 | AA15: 543437.88 | AB15: 7322021.6 | AC15: 1682835.1 | AD15: 2427296.4 | AE15: 13333358 | AF15: 2799716.9 | AG15: 3622542.1 | AH15: 10268052 | AI15: 4408326.4 | AJ15: 1211127.7 | AK15: 7094112.2 | AL15: 3701888.9 | AM15: 1471059.9 | AN15: 884368.25 | AO15: 293924.81 | AP15: 144289.94 | AQ15: 330372.13 | AR15: 288537.91 | AS15: 202647.32 | AT15: 219602.39 | AU15: 210203.76 | AV15: 136865.98 | AW15: 866829.57 | AX15: 160577.59 | AY15: 183760.04 | AZ15: 261883.57 | BA15: 16620.89 | BB15: 34350.08 | BC15: 85896.16 | BD15: 1602383.8 | BE15: 822523.29 | BF15: 5038.43 | BG15: 11531.22 | BH15: 28087.85 | BI15: 109392.65 | BJ15: 353348.13 | BK15: 119794.46 | BL15: 113214.59 | BM15: 60410.57 | BN15: 36915.33 | BO15: 15426.42 | BP15: 38742.68 | BQ15: 164458.3 | BR15: 94098.13 | BS15: 13797.29 | BT15: 68623.83 | BU15: 173039.77 | BV15: 40973.92 | BW15: 126905.61 | BX15: 133894.75
B16: POSICIONES ACTIVAS EN OPERACIONES DE MERCADO MONETARIO Y RELACIONADAS | D16: 22515567 | E16: 22447883 | F16: 6856334.6 | G16: 15591549 | H16: 67683.73 | I16: 0 | J16: 21552983 | K16: 21485299 | L16: 5893750 | M16: 15591549 | N16: 67683.73 | O16: 5961433.8 | P16: 949386.47 | Q16: 949386.47 | R16: 949386.47 | S16: 0 | T16: 13198.12 | U16: 13198.12 | V16: 0 | W16: 13198.12 | X16: 13198.12 | Y16: 13198.12 | Z16: 0 | AA16: 0 | AB16: 69920.02 | AC16: 147007.26 | AD16: 2411319.2 | AE16: 1419807.7 | AF16: 1159172.8 | AG16: 8849894.3 | AH16: 737063.89 | AI16: 398024.52 | AJ16: 1350354.7 | AK16: 2220163.5 | AL16: 1286076.7 | AM16: 67683.73 | AN16: 24933.59 | AO16: 0 | AP16: 46006.46 | AQ16: 76874.63 | AR16: 14656.69 | AS16: 0 | AT16: 99500 | AU16: 0 | AV16: 0 | AW16: 230954.94 | AX16: 0 | AY16: 3000.49 | AZ16: 120000 | BA16: 817567.02 | BB16: 3000.49 | BC16: 0 | BD16: 949386.47 | BE16: 0 | BF16: 0 | BG16: 0 | BH16: 0 | BI16: 0 | BJ16: 0 | BK16: 0 | BL16: 0 | BM16: 0 | BN16: 0 | BO16: 0 | BP16: 0 | BQ16: 13198.12 | BR16: 0 | BS16: 0 | BT16: 0 | BU16: 0 | BV16: 0 | BW16: 0 | BX16: 0
C17: INTERBANCARIOS | D17: 4678851.2 | E17: 4611167.5 | F17: 3387897.7 | G17: 1223269.9 | H17: 67683.73 | I17: 0 | J17: 4371876 | K17: 4304192.3 | L17: 3080922.4 | M17: 1223269.9 | N17: 67683.73 | O17: 3148606.1 | P17: 306975.24 | Q17: 306975.24 | R17: 306975.24 | S17: 0 | T17: 0 | U17: 0 | V17: 0 | W17: 0 | X17: 0 | Y17: 0 | Z17: 0 | AA17: 0 | AB17: 40013.55 | AC17: 8201.19 | AD17: 384721.61 | AE17: 707904.43 | AF17: 0 | AG17: 115843.37 | AH17: 30009.72 | AI17: 325437.84 | AJ17: 1350354.7 | AK17: 477003.3 | AL17: 593195.15 | AM17: 67683.73 | AN17: 0 | AO17: 0 | AP17: 46006.46 | AQ17: 0 | AR17: 0 | AS17: 0 | AT17: 99500 | AU17: 0 | AV17: 0 | AW17: 0 | AX17: 0 | AY17: 3000.49 | AZ17: 120000 | BA17: 0 | BB17: 3000.49 | BC17: 0 | BD17: 306975.24 | BE17: 0 | BF17: 0 | BG17: 0 | BH17: 0 | BI17: 0 | BJ17: 0 | BK17: 0 | BL17: 0 | BM17: 0 | BN17: 0 | BO17: 0 | BP17: 0 | BQ17: 0 | BR17: 0 | BS17: 0 | BT17: 0 | BU17: 0 | BV17: 0 | BW17: 0 | BX17: 0
C18: OPERACIONES DE REPORTO O REPO | D18: 0 | E18: 0 | F18: 0 | G18: 0 | H18: 0 | I18: 0 | J18: 0 | K18: 0 | L18: 0 | M18: 0 | N18: 0 | O18: 0 | P18: 0 | Q18: 0 | R18: 0 | S18: 0 | T18: 0 | U18: 0 | V18: 0 | W18: 0 | X18: 0 | Y18: 0 | Z18: 0 | AA18: 0 | AB18: 0 | AC18: 0 | AD18: 0 | AE18: 0 | AF18: 0 | AG18: 0 | AH18: 0 | AI18: 0 | AJ18: 0 | AK18: 0 | AL18: 0 | AM18: 0 | AN18: 0 | AO18: 0 | AP18: 0 | AQ18: 0 | AR18: 0 | AS18: 0 | AT18: 0 | AU18: 0 | AV18: 0 | AW18: 0 | AX18: 0 | AY18: 0 | AZ18: 0 | BA18: 0 | BB18: 0 | BC18: 0 | BD18: 0 | BE18: 0 | BF18: 0 | BG18: 0 | BH18: 0 | BI18: 0 | BJ18: 0 | BK18: 0 | BL18: 0 | BM18: 0 | BN18: 0 | BO18: 0 | BP18: 0 | BQ18: 0 | BR18: 0 | BS18: 0 | BT18: 0 | BU18: 0 | BV18: 0 | BW18: 0 | BX18: 0
C19: OPERACIONES SIMULTÁNEAS | D19: 17836716 | E19: 17836716 | F19: 3468437 | G19: 14368279 | H19: 0 | I19: 0 | J19: 17181107 | K19: 17181107 | L19: 2812827.6 | M19: 14368279 | N19: 0 | O19: 2812827.6 | P19: 642411.23 | Q19: 642411.23 | R19: 642411.23 | S19: 0 | T19: 13198.12 | U19: 13198.12 | V19: 0 | W19: 13198.12 | X19: 13198.12 | Y19: 13198.12 | Z19: 0 | AA19: 0 | AB19: 29906.46 | AC19: 138806.07 | AD19: 2026597.6 | AE19: 711903.28 | AF19: 1159172.8 | AG19: 8734051 | AH19: 707054.17 | AI19: 72586.67 | AJ19: 0 | AK19: 1743160.2 | AL19: 692881.52 | AM19: 0 | AN19: 24933.59 | AO19: 0 | AP19: 0 | AQ19: 76874.63 | AR19: 14656.69 | AS19: 0 | AT19: 0 | AU19: 0 | AV19: 0 | AW19: 230954.94 | AX19: 0 | AY19: 0 | AZ19: 0 | BA19: 817567.02 | BB19: 0 | BC19: 0 | BD19: 642411.23 | BE19: 0 | BF19: 0 | BG19: 0 | BH19: 0 | BI19: 0 | BJ19: 0 | BK19: 0 | BL19: 0 | BM19: 0 | BN19: 0 | BO19: 0 | BP19: 0 | BQ19: 13198.12 | BR19: 0 | BS19: 0 | BT19: 0 | BU19: 0 | BV19: 0 | BW19: 0 | BX19: 0
C20: OPERACIONES DE TRANSFERENCIA TEMPORAL DE VALORES | D20: 0 | E20: 0 | F20: 0 | G20: 0 | H20: 0 | I20: 0 | J20: 0 | K20: 0 | L20: 0 | M20: 0 | N20: 0 | O20: 0 | P20: 0 | Q20: 0 | R20: 0 | S20: 0 | T20: 0 | U20: 0 | V20: 0 | W20: 0 | X20: 0 | Y20: 0 | Z20: 0 | AA20: 0 | AB20: 0 | AC20: 0 | AD20: 0 | AE20: 0 | AF20: 0 | AG20: 0 | AH20: 0 | AI20: 0 | AJ20: 0 | AK20: 0 | AL20: 0 | AM20: 0 | AN20: 0 | AO20: 0 | AP20: 0 | AQ20: 0 | AR20: 0 | AS20: 0 | AT20: 0 | AU20: 0 | AV20: 0 | AW20: 0 | AX20: 0 | AY20: 0 | AZ20: 0 | BA20: 0 | BB20: 0 | BC20: 0 | BD20: 0 | BE20: 0 | BF20: 0 | BG20: 0 | BH20: 0 | BI20: 0 | BJ20: 0 | BK20: 0 | BL20: 0 | BM20: 0 | BN20: 0 | BO20: 0 | BP20: 0 | BQ20: 0 | BR20: 0 | BS20: 0 | BT20: 0 | BU20: 0 | BV20: 0 | BW20: 0 | BX20: 0
C21: OTRAS POSICIONES ACTIVAS EN OPERACIONES DE MERCADO MONETARIO | D21: 0.0099999979 | E21: 0.0099999979 | F21: 0.02 | G21: -0.0099999998 | H21: 0 | I21: 0 | J21: 0.0099999979 | K21: 0.010000002 | L21: 0.02 | M21: -0.0099999998 | N21: 0 | O21: 0.02 | P21: 0 | Q21: 0 | R21: 0 | S21: 0 | T21: 0 | U21: 0 | V21: 0 | W21: 0 | X21: 0 | Y21: 0 | Z21: 0 | AA21: 0 | AB21: 0.01 | AC21: 0 | AD21: -0.01 | AE21: 0 | AF21: 0 | AG21: 0 | AH21: 0 | AI21: 0.01 | AJ21: 0 | AK21: 0 | AL21: 0 | AM21: 0 | AN21: 0 | AO21: 0 | AP21: 0 | AQ21: 0 | AR21: 0 | AS21: 0 | AT21: 0 | AU21: 0 | AV21: 0 | AW21: 0 | AX21: 0 | AY21: 0 | AZ21: 0 | BA21: 0 | BB21: 0 | BC21: 0 | BD21: 0 | BE21: 0 | BF21: 0 | BG21: 0 | BH21: 0 | BI21: 0 | BJ21: 0 | BK21: 0 | BL21: 0 | BM21: 0 | BN21: 0 | BO21: 0 | BP21: 0 | BQ21: 0 | BR21: 0 | BS21: 0 | BT21: 0 | BU21: 0 | BV21: 0 | BW21: 0 | BX21: 0
B22: INVERSIONES Y OPERACIONES CON DERIVADOS | D22: 1.9367992e+08 | E22: 1.7790376e+08 | F22: 1.3569436e+08 | G22: 42209405 | H22: 15419465 | I22: 356684.87 | J22: 1.7148951e+08 | K22: 1.5607004e+08 | L22: 1.1436017e+08 | M22: 41709877 | N22: 15419465 | O22: 1.2977963e+08 | P22: 21223296 | Q22: 21223296 | R22: 20801488 | S22: 421807.57 | T22: 610425.36 | U22: 532705.3 | V22: 77720.06 | W22: 610425.36 | X22: 610425.36 | Y22: 532705.3 | Z22: 77720.06 | AA22: 356684.87 | AB22: 34074776 | AC22: 5295881.2 | AD22: 4171100.9 | AE22: 44149292 | AF22: 5546201.6 | AG22: 11736059 | AH22: 10830911 | AI22: 8163289 | AJ22: 2512551.6 | AK22: 15764447 | AL22: 4491961.5 | AM22: 15419465 | AN22: 3197226.4 | AO22: 65568.64 | AP22: 33143.52 | AQ22: 61804.83 | AR22: 553230.9 | AS22: 69309.73 | AT22: 808932.34 | AU22: 543132.7 | AV22: 134399.31 | AW22: 1018342.2 | AX22: 132704.05 | AY22: 38948.1 | AZ22: 108016 | BA22: 2563235.5 | BB22: 5577.73 | BC22: 0 | BD22: 18761398 | BE22: 1188726.3 | BF22: 421807.57 | BG22: 712546.28 | BH22: 138817.84 | BI22: 215062.63 | BJ22: 109569.5 | BK22: 32837.75 | BL22: 71141.24 | BM22: 11917.47 | BN22: 3448.28 | BO22: 7354.91 | BP22: 18046.81 | BQ22: 121566.18 | BR22: 9469.49 | BS22: 10011.1 | BT22: 31035.35 | BU22: 102978 | BV22: 11340.64 | BW22: 124172.67 | BX22: 87158.21
C23: INVERSIONES A VALOR RAZONABLE CON CAMBIOS EN RESULTADOS - INSTRUMENTOS REPRESENTATIVOS DE DEUDA | D23: 26671359 | E23: 22755402 | F23: 16701036 | G23: 6054366 | H23: 3865857.6 | I23: 50098.96 | J23: 26267678 | K23: 22401821 | L23: 16519935 | M23: 5881885.2 | N23: 3865857.6 | O23: 20385793 | P23: 252233.74 | Q23: 252233.74 | R23: 93167.44 | S23: 159066.3 | T23: 101347.62 | U23: 87933.08 | V23: 13414.54 | W23: 101347.62 | X23: 101347.62 | Y23: 87933.08 | Z23: 13414.54 | AA23: 50098.96 | AB23: 940898.05 | AC23: 154777.83 | AD23: 754336.61 | AE23: 10983892 | AF23: 843186.84 | AG23: 4126.97 | AH23: 2554423.5 | AI23: 361289.09 | AJ23: 107371.2 | AK23: 3298599.7 | AL23: 570682.2 | AM23: 3865857.6 | AN23: 126849.71 | AO23: 14809.02 | AP23: 33142.49 | AQ23: 24178.74 | AR23: 306279.73 | AS23: 22460.12 | AT23: 45477.19 | AU23: 65564.86 | AV23: 74539.48 | AW23: 36451.27 | AX23: 68674.11 | AY23: 2173.69 | AZ23: 0 | BA23: 1007635.7 | BB23: 0 | BC23: 0 | BD23: 93167.44 | BE23: 0 | BF23: 159066.3 | BG23: 0 | BH23: 0 | BI23: 21220 | BJ23: 0 | BK23: 0 | BL23: 0 | BM23: 0 | BN23: 0 | BO23: 0 | BP23: 5006.68 | BQ23: 66713.08 | BR23: 0 | BS23: 8407.86 | BT23: 0 | BU23: 0 | BV23: 0 | BW23: 46587.31 | BX23: 3511.65
C24: INVERSIONES A VALOR RAZONABLE CON CAMBIOS EN RESULTADOS - INSTRUMENTOS DE PATRIMONIO | D24: 2026701.5 | E24: 2004376.2 | F24: 1450881.3 | G24: 553494.86 | H24: 0 | I24: 22325.33 | J24: 1864453 | K24: 1864453 | L24: 1320773.2 | M24: 543679.83 | N24: 0 | O24: 1320773.2 | P24: 119861.4 | Q24: 119861.4 | R24: 119861.4 | S24: 0 | T24: 20061.81 | U24: 10246.78 | V24: 9815.03 | W24: 20061.81 | X24: 20061.81 | Y24: 10246.78 | Z24: 9815.03 | AA24: 22325.33 | AB24: 624754.41 | AC24: 104167.89 | AD24: 9450.11 | AE24: 0 | AF24: 0 | AG24: 525724.5 | AH24: 0 | AI24: 422034.48 | AJ24: 218.94 | AK24: 11545.98 | AL24: 0 | AM24: 0 | AN24: 121738.68 | AO24: 3697.31 | AP24: 1.03 | AQ24: 803.2 | AR24: 0 | AS24: 150.05 | AT24: 0 | AU24: 8505.22 | AV24: 1058.01 | AW24: 0 | AX24: 28269.49 | AY24: 812.7 | AZ24: 1520.99 | BA24: 0 | BB24: 0 | BC24: 0 | BD24: 114736.4 | BE24: 5125 | BF24: 0 | BG24: 0 | BH24: 0 | BI24: 0 | BJ24: 7438.78 | BK24: 361.01 | BL24: 0 | BM24: 0 | BN24: 635.83 | BO24: 3643.74 | BP24: 936.33 | BQ24: 2172.17 | BR24: 3270.71 | BS24: 1603.24 | BT24: 10798.4 | BU24: 0 | BV24: 86.14 | BW24: 420.12 | BX24: 11020.67
C25: INVERSIONES A COSTO AMORTIZADO | D25: 26968300 | E25: 16909191 | F25: 13647225 | G25: 3261966.8 | H25: 9792908.2 | I25: 266200.91 | J25: 26441440 | K25: 16648532 | L25: 13431117 | M25: 3217415 | N25: 9792908.2 | O25: 23224025 | P25: 126.01 | Q25: 126.01 | R25: 126.01 | S25: 0 | T25: 260533.21 | U25: 215981.37 | V25: 44551.84 | W25: 260533.21 | X25: 260533.21 | Y25: 215981.37 | Z25: 44551.84 | AA25: 266200.91 | AB25: 2726597.2 | AC25: 1095453.9 | AD25: 682233.41 | AE25: 3120957.4 | AF25: 0 | AG25: 1185867.3 | AH25: 55422.37 | AI25: 775923.02 | AJ25: 1334860.1 | AK25: 3403052.1 | AL25: 773935.57 | AM25: 9792908.2 | AN25: 483919.05 | AO25: 44889.98 | AP25: 0 | AQ25: 29886.93 | AR25: 158564.48 | AS25: 23463.81 | AT25: 314232.9 | AU25: 43325.37 | AV25: 55494.21 | AW25: 162398.03 | AX25: 35760.45 | AY25: 35798.95 | AZ25: 106495.01 | BA25: 0 | BB25: 0.48 | BC25: 0 | BD25: 0 | BE25: 126.01 | BF25: 0 | BG25: 0 | BH25: 0 | BI25: 17499.44 | BJ25: 102130.72 | BK25: 32476.74 | BL25: 29830.91 | BM25: 11911.55 | BN25: 2812.45 | BO25: 3711.17 | BP25: 2165.15 | BQ25: 51796.3 | BR25: 6198.78 | BS25: 0 | BT25: 16394.97 | BU25: 102978 | BV25: 10897.04 | BW25: 65385.65 | BX25: 70545.25
C26: INVERSIONES A VALOR RAZONABLE CON CAMBIOS EN EL ORI - INSTRUMENTOS DE PATRIMONIO | D26: 3441351.1 | E26: 3271277 | F26: 2818316.4 | G26: 452960.63 | H26: 164663.7 | I26: 5410.38 | J26: 2049560.5 | K26: 1884896.8 | L26: 1431936.2 | M26: 452960.63 | N26: 164663.7 | O26: 1596599.9 | P26: 1368038.2 | Q26: 1368038.2 | R26: 1368038.2 | S26: 0 | T26: 18342.05 | U26: 18342.05 | V26: 0 | W26: 18342.05 | X26: 18342.05 | Y26: 18342.05 | Z26: 0 | AA26: 5410.38 | AB26: 271578.68 | AC26: 150617.44 | AD26: 34323.78 | AE26: 172424.16 | AF26: 74935.16 | AG26: 0 | AH26: 282266.5 | AI26: 110822.4 | AJ26: 136929.48 | AK26: 477538.75 | AL26: 61272.43 | AM26: 164663.7 | AN26: 96553.02 | AO26: 2172.33 | AP26: 0 | AQ26: 0 | AR26: 11788.24 | AS26: 1348.89 | AT26: 0 | AU26: 162.76 | AV26: 0 | AW26: 0 | AX26: 0 | AY26: 162.76 | AZ26: 0 | BA26: 0 | BB26: 0 | BC26: 0 | BD26: 1335870.5 | BE26: 32167.74 | BF26: 0 | BG26: 0 | BH26: 0 | BI26: 0 | BJ26: 0 | BK26: 0 | BL26: 17147.22 | BM26: 0 | BN26: 0 | BO26: 0 | BP26: 0 | BQ26: 1194.83 | BR26: 0 | BS26: 0 | BT26: 765.73 | BU26: 0 | BV26: 357.46 | BW26: 1556.37 | BX26: 2730.82
C27: INVERSIONES A VALOR RAZONABLE CON CAMBIOS EN RESULTADOS ENTREGADOS EN OPERACIONES DE MERCADO MONETARIO - INSTRUMENTOS REPRESENTATIVOS DE DEUDA (DERECHOS DE TRANSFERENCIA) | D27: 6903788.4 | E27: 5522002.6 | F27: 2690455.8 | G27: 2831546.8 | H27: 1381785.9 | I27: 0 | J27: 4956874 | K27: 3575088.1 | L27: 858356.32 | M27: 2716731.8 | N27: 1381785.9 | O27: 2240142.2 | P27: 1946914.5 | Q27: 1946914.5 | R27: 1832099.5 | S27: 114815.03 | T27: 0 | U27: 0 | V27: 0 | W27: 0 | X27: 0 | Y27: 0 | Z27: 0 | AA27: 0 | AB27: 0 | AC27: 0 | AD27: 38030.67 | AE27: 420792.3 | AF27: 624025.12 | AG27: 0 | AH27: 169048.78 | AI27: 329126.17 | AJ27: 0 | AK27: 94566.03 | AL27: 569797.32 | AM27: 1381785.9 | AN27: 0 | AO27: 0 | AP27: 0 | AQ27: 0 | AR27: 13871.82 | AS27: 0 | AT27: 0 | AU27: 0 | AV27: 0 | AW27: 0 | AX27: 0 | AY27: 0 | AZ27: 0 | BA27: 1315829.9 | BB27: 0 | BC27: 0 | BD27: 1832099.5 | BE27: 0 | BF27: 114815.03 | BG27: 0 | BH27: 0 | BI27: 0 | BJ27: 0 | BK27: 0 | BL27: 0 | BM27: 0 | BN27: 0 | BO27: 0 | BP27: 0 | BQ27: 0 | BR27: 0 | BS27: 0 | BT27: 0 | BU27: 0 | BV27: 0 | BW27: 0 | BX27: 0
C28: INVERSIONES A VALOR RAZONABLE CON CAMBIOS EN RESULTADOS ENTREGADOS EN OPERACIONES DE MERCADO MONETARIO - INSTRUMENTOS DE PATRIMONIO (DERECHOS DE TRANSFERENCIA) | D28: 0 | E28: 0 | F28: 0 | G28: 0 | H28: 0 | I28: 0 | J28: 0 | K28: 0 | L28: 0 | M28: 0 | N28: 0 | O28: 0 | P28: 0 | Q28: 0 | R28: 0 | S28: 0 | T28: 0 | U28: 0 | V28: 0 | W28: 0 | X28: 0 | Y28: 0 | Z28: 0 | AA28: 0 | AB28: 0 | AC28: 0 | AD28: 0 | AE28: 0 | AF28: 0 | AG28: 0 | AH28: 0 | AI28: 0 | AJ28: 0 | AK28: 0 | AL28: 0 | AM28: 0 | AN28: 0 | AO28: 0 | AP28: 0 | AQ28: 0 | AR28: 0 | AS28: 0 | AT28: 0 | AU28: 0 | AV28: 0 | AW28: 0 | AX28: 0 | AY28: 0 | AZ28: 0 | BA28: 0 | BB28: 0 | BC28: 0 | BD28: 0 | BE28: 0 | BF28: 0 | BG28: 0 | BH28: 0 | BI28: 0 | BJ28: 0 | BK28: 0 | BL28: 0 | BM28: 0 | BN28: 0 | BO28: 0 | BP28: 0 | BQ28: 0 | BR28: 0 | BS28: 0 | BT28: 0 | BU28: 0 | BV28: 0 | BW28: 0 | BX28: 0
C29: INVERSIONES A COSTO AMORTIZADO CON CAMBIOS EN RESULTADOS ENTREGADOS EN OPERACIONES DE MERCADO MONETARIO - INSTRUMENTOS REPRESENTATIVOS DE DEUDA (DERECHOS DE TRANSFERENCIA) | D29: 2429124.3 | E29: 2429124.3 | F29: 398452.95 | G29: 2030671.3 | H29: 0 | I29: 0 | J29: 2353895.9 | K29: 2353895.9 | L29: 323224.55 | M29: 2030671.3 | N29: 0 | O29: 323224.55 | P29: 75228.4 | Q29: 75228.4 | R29: 75228.4 | S29: 0 | T29: 0 | U29: 0 | V29: 0 | W29: 0 | X29: 0 | Y29: 0 | Z29: 0 | AA29: 0 | AB29: 100000 | AC29: 0 | AD29: 0 | AE29: 0 | AF29: 0 | AG29: 0 | AH29: 2030671.3 | AI29: 126690.73 | AJ29: 50981.14 | AK29: 0 | AL29: 0 | AM29: 0 | AN29: 0 | AO29: 0 | AP29: 0 | AQ29: 0 | AR29: 45552.68 | AS29: 0 | AT29: 0 | AU29: 0 | AV29: 0 | AW29: 0 | AX29: 0 | AY29: 0 | AZ29: 0 | BA29: 0 | BB29: 0 | BC29: 0 | BD29: 75228.4 | BE29: 0 | BF29: 0 | BG29: 0 | BH29: 0 | BI29: 0 | BJ29: 0 | BK29: 0 | BL29: 0 | BM29: 0 | BN29: 0 | BO29: 0 | BP29: 0 | BQ29: 0 | BR29: 0 | BS29: 0 | BT29: 0 | BU29: 0 | BV29: 0 | BW29: 0 | BX29: 0
C30: INVERSIONES A VALOR RAZONABLE CON CAMBIOS EN EL ORI ENTREGADOS EN OPERACIONES DE MERCADO MONETARIO - INSTRUMENTOS DE PATRIMONIO | D30: 0 | E30: 0 | F30: 0 | G30: 0 | H30: 0 | I30: 0 | J30: 0 | K30: 0 | L30: 0 | M30: 0 | N30: 0 | O30: 0 | P30: 0 | Q30: 0 | R30: 0 | S30: 0 | T30: 0 | U30: 0 | V30: 0 | W30: 0 | X30: 0 | Y30: 0 | Z30: 0 | AA30: 0 | AB30: 0 | AC30: 0 | AD30: 0 | AE30: 0 | AF30: 0 | AG30: 0 | AH30: 0 | AI30: 0 | AJ30: 0 | AK30: 0 | AL30: 0 | AM30: 0 | AN30: 0 | AO30: 0 | AP30: 0 | AQ30: 0 | AR30: 0 | AS30: 0 | AT30: 0 | AU30: 0 | AV30: 0 | AW30: 0 | AX30: 0 | AY30: 0 | AZ30: 0 | BA30: 0 | BB30: 0 | BC30: 0 | BD30: 0 | BE30: 0 | BF30: 0 | BG30: 0 | BH30: 0 | BI30: 0 | BJ30: 0 | BK30: 0 | BL30: 0 | BM30: 0 | BN30: 0 | BO30: 0 | BP30: 0 | BQ30: 0 | BR30: 0 | BS30: 0 | BT30: 0 | BU30: 0 | BV30: 0 | BW30: 0 | BX30: 0
C31: INVERSIONES A VALOR RAZONABLE CON CAMBIOS EN RESULTADOS ENTREGADAS EN GARANTÍA DE OPERACIONES CON INSTRUMENTOS DERIVADOS - INSTRUMENTOS REPRESENTATIVOS DE DEUDA | D31: 930369.98 | E31: 821161.2 | F31: 548116.39 | G31: 273044.81 | H31: 109208.78 | I31: 0 | J31: 925794.53 | K31: 816585.75 | L31: 543540.94 | M31: 273044.81 | N31: 109208.78 | O31: 652749.72 | P31: 4575.45 | Q31: 4575.45 | R31: 4575.45 | S31: 0 | T31: 0 | U31: 0 | V31: 0 | W31: 0 | X31: 0 | Y31: 0 | Z31: 0 | AA31: 0 | AB31: 0 | AC31: 0 | AD31: 5322.6 | AE31: 543540.94 | AF31: 11154.5 | AG31: 0 | AH31: 0 | AI31: 0 | AJ31: 0 | AK31: 0 | AL31: 55491.82 | AM31: 109208.78 | AN31: 0 | AO31: 0 | AP31: 0 | AQ31: 0 | AR31: 0 | AS31: 0 | AT31: 0 | AU31: 0 | AV31: 0 | AW31: 0 | AX31: 0 | AY31: 0 | AZ31: 0 | BA31: 201075.89 | BB31: 0 | BC31: 0 | BD31: 4575.45 | BE31: 0 | BF31: 0 | BG31: 0 | BH31: 0 | BI31: 0 | BJ31: 0 | BK31: 0 | BL31: 0 | BM31: 0 | BN31: 0 | BO31: 0 | BP31: 0 | BQ31: 0 | BR31: 0 | BS31: 0 | BT31: 0 | BU31: 0 | BV31: 0 | BW31: 0 | BX31: 0
C32: INVERSIONES A VALOR RAZONABLE CON CAMBIOS EN RESULTADOS ENTREGADOS EN GARANTÍA DE OPERACIONES CON INSTRUMENTOS DERIVADOS - INSTRUMENTOS DE PATRIMONIO | D32: 0 | E32: 0 | F32: 0 | G32: 0 | H32: 0 | I32: 0 | J32: 0 | K32: 0 | L32: 0 | M32: 0 | N32: 0 | O32: 0 | P32: 0 | Q32: 0 | R32: 0 | S32: 0 | T32: 0 | U32: 0 | V32: 0 | W32: 0 | X32: 0 | Y32: 0 | Z32: 0 | AA32: 0 | AB32: 0 | AC32: 0 | AD32: 0 | AE32: 0 | AF32: 0 | AG32: 0 | AH32: 0 | AI32: 0 | AJ32: 0 | AK32: 0 | AL32: 0 | AM32: 0 | AN32: 0 | AO32: 0 | AP32: 0 | AQ32: 0 | AR32: 0 | AS32: 0 | AT32: 0 | AU32: 0 | AV32: 0 | AW32: 0 | AX32: 0 | AY32: 0 | AZ32: 0 | BA32: 0 | BB32: 0 | BC32: 0 | BD32: 0 | BE32: 0 | BF32: 0 | BG32: 0 | BH32: 0 | BI32: 0 | BJ32: 0 | BK32: 0 | BL32: 0 | BM32: 0 | BN32: 0 | BO32: 0 | BP32: 0 | BQ32: 0 | BR32: 0 | BS32: 0 | BT32: 0 | BU32: 0 | BV32: 0 | BW32: 0 | BX32: 0
C33: INVERSIONES A COSTO AMORTIZADO CON CAMBIOS EN RESULTADOS ENTREGADOS EN GARANTÍA DE OPERACIONES CON INSTRUMENTOS DERIVADOS - INSTRUMENTOS REPRESENTATIVOS DE DEUDA | D33: 99872.16 | E33: 64317.65 | F33: 0 | G33: 64317.65 | H33: 35554.51 | I33: 0 | J33: 99872.16 | K33: 64317.65 | L33: 0 | M33: 64317.65 | N33: 35554.51 | O33: 35554.51 | P33: 0 | Q33: 0 | R33: 0 | S33: 0 | T33: 0 | U33: 0 | V33: 0 | W33: 0 | X33: 0 | Y33: 0 | Z33: 0 | AA33: 0 | AB33: 0 | AC33: 0 | AD33: 0 | AE33: 0 | AF33: 0 | AG33: 0 | AH33: 0 | AI33: 0 | AJ33: 0 | AK33: 0 | AL33: 0 | AM33: 35554.51 | AN33: 0 | AO33: 0 | AP33: 0 | AQ33: 0 | AR33: 0 | AS33: 0 | AT33: 0 | AU33: 0 | AV33: 0 | AW33: 64317.65 | AX33: 0 | AY33: 0 | AZ33: 0 | BA33: 0 | BB33: 0 | BC33: 0 | BD33: 0 | BE33: 0 | BF33: 0 | BG33: 0 | BH33: 0 | BI33: 0 | BJ33: 0 | BK33: 0 | BL33: 0 | BM33: 0 | BN33: 0 | BO33: 0 | BP33: 0 | BQ33: 0 | BR33: 0 | BS33: 0 | BT33: 0 | BU33: 0 | BV33: 0 | BW33: 0 | BX33: 0
C34: INVERSIONES A VALOR RAZONABLE CON CAMBIOS EN EL ORI ENTREGADOS EN GARANTÍA DE OPERACIONES CON INSTRUMENTOS DERIVADOS - INSTRUMENTOS DE PATRIMONIO | D34: 0 | E34: 0 | F34: 0 | G34: 0 | H34: 0 | I34: 0 | J34: 0 | K34: 0 | L34: 0 | M34: 0 | N34: 0 | O34: 0 | P34: 0 | Q34: 0 | R34: 0 | S34: 0 | T34: 0 | U34: 0 | V34: 0 | W34: 0 | X34: 0 | Y34: 0 | Z34: 0 | AA34: 0 | AB34: 0 | AC34: 0 | AD34: 0 | AE34: 0 | AF34: 0 | AG34: 0 | AH34: 0 | AI34: 0 | AJ34: 0 | AK34: 0 | AL34: 0 | AM34: 0 | AN34: 0 | AO34: 0 | AP34: 0 | AQ34: 0 | AR34: 0 | AS34: 0 | AT34: 0 | AU34: 0 | AV34: 0 | AW34: 0 | AX34: 0 | AY34: 0 | AZ34: 0 | BA34: 0 | BB34: 0 | BC34: 0 | BD34: 0 | BE34: 0 | BF34: 0 | BG34: 0 | BH34: 0 | BI34: 0 | BJ34: 0 | BK34: 0 | BL34: 0 | BM34: 0 | BN34: 0 | BO34: 0 | BP34: 0 | BQ34: 0 | BR34: 0 | BS34: 0 | BT34: 0 | BU34: 0 | BV34: 0 | BW34: 0 | BX34: 0
... C63: DETERIORO EN INVERSIONES A VALOR RAZONABLE | D63: 125824.87 | E63: 125608.44 | F63: 125608.44 | G63: 0 | H63: 0 | I63: 216.43 | J63: 24857.29 | K63: 24857.29 | L63: 24857.29 | M63: 0 | N63: 0 | O63: 24857.29 | P63: 100751.15 | Q63: 100751.15 | R63: 100751.15 | S63: 0 | T63: 0 | U63: 0 | V63: 0 | W63: 0 | X63: 0 | Y63: 0 | Z63: 0 | AA63: 216.43 | AB63: 23631.88 | AC63: 689.97 | AD63: 0 | AE63: 0 | AF63: 0 | AG63: 0 | AH63: 0 | AI63: 423.62 | AJ63: 0 | AK63: 0 | AL63: 0 | AM63: 0 | AN63: 0 | AO63: 0 | AP63: 0 | AQ63: 0 | AR63: 0 | AS63: 0 | AT63: 0 | AU63: 0 | AV63: 111.82 | AW63: 0 | AX63: 0 | AY63: 0 | AZ63: 0 | BA63: 0 | BB63: 0 | BC63: 0 | BD63: 100751.15 | BE63: 0 | BF63: 0 | BG63: 0 | BH63: 0 | BI63: 0 | BJ63: 0 | BK63: 0 | BL63: 0 | BM63: 0 | BN63: 0 | BO63: 0 | BP63: 0 | BQ63: 0 | BR63: 0 | BS63: 0 | BT63: 0 | BU63: 0 | BV63: 0 | BW63: 35 | BX63: 181.43
B64: CARTERA DE CREDITOS Y OPERACIONES DE LEASING | D64: 5.2881346e+08 | E64: 5.1132506e+08 | F64: 3.8078307e+08 | G64: 1.3054199e+08 | H64: 14175668 | I64: 3312734.2 | J64: 5.1458786e+08 | K64: 5.0041219e+08 | L64: 3.7480975e+08 | M64: 1.2560245e+08 | N64: 14175668 | O64: 3.8898541e+08 | P64: 0 | Q64: 0 | R64: 0 | S64: 0 | T64: 10912869 | U64: 5973327.4 | V64: 4939541.8 | W64: 10912869 | X64: 10912869 | Y64: 5973327.4 | Z64: 4939541.8 | AA64: 3312734.2 | AB64: 60344884 | AC64: 21340077 | AD64: 19809785 | AE64: 1.356714e+08 | AF64: 2686371.6 | AG64: 10515136 | AH64: 54191676 | AI64: 32044982 | AJ64: 11715250 | AK64: 85649331 | AL64: 28178938 | AM64: 14175668 | AN64: 12181127 | AO64: 1459202.7 | AP64: 1543544.6 | AQ64: 1342563.1 | AR64: 3758155.5 | AS64: 2400027.4 | AT64: 4801338.4 | AU64: 2201930.4 | AV64: 826290.59 | AW64: 3181224.8 | AX64: 1873241.4 | AY64: 985202.59 | AZ64: 1674448.5 | BA64: 36044.97 | BB64: 12.63 | BC64: 0 | BD64: 0 | BE64: 0 | BF64: 0 | BG64: 0 | BH64: 0 | BI64: 457792.69 | BJ64: 3105577.3 | BK64: 1751624.3 | BL64: 612233 | BM64: 362063.33 | BN64: 523585.29 | BO64: 356294.22 | BP64: 284933.61 | BQ64: 912075.78 | BR64: 2546689.6 | BS64: 0 | BT64: 376601.61 | BU64: 969029.11 | BV64: 247169.47 | BW64: 744072.5 | BX64: 975861.53
C65: CARTERA DE CREDITOS | D65: 5.6576322e+08 | E65: 5.4656803e+08 | F65: 4.0830002e+08 | G65: 1.3826801e+08 | H65: 15487799 | I65: 3707387.5 | J65: 5.5020427e+08 | K65: 5.3471648e+08 | L65: 4.0165232e+08 | M65: 1.3306416e+08 | N65: 15487799 | O65: 4.1714011e+08 | P65: 0 | Q65: 0 | R65: 0 | S65: 0 | T65: 11851555 | U65: 6647705.8 | V65: 5203849.5 | W65: 11851555 | X65: 11851555 | Y65: 6647705.8 | Z65: 5203849.5 | AA65: 3707387.5 | AB65: 64792731 | AC65: 22546234 | AD65: 21283364 | AE65: 1.4676048e+08 | AF65: 2720195.2 | AG65: 10947792 | AH65: 57632221 | AI65: 34208817 | AJ65: 12448223 | AK65: 90903256 | AL65: 29678746 | AM65: 15487799 | AN65: 12827816 | AO65: 1551733.9 | AP65: 1645477.7 | AQ65: 1511073.8 | AR65: 4024717.3 | AS65: 2632881.3 | AT65: 5122428.2 | AU65: 2379390 | AV65: 855119.78 | AW65: 3263524.1 | AX65: 2010134.6 | AY65: 1079277.4 | AZ65: 1854327.5 | BA65: 36500 | BB65: 13 | BC65: 0 | BD65: 0 | BE65: 0 | BF65: 0 | BG65: 0 | BH65: 0 | BI65: 500127.15 | BJ65: 3614824.8 | BK65: 1840505.9 | BL65: 637083.48 | BM65: 399620.16 | BN65: 539132.68 | BO65: 389279 | BP65: 296270.87 | BQ65: 956917.46 | BR65: 2677793.7 | BS65: 0 | BT65: 429056.65 | BU65: 1190075.3 | BV65: 262431.46 | BW65: 796149.98 | BX65: 1029674.1
C66: CARTERA Y OPERACIONES DE LEASING COMERCIALES | D66: 2.8608012e+08 | E66: 2.7815846e+08 | F66: 2.175754e+08 | G66: 60583064 | H66: 7342607.1 | I66: 579046.85 | J66: 2.8380355e+08 | K66: 2.7646094e+08 | L66: 2.1685043e+08 | M66: 59610515 | N66: 7342607.1 | O66: 2.2419303e+08 | P66: 0 | Q66: 0 | R66: 0 | S66: 0 | T66: 1697524.3 | U66: 724975.55 | V66: 972548.77 | W66: 1697524.3 | X66: 1697524.3 | Y66: 724975.55 | Z66: 972548.77 | AA66: 579046.85 | AB66: 44003638 | AC66: 6287127.7 | AD66: 13302764 | AE66: 95918912 | AF66: 2720195.2 | AG66: 5407122 | AH66: 22216442 | AI66: 23381461 | AJ66: 2133729.7 | AK66: 39313210 | AL66: 12670785 | AM66: 7342607.1 | AN66: 2716622.1 | AO66: 88858.63 | AP66: 122324.13 | AQ66: 149903.85 | AR66: 635726.75 | AS66: 260054.81 | AT66: 0 | AU66: 651451.68 | AV66: 733112.4 | AW66: 2605256.1 | AX66: 246432.21 | AY66: 234655.11 | AZ66: 624657.09 | BA66: 36500 | BB66: 0 | BC66: 0 | BD66: 0 | BE66: 0 | BF66: 0 | BG66: 0 | BH66: 0 | BI66: 21216.29 | BJ66: 0 | BK66: 552680.78 | BL66: 424797.75 | BM66: 202164.36 | BN66: 1974.92 | BO66: 64525.07 | BP66: 0 | BQ66: 74822.23 | BR66: 355342.92 | BS66: 0 | BT66: 144582.58 | BU66: 79753.5 | BV66: 65445.69 | BW66: 48884.6 | BX66: 240380.48
C67: CARTERA Y OPERACIONES DE LEASING DE CONSUMO | D67: 1.8086569e+08 | E67: 1.7735147e+08 | F67: 1.2335223e+08 | G67: 53999245 | H67: 1203868.6 | I67: 2310345 | J67: 1.6960284e+08 | K67: 1.6839897e+08 | L67: 1.180616e+08 | M67: 50337376 | N67: 1203868.6 | O67: 1.1926546e+08 | P67: 0 | Q67: 0 | R67: 0 | S67: 0 | T67: 8952502.9 | U67: 5290633.8 | V67: 3661869 | W67: 8952502.9 | X67: 8952502.9 | Y67: 5290633.8 | Z67: 3661869 | AA67: 2310345 | AB67: 14907105 | AC67: 15084895 | AD67: 4566209.4 | AE67: 33819776 | AF67: 0 | AG67: 5501893 | AH67: 21851433 | AI67: 8745518 | AJ67: 3191251.3 | AK67: 27395483 | AL67: 10909206 | AM67: 1203868.6 | AN67: 7617007.1 | AO67: 1330743.6 | AP67: 8206.64 | AQ67: 72461.96 | AR67: 1960332.6 | AS67: 2371888.2 | AT67: 5122428.2 | AU67: 1727938.4 | AV67: 110822.3 | AW67: 658268 | AX67: 208401.27 | AY67: 8020.17 | AZ67: 1229670.4 | BA67: 0 | BB67: 13 | BC67: 0 | BD67: 0 | BE67: 0 | BF67: 0 | BG67: 0 | BH67: 0 | BI67: 385872.15 | BJ67: 3614824.8 | BK67: 1287825.2 | BL67: 209271.63 | BM67: 197455.8 | BN67: 1114.2 | BO67: 241.36 | BP67: 51351.75 | BQ67: 882095.23 | BR67: 2322450.8 | BS67: 0 | BT67: 162741.22 | BU67: 1002615.7 | BV67: 162342.91 | BW67: 646687.16 | BX67: 335958.09
C68: CARTERA Y LEASING DE MICROCRÉDITOS | D68: 14552533 | E68: 7342627 | F68: 7018112.9 | G68: 324514.08 | H68: 6865179.8 | I68: 344725.81 | J68: 13883294 | K68: 7018114.4 | L68: 7018112.9 | M68: 1.51 | N68: 6865179.8 | O68: 13883293 | P68: 0 | Q68: 0 | R68: 0 | S68: 0 | T68: 324512.57 | U68: 0 | V68: 324512.57 | W68: 324512.57 | X68: 324512.57 | Y68: 0 | Z68: 324512.57 | AA68: 344725.81 | AB68: 272654.37 | AC68: 2792.73 | AD68: 0 | AE68: 635056.98 | AF68: 0 | AG68: 0 | AH68: 1.51 | AI68: 0 | AJ68: 827916.08 | AK68: 5041.23 | AL68: 0 | AM68: 6865179.8 | AN68: 212.18 | AO68: 132131.63 | AP68: 1498383.4 | AQ68: 1288708 | AR68: 0 | AS68: 28.79 | AT68: 0 | AU68: 0 | AV68: 11185.08 | AW68: 0 | AX68: 1555301.1 | AY68: 788701.35 | AZ68: 0 | BA68: 0 | BB68: 0 | BC68: 0 | BD68: 0 | BE68: 0 | BF68: 0 | BG68: 0 | BH68: 0 | BI68: 0 | BJ68: 0 | BK68: 0 | BL68: 0 | BM68: 0 | BN68: 0 | BO68: 324512.57 | BP68: 0 | BQ68: 0 | BR68: 0 | BS68: 0 | BT68: 109880.36 | BU68: 107599.47 | BV68: 2605.72 | BW68: 22900.95 | BX68: 101739.31
C69: CARTERA DE VIVIENDA Y OPERACIONES DE LEASING HABITACIONAL | D69: 84264878 | E69: 83715466 | F69: 60354278 | G69: 23361187 | H69: 76143.1 | I69: 473269.77 | J69: 82914593 | K69: 82838450 | L69: 59722182 | M69: 23116268 | N69: 76143.1 | O69: 59798325 | P69: 0 | Q69: 0 | R69: 0 | S69: 0 | T69: 877015.49 | U69: 632096.37 | V69: 244919.12 | W69: 877015.49 | X69: 877015.49 | Y69: 632096.37 | Z69: 244919.12 | AA69: 473269.77 | AB69: 5609334 | AC69: 1171418.6 | AD69: 3414391.2 | AE69: 16386739 | AF69: 0 | AG69: 38776.75 | AH69: 13564344 | AI69: 2081837.2 | AJ69: 6295326 | AK69: 24189521 | AL69: 6098756.2 | AM69: 76143.1 | AN69: 2493974.3 | AO69: 0 | AP69: 16563.49 | AQ69: 0 | AR69: 1428658 | AS69: 909.5 | AT69: 0 | AU69: 0 | AV69: 0 | AW69: 0 | AX69: 0 | AY69: 47900.72 | AZ69: 0 | BA69: 0 | BB69: 0 | BC69: 0 | BD69: 0 | BE69: 0 | BF69: 0 | BG69: 0 | BH69: 0 | BI69: 93038.71 | BJ69: 0 | BK69: 0 | BL69: 3014.1 | BM69: 0 | BN69: 536043.56 | BO69: 0 | BP69: 244919.12 | BQ69: 0 | BR69: 0 | BS69: 0 | BT69: 11852.49 | BU69: 106.64 | BV69: 32037.14 | BW69: 77677.27 | BX69: 351596.23
C70: DETERIORO | D70: 32709636 | E70: 31152050 | F70: 24375103 | G70: 6776946.4 | H70: 1224160.2 | I70: 333426.02 | J70: 31578331 | K70: 30354171 | L70: 23787881 | M70: 6566289.6 | N70: 1224160.2 | O70: 25012041 | P70: 0 | Q70: 0 | R70: 0 | S70: 0 | T70: 797879.07 | U70: 587222.23 | V70: 210656.84 | W70: 797879.07 | X70: 797879.07 | Y70: 587222.23 | Z70: 210656.84 | AA70: 333426.02 | AB70: 4022363.7 | AC70: 987401.85 | AD70: 1319801.7 | AE70: 9981202 | AF70: 27469.84 | AG70: 329044.34 | AH70: 2994822.5 | AI70: 1886656.4 | AJ70: 675555.48 | AK70: 4585211.8 | AL70: 1448765 | AM70: 1224160.2 | AN70: 530494.86 | AO70: 70956.2 | AP70: 99944.84 | AQ70: 164879.03 | AR70: 219938.49 | AS70: 169653.8 | AT70: 235340.7 | AU70: 147496.44 | AV70: 20645.85 | AW70: 63231.16 | AX70: 130684.96 | AY70: 90191.48 | AZ70: 152100.16 | BA70: 317.9 | BB70: 0.2 | BC70: 0 | BD70: 0 | BE70: 0 | BF70: 0 | BG70: 0 | BH70: 0 | BI70: 36652.85 | BJ70: 441574.85 | BK70: 75689.44 | BL70: 23163.81 | BM70: 31770.5 | BN70: 15515.53 | BO70: 32004.97 | BP70: 10113.3 | BQ70: 38544.69 | BR70: 92849.13 | BS70: 0 | BT70: 47938.28 | BU70: 182311.94 | BV70: 12184.03 | BW70: 43518.79 | BX70: 47472.98
C71: DETERIORO (DETERIORO) CRÉDITOS Y OPERACIONES DE LEASING COMERCIALES | D71: 16005194 | E71: 15157369 | F71: 12553098 | G71: 2604271.3 | H71: 797968.6 | I71: 49856.04 | J71: 15872729 | K71: 15074760 | L71: 12508183 | M71: 2566577.7 | N71: 797968.6 | O71: 13306151 | P71: 0 | Q71: 0 | R71: 0 | S71: 0 | T71: 82609.11 | U71: 44915.58 | V71: 37693.53 | W71: 82609.11 | X71: 82609.11 | Y71: 44915.58 | Z71: 37693.53 | AA71: 49856.04 | AB71: 2477973.8 | AC71: 262684.48 | AD71: 814405.52 | AE71: 5814977.3 | AF71: 21480.26 | AG71: 154185.37 | AH71: 806680.36 | AI71: 1120671.5 | AJ71: 140126.08 | AK71: 2461950.3 | AL71: 709003.5 | AM71: 797968.6 | AN71: 75242.41 | AO71: 11547.73 | AP71: 6242.71 | AQ71: 18251.13 | AR71: 29174.97 | AS71: 16266.23 | AT71: 0 | AU71: 22195.6 | AV71: 13379.67 | AW71: 38309.22 | AX71: 11221.78 | AY71: 11465.75 | AZ71: 37006.61 | BA71: 317.9 | BB71: 0 | BC71: 0 | BD71: 0 | BE71: 0 | BF71: 0 | BG71: 0 | BH71: 0 | BI71: 2690.54 | BJ71: 0 | BK71: 18840.22 | BL71: 15755.38 | BM71: 21727.65 | BN71: 17.7 | BO71: 5027.12 | BP71: 0 | BQ71: 4724.31 | BR71: 13826.19 | BS71: 0 | BT71: 12882.18 | BU71: 20702.8 | BV71: 2214.54 | BW71: 8030.79 | BX71: 6025.73
C72: DETERIORO (DETERIORO) CARTERA Y OPERACIONES DE LEASING DE CONSUMO | D72: 10645922 | E72: 10390221 | F72: 7294482.5 | G72: 3095738.1 | H72: 61892.18 | I72: 193808.86 | J72: 9792948 | K72: 9731055.8 | L72: 6770602.1 | M72: 2960453.7 | N72: 61892.18 | O72: 6832494.3 | P72: 0 | Q72: 0 | R72: 0 | S72: 0 | T72: 659164.78 | U72: 523880.45 | V72: 135284.33 | W72: 659164.78 | X72: 659164.78 | Y72: 523880.45 | Z72: 135284.33 | AA72: 193808.86 | AB72: 895014.28 | AC72: 608500.75 | AD72: 260017.21 | AE72: 2452515.4 | AF72: 0 | AG72: 173612.02 | AH72: 1661512.8 | AI72: 384208.66 | AJ72: 149893.77 | AK72: 1450959.8 | AL72: 490247.27 | AM72: 61892.18 | AN72: 341787.92 | AO72: 45245.61 | AP72: 551.73 | AQ72: 5739.9 | AR72: 150540.88 | AS72: 153376.74 | AT72: 235340.7 | AU72: 125300.84 | AV72: 6284.68 | AW72: 14422.86 | AX72: 9976.17 | AY72: 912.09 | AZ72: 115093.55 | BA72: 0 | BB72: 0.2 | BC72: 0 | BD72: 0 | BE72: 0 | BF72: 0 | BG72: 0 | BH72: 0 | BI72: 31160.41 | BJ72: 441574.85 | BK72: 52529.22 | BL72: 7160.85 | BM72: 10042.85 | BN72: 121.11 | BO72: 59.26 | BP72: 3672.91 | BQ72: 33820.38 | BR72: 79022.94 | BS72: 0 | BT72: 18819.28 | BU72: 120838.08 | BV72: 5193.82 | BW72: 27478.15 | BX72: 21479.53
C73: DETERIORO (DETERIORO) MICROCRÉDITOS | D73: 1003557.6 | E73: 578617.37 | F73: 551697.25 | G73: 26920.12 | H73: 361507.54 | I73: 63432.74 | J73: 913206.32 | K73: 551698.78 | L73: 551697.25 | M73: 1.53 | N73: 361507.54 | O73: 913204.79 | P73: 0 | Q73: 0 | R73: 0 | S73: 0 | T73: 26918.59 | U73: 0 | V73: 26918.59 | W73: 26918.59 | X73: 26918.59 | Y73: 0 | Z73: 26918.59 | AA73: 63432.74 | AB73: 61480.46 | AC73: 232.15 | AD73: 0 | AE73: 86944.8 | AF73: 0 | AG73: 0 | AH73: 1.53 | AI73: 0 | AJ73: 53581.12 | AK73: 815.08 | AL73: 0 | AM73: 361507.54 | AN73: 28.26 | AO73: 14162.86 | AP73: 78595.55 | AQ73: 107348.53 | AR73: 0 | AS73: 1.73 | AT73: 0 | AU73: 0 | AV73: 981.5 | AW73: 0 | AX73: 109487.01 | AY73: 38038.2 | AZ73: 0 | BA73: 0 | BB73: 0 | BC73: 0 | BD73: 0 | BE73: 0 | BF73: 0 | BG73: 0 | BH73: 0 | BI73: 0 | BJ73: 0 | BK73: 0 | BL73: 0 | BM73: 0 | BN73: 0 | BO73: 26918.59 | BP73: 0 | BQ73: 0 | BR73: 0 | BS73: 0 | BT73: 12326.78 | BU73: 40768.92 | BV73: 100.4 | BW73: 1788.25 | BX73: 8448.39
C74: DETERIORO (DETERIORO) CARTERA DE VIVIENDA Y LEASING HABITACIONAL | D74: 3057335 | E74: 3041829 | F74: 2212162.9 | G74: 829666.04 | H74: 2791.84 | I74: 12714.19 | J74: 3020928 | K74: 3018136.2 | L74: 2194910.5 | M74: 823225.65 | N74: 2791.84 | O74: 2197702.3 | P74: 0 | Q74: 0 | R74: 0 | S74: 0 | T74: 23692.8 | U74: 17252.41 | V74: 6440.39 | W74: 23692.8 | X74: 23692.8 | Y74: 17252.41 | Z74: 6440.39 | AA74: 12714.19 | AB74: 148105.33 | AC74: 31584.47 | AD74: 113079.01 | AE74: 836201.07 | AF74: 0 | AG74: 1246.95 | AH74: 526627.75 | AI74: 62425.27 | AJ74: 331954.51 | AK74: 671486.62 | AL74: 182271.94 | AM74: 2791.84 | AN74: 71367.31 | AO74: 0 | AP74: 339.74 | AQ74: 0 | AR74: 40222.64 | AS74: 9.1 | AT74: 0 | AU74: 0 | AV74: 0 | AW74: 0 | AX74: 0 | AY74: 1214.44 | AZ74: 0 | BA74: 0 | BB74: 0 | BC74: 0 | BD74: 0 | BE74: 0 | BF74: 0 | BG74: 0 | BH74: 0 | BI74: 2801.9 | BJ74: 0 | BK74: 0 | BL74: 247.58 | BM74: 0 | BN74: 14202.93 | BO74: 0 | BP74: 6440.39 | BQ74: 0 | BR74: 0 | BS74: 0 | BT74: 250.04 | BU74: 2.14 | BV74: 785.77 | BW74: 1472.91 | BX74: 10203.33
C75: OTROS DETERIOROS | D75: 1997627.7 | E75: 1984013.5 | F75: 1763662.5 | G75: 220350.95 | H75: 0 | I75: 13614.19 | J75: 1978519.7 | K75: 1978519.7 | L75: 1762488.7 | M75: 216030.95 | N75: 0 | O75: 1762488.7 | P75: 0 | Q75: 0 | R75: 0 | S75: 0 | T75: 5493.79 | U75: 1173.79 | V75: 4320 | W75: 5493.79 | X75: 5493.79 | Y75: 1173.79 | Z75: 4320 | AA75: 13614.19 | AB75: 439789.76 | AC75: 84400 | AD75: 132300 | AE75: 790563.45 | AF75: 5989.58 | AG75: 0 | AH75: 0 | AI75: 319350.98 | AJ75: 0 | AK75: 0 | AL75: 67242.29 | AM75: 0 | AN75: 42068.96 | AO75: 0 | AP75: 14215.11 | AQ75: 33539.47 | AR75: 0 | AS75: 0 | AT75: 0 | AU75: 0 | AV75: 0 | AW75: 10499.08 | AX75: 0 | AY75: 38561 | AZ75: 0 | BA75: 0 | BB75: 0 | BC75: 0 | BD75: 0 | BE75: 0 | BF75: 0 | BG75: 0 | BH75: 0 | BI75: 0 | BJ75: 0 | BK75: 4320 | BL75: 0 | BM75: 0 | BN75: 1173.79 | BO75: 0 | BP75: 0 | BQ75: 0 | BR75: 0 | BS75: 0 | BT75: 3660 | BU75: 0 | BV75: 3889.5 | BW75: 4748.69 | BX75: 1316
C76: DETERIORO COMPONENTE CONTRACICLICO | D76: 4240118.7 | E76: 4090921.4 | F76: 3141845.2 | G76: 949076.16 | H76: 87970.07 | I76: 61227.23 | J76: 4038084.5 | K76: 3950114.4 | L76: 3054689.1 | M76: 895425.26 | N76: 87970.07 | O76: 3142659.2 | P76: 0 | Q76: 0 | R76: 0 | S76: 0 | T76: 140807.03 | U76: 87156.13 | V76: 53650.9 | W76: 140807.03 | X76: 140807.03 | Y76: 87156.13 | Z76: 53650.9 | AA76: 61227.23 | AB76: 425483.92 | AC76: 218754.46 | AD76: 153777.46 | AE76: 1107876.7 | AF76: 6353.74 | AG76: 103610.86 | AH76: 445722.17 | AI76: 277178.55 | AJ76: 57417.46 | AK76: 668712.5 | AL76: 51043.51 | AM76: 87970.07 | AN76: 116193.53 | AO76: 21574.95 | AP76: 1988.26 | AQ76: 3631.66 | AR76: 46623.25 | AS76: 63200.08 | AT76: 85749.09 | AU76: 29963.16 | AV76: 8183.34 | AW76: 19068.14 | AX76: 6208.19 | AY76: 3883.28 | AZ76: 27778.86 | BA76: 137.13 | BB76: 0.17 | BC76: 0 | BD76: 0 | BE76: 0 | BF76: 0 | BG76: 0 | BH76: 0 | BI76: 5681.61 | BJ76: 67672.67 | BK76: 13192.16 | BL76: 1686.67 | BM76: 5786.33 | BN76: 31.86 | BO76: 979.81 | BP76: 1223.96 | BQ76: 6296.99 | BR76: 38254.97 | BS76: 0 | BT76: 4516.76 | BU76: 38734.22 | BV76: 3077.96 | BW76: 8558.69 | BX76: 6339.6
... C78: CRÉDITOS Y OPERACIONES DE LEASING COMERCIALES | D78: 1602414.9 | E78: 1523461.6 | F78: 1248898 | G78: 274563.61 | H78: 69469.08 | I78: 9484.26 | J78: 1580095.4 | K78: 1510626.3 | L78: 1244442.2 | M78: 266184.12 | N78: 69469.08 | O78: 1313911.3 | P78: 0 | Q78: 0 | R78: 0 | S78: 0 | T78: 12835.24 | U78: 4455.75 | V78: 8379.49 | W78: 12835.24 | X78: 12835.24 | Y78: 4455.75 | Z78: 8379.49 | AA78: 9484.26 | AB78: 213241.54 | AC78: 29624.44 | AD78: 81390.78 | AE78: 566159.45 | AF78: 6353.74 | AG78: 24430.4 | AH78: 125105.9 | AI78: 143333.26 | AJ78: 13563.8 | AK78: 231058.37 | AL78: 11282.49 | AM78: 69469.08 | AN78: 12388.81 | AO78: 1228.98 | AP78: 1822.09 | AQ78: 2517.52 | AR78: 4100.15 | AS78: 7103.09 | AT78: 0 | AU78: 6527.78 | AV78: 6214.46 | AW78: 10955.9 | AX78: 3211.81 | AY78: 3730.32 | AZ78: 5144.12 | BA78: 137.13 | BB78: 0 | BC78: 0 | BD78: 0 | BE78: 0 | BF78: 0 | BG78: 0 | BH78: 0 | BI78: 271.18 | BJ78: 0 | BK78: 3400.44 | BL78: 1129.43 | BM78: 2543.55 | BN78: 10.36 | BO78: 972.54 | BP78: 0 | BQ78: 501.23 | BR78: 4006.51 | BS78: 0 | BT78: 1993.18 | BU78: 4686.4 | BV78: 687.28 | BW78: 245.74 | BX78: 1871.66
B79: OTROS ACTIVOS | D79: 48216951 | E79: 46897840 | F79: 36412546 | G79: 10485294 | H79: 1083019.3 | I79: 236092.13 | J79: 46277430 | K79: 45194410 | L79: 35218526 | M79: 9975884.3 | N79: 1083019.3 | O79: 36301545 | P79: 575030.48 | Q79: 575030.48 | R79: 504111.88 | S79: 70918.6 | T79: 1128398.9 | U79: 689907.95 | V79: 438490.96 | W79: 1128398.9 | X79: 1128398.9 | Y79: 689907.95 | Z79: 438490.96 | AA79: 236092.13 | AB79: 6818893 | AC79: 1242263.4 | AD79: 1597777.9 | AE79: 14386207 | AF79: 174537.71 | AG79: 1234408.5 | AH79: 3488956.1 | AI79: 2133180.9 | AJ79: 1280367.9 | AK79: 6603700.2 | AL79: 2599894 | AM79: 1083019.3 | AN79: 966175.19 | AO79: 232023.3 | AP79: 289808.1 | AQ79: 367501.53 | AR79: 200144.67 | AS79: 63106.94 | AT79: 421953.53 | AU79: 202880.5 | AV79: 46685.79 | AW79: 210389.08 | AX79: 153438.81 | AY79: 191078.76 | AZ79: 130528.27 | BA79: 28896.36 | BB79: 113422.76 | BC79: 16190.54 | BD79: 399640.85 | BE79: 8118.01 | BF79: 70918.6 | BG79: 30129.85 | BH79: 66223.17 | BI79: 123385.33 | BJ79: 292862.33 | BK79: 163666.76 | BL79: 99090.55 | BM79: 88063.24 | BN79: 9651.73 | BO79: 63508.92 | BP79: 15672.52 | BQ79: 76854.77 | BR79: 191239.54 | BS79: 4403.22 | BT79: 49612.1 | BU79: 39287.39 | BV79: 19723.75 | BW79: 60018.13 | BX79: 67450.76
C80: CUENTAS POR COBRAR | D80: 22687497 | E80: 21958294 | F80: 16667471 | G80: 5290823.7 | H80: 637473.88 | I80: 91729 | J80: 21576307 | K80: 20938833 | L80: 15908450 | M80: 5030383.6 | N80: 637473.88 | O80: 16545924 | P80: 422466.74 | Q80: 422466.74 | R80: 373004.95 | S80: 49461.79 | T80: 596994.17 | U80: 386015.9 | V80: 210978.27 | W80: 596994.17 | X80: 596994.17 | Y80: 386015.9 | Z80: 210978.27 | AA80: 91729 | AB80: 3076539.5 | AC80: 381868.2 | AD80: 602319.55 | AE80: 6442170.2 | AF80: 49447.5 | AG80: 655568.14 | AH80: 2123668.8 | AI80: 795826.44 | AJ80: 549135.86 | AK80: 3726857.3 | AL80: 1146359.6 | AM80: 637473.88 | AN80: 303203.56 | AO80: 45933.79 | AP80: 120534.14 | AQ80: 116899.41 | AR80: 118343.95 | AS80: 38715.6 | AT80: 238088.28 | AU80: 70132.75 | AV80: 20367.84 | AW80: 140067.09 | AX80: 42753.01 | AY80: 64011.93 | AZ80: 62938.06 | BA80: 1953.09 | BB80: 2350.95 | BC80: 2778.75 | BD80: 298813.75 | BE80: 5045.99 | BF80: 49461.79 | BG80: 2929.83 | BH80: 66215.38 | BI80: 49424.52 | BJ80: 176445.45 | BK80: 94299.92 | BL80: 59312.81 | BM80: 45341.07 | BN80: 8845.91 | BO80: 43373.16 | BP80: 13296 | BQ80: 46646.14 | BR80: 59685.64 | BS80: 323.55 | BT80: 21177.38 | BU80: 14184.01 | BV80: 5548.57 | BW80: 18140.52 | BX80: 32678.52
C81: ACTIVOS NO CORRIENTES MANTENIDOS PARA LA VENTA | D81: 542027.21 | E81: 533286.17 | F81: 348781.62 | G81: 184504.55 | H81: 6352.62 | I81: 2388.42 | J81: 514496.52 | K81: 508143.9 | L81: 335076.58 | M81: 173067.32 | N81: 6352.62 | O81: 341429.2 | P81: 0 | Q81: 0 | R81: 0 | S81: 0 | T81: 25142.27 | U81: 13705.04 | V81: 11437.23 | W81: 25142.27 | X81: 25142.27 | Y81: 13705.04 | Z81: 11437.23 | AA81: 2388.42 | AB81: 19971.8 | AC81: 0 | AD81: 37056.48 | AE81: 135107.81 | AF81: 0 | AG81: 62786.58 | AH81: 58932.06 | AI81: 5378.24 | AJ81: 2061.92 | AK81: 159035.71 | AL81: 13282.9 | AM81: 6352.62 | AN81: 4927.45 | AO81: 953.52 | AP81: 0 | AQ81: 0 | AR81: 1751.88 | AS81: 3335.63 | AT81: 0 | AU81: 1009.3 | AV81: 898.14 | AW81: 0 | AX81: 0 | AY81: 0 | AZ81: 1654.48 | BA81: 0 | BB81: 0 | BC81: 0 | BD81: 0 | BE81: 0 | BF81: 0 | BG81: 0 | BH81: 0 | BI81: 3156.74 | BJ81: 0 | BK81: 6476.16 | BL81: 41.71 | BM81: 6975.32 | BN81: 40.77 | BO81: 120.41 | BP81: 41.4 | BQ81: 3490.5 | BR81: 4799.26 | BS81: 0 | BT81: 0 | BU81: 0 | BV81: 0 | BW81: 2388.42 | BX81: 0
C82: BIENES RECIBIDOS EN PAGO | D82: 593792.31 | E82: 558641.91 | F82: 234134.13 | G82: 324507.78 | H82: 34495.32 | I82: 655.08 | J82: 559919.07 | K82: 525423.75 | L82: 215133.32 | M82: 310290.43 | N82: 34495.32 | O82: 249628.64 | P82: 0 | Q82: 0 | R82: 0 | S82: 0 | T82: 33218.16 | U82: 19000.81 | V82: 14217.35 | W82: 33218.16 | X82: 33218.16 | Y82: 19000.81 | Z82: 14217.35 | AA82: 655.08 | AB82: 31396.77 | AC82: 0 | AD82: 79208.26 | AE82: 25268.84 | AF82: 0 | AG82: 178065.3 | AH82: 40022.16 | AI82: 0 | AJ82: 1951.39 | AK82: 129447.64 | AL82: 10773.34 | AM82: 34495.32 | AN82: 2237.36 | AO82: 1207.48 | AP82: 0 | AQ82: 0 | AR82: 12610.41 | AS82: 3079.18 | AT82: 0 | AU82: 2221.37 | AV82: 1651.92 | AW82: 0 | AX82: 0 | AY82: 0 | AZ82: 6282.33 | BA82: 0 | BB82: 0 | BC82: 0 | BD82: 0 | BE82: 0 | BF82: 0 | BG82: 0 | BH82: 0 | BI82: 4336.71 | BJ82: 0 | BK82: 7902.41 | BL82: 202.08 | BM82: 5599.56 | BN82: 58.12 | BO82: 602.04 | BP82: 108 | BQ82: 8804.34 | BR82: 5604.9 | BS82: 0 | BT82: 0 | BU82: 0 | BV82: 0 | BW82: 525.32 | BX82: 129.76
C83: BIENES RESTITUIDOS DE CONTRATOS DE LEASING | D83: 584076.75 | E83: 584076.75 | F83: 487633.57 | G83: 96443.18 | H83: 0 | I83: 0 | J83: 569583.74 | K83: 569583.74 | L83: 473140.56 | M83: 96443.18 | N83: 0 | O83: 473140.56 | P83: 0 | Q83: 0 | R83: 0 | S83: 0 | T83: 14493.01 | U83: 14493.01 | V83: 0 | W83: 14493.01 | X83: 14493.01 | Y83: 14493.01 | Z83: 0 | AA83: 0 | AB83: 19811.18 | AC83: 0 | AD83: 45638.2 | AE83: 404911.85 | AF83: 0 | AG83: 0 | AH83: 44637.37 | AI83: 0 | AJ83: 1276.47 | AK83: 44629.86 | AL83: 6061.19 | AM83: 0 | AN83: 0 | AO83: 0 | AP83: 0 | AQ83: 0 | AR83: 0 | AS83: 509.81 | AT83: 0 | AU83: 106.42 | AV83: 0 | AW83: 0 | AX83: 0 | AY83: 0 | AZ83: 2001.39 | BA83: 0 | BB83: 0 | BC83: 0 | BD83: 0 | BE83: 0 | BF83: 0 | BG83: 0 | BH83: 0 | BI83: 86.57 | BJ83: 0 | BK83: 0 | BL83: 0 | BM83: 14406.44 | BN83: 0 | BO83: 0 | BP83: 0 | BQ83: 0 | BR83: 0 | BS83: 0 | BT83: 0 | BU83: 0 | BV83: 0 | BW83: 0 | BX83: 0
C84: OPERACIONES DISCONTINUADAS | D84: 0 | E84: 0 | F84: 0 | G84: 0 | H84: 0 | I84: 0 | J84: 0 | K84: 0 | L84: 0 | M84: 0 | N84: 0 | O84: 0 | P84: 0 | Q84: 0 | R84: 0 | S84: 0 | T84: 0 | U84: 0 | V84: 0 | W84: 0 | X84: 0 | Y84: 0 | Z84: 0 | AA84: 0 | AB84: 0 | AC84: 0 | AD84: 0 | AE84: 0 | AF84: 0 | AG84: 0 | AH84: 0 | AI84: 0 | AJ84: 0 | AK84: 0 | AL84: 0 | AM84: 0 | AN84: 0 | AO84: 0 | AP84: 0 | AQ84: 0 | AR84: 0 | AS84: 0 | AT84: 0 | AU84: 0 | AV84: 0 | AW84: 0 | AX84: 0 | AY84: 0 | AZ84: 0 | BA84: 0 | BB84: 0 | BC84: 0 | BD84: 0 | BE84: 0 | BF84: 0 | BG84: 0 | BH84: 0 | BI84: 0 | BJ84: 0 | BK84: 0 | BL84: 0 | BM84: 0 | BN84: 0 | BO84: 0 | BP84: 0 | BQ84: 0 | BR84: 0 | BS84: 0 | BT84: 0 | BU84: 0 | BV84: 0 | BW84: 0 | BX84: 0
C85: ACTIVOS NO CORRIENTES MANTENIDOS PARA DISTRIBUIR A LOS PROPIETARIOS | D85: 0 | E85: 0 | F85: 0 | G85: 0 | H85: 0 | I85: 0 | J85: 0 | K85: 0 | L85: 0 | M85: 0 | N85: 0 | O85: 0 | P85: 0 | Q85: 0 | R85: 0 | S85: 0 | T85: 0 | U85: 0 | V85: 0 | W85: 0 | X85: 0 | Y85: 0 | Z85: 0 | AA85: 0 | AB85: 0 | AC85: 0 | AD85: 0 | AE85: 0 | AF85: 0 | AG85: 0 | AH85: 0 | AI85: 0 | AJ85: 0 | AK85: 0 | AL85: 0 | AM85: 0 | AN85: 0 | AO85: 0 | AP85: 0 | AQ85: 0 | AR85: 0 | AS85: 0 | AT85: 0 | AU85: 0 | AV85: 0 | AW85: 0 | AX85: 0 | AY85: 0 | AZ85: 0 | BA85: 0 | BB85: 0 | BC85: 0 | BD85: 0 | BE85: 0 | BF85: 0 | BG85: 0 | BH85: 0 | BI85: 0 | BJ85: 0 | BK85: 0 | BL85: 0 | BM85: 0 | BN85: 0 | BO85: 0 | BP85: 0 | BQ85: 0 | BR85: 0 | BS85: 0 | BT85: 0 | BU85: 0 | BV85: 0 | BW85: 0 | BX85: 0
C86: OTROS ACTIVOS NO CORRIENTES MANTENIDOS PARA LA VENTA | D86: 36750.52 | E86: 34887.42 | F86: 10549.48 | G86: 24337.94 | H86: 0 | I86: 1863.1 | J86: 34442.04 | K86: 34442.04 | L86: 10104.1 | M86: 24337.94 | N86: 0 | O86: 10104.1 | P86: 0 | Q86: 0 | R86: 0 | S86: 0 | T86: 445.38 | U86: 445.38 | V86: 0 | W86: 445.38 | X86: 445.38 | Y86: 445.38 | Z86: 0 | AA86: 1863.1 | AB86: 0 | AC86: 0 | AD86: 0 | AE86: 0 | AF86: 0 | AG86: 0 | AH86: 24337.94 | AI86: 5378.24 | AJ86: 0 | AK86: 0 | AL86: 0 | AM86: 0 | AN86: 4725.86 | AO86: 0 | AP86: 0 | AQ86: 0 | AR86: 0 | AS86: 0 | AT86: 0 | AU86: 0 | AV86: 0 | AW86: 0 | AX86: 0 | AY86: 0 | AZ86: 0 | BA86: 0 | BB86: 0 | BC86: 0 | BD86: 0 | BE86: 0 | BF86: 0 | BG86: 0 | BH86: 0 | BI86: 0 | BJ86: 0 | BK86: 0 | BL86: 0 | BM86: 0 | BN86: 0 | BO86: 0 | BP86: 0 | BQ86: 445.38 | BR86: 0 | BS86: 0 | BT86: 0 | BU86: 0 | BV86: 0 | BW86: 1863.1 | BX86: 0
C87: DETERIORO ACTIVOS NO CORRIENTES MANTENIDOS PARA LA VENTA | D87: 672592.37 | E87: 644319.91 | F87: 383535.56 | G87: 260784.35 | H87: 28142.7 | I87: 129.76 | J87: 649448.33 | K87: 621305.63 | L87: 363301.4 | M87: 258004.23 | N87: 28142.7 | O87: 391444.1 | P87: 0 | Q87: 0 | R87: 0 | S87: 0 | T87: 23014.28 | U87: 20234.16 | V87: 2780.12 | W87: 23014.28 | X87: 23014.28 | Y87: 20234.16 | Z87: 2780.12 | AA87: 129.76 | AB87: 31236.15 | AC87: 0 | AD87: 87789.98 | AE87: 295072.88 | AF87: 0 | AG87: 115278.72 | AH87: 50065.41 | AI87: 0 | AJ87: 1165.94 | AK87: 15041.79 | AL87: 3551.63 | AM87: 28142.7 | AN87: 2035.77 | AO87: 253.96 | AP87: 0 | AQ87: 0 | AR87: 10858.53 | AS87: 253.36 | AT87: 0 | AU87: 1318.49 | AV87: 753.78 | AW87: 0 | AX87: 0 | AY87: 0 | AZ87: 6629.24 | BA87: 0 | BB87: 0 | BC87: 0 | BD87: 0 | BE87: 0 | BF87: 0 | BG87: 0 | BH87: 0 | BI87: 1266.54 | BJ87: 0 | BK87: 1426.25 | BL87: 160.37 | BM87: 13030.68 | BN87: 17.35 | BO87: 481.63 | BP87: 66.6 | BQ87: 5759.22 | BR87: 805.64 | BS87: 0 | BT87: 0 | BU87: 0 | BV87: 0 | BW87: 0 | BX87: 129.76
C88: ACTIVOS MATERIALES | D88: 12992255 | E88: 12570957 | F88: 10369969 | G88: 2200988.2 | H88: 287659.31 | I88: 133638.8 | J88: 12614922 | K88: 12327263 | L88: 10160854 | M88: 2166409.2 | N88: 287659.31 | O88: 10448513 | P88: 82915.29 | Q88: 82915.29 | R88: 76123.7 | S88: 6791.59 | T88: 160778.68 | U88: 132991.27 | V88: 27787.41 | W88: 160778.68 | X88: 160778.68 | Y88: 132991.27 | Z88: 27787.41 | AA88: 133638.8 | AB88: 1185576.3 | AC88: 585339.56 | AD88: 265313.31 | AE88: 5156915.5 | AF88: 55776.63 | AG88: 240990 | AH88: 779356.04 | AI88: 577238.23 | AJ88: 618859.43 | AK88: 1164378.3 | AL88: 644166.76 | AM88: 287659.31 | AN88: 508572.2 | AO88: 16754.41 | AP88: 77801.68 | AQ88: 46403.28 | AR88: 40285.74 | AS88: 10835.47 | AT88: 56073.82 | AU88: 101316.17 | AV88: 24057.9 | AW88: 11341.02 | AX88: 87545.51 | AY88: 18875.16 | AZ88: 35096.64 | BA88: 12075.42 | BB88: 6318.71 | BC88: 0 | BD88: 75637.15 | BE88: 481.28 | BF88: 6791.59 | BG88: 5.27 | BH88: 0 | BI88: 60816.59 | BJ88: 23638.51 | BK88: 4185.45 | BL88: 22485.33 | BM88: 7563.96 | BN88: 681.3 | BO88: 16108.54 | BP88: 819.2 | BQ88: 17805.58 | BR88: 6386.82 | BS88: 287.4 | BT88: 27277.34 | BU88: 25102.46 | BV88: 12092.31 | BW88: 36398.38 | BX88: 32768.31
C89: PROPIEDAD, PLANTA Y EQUIPO | D89: 6314535.2 | E89: 6049250.4 | F89: 4616396 | G89: 1432854.4 | H89: 176572.03 | I89: 88712.83 | J89: 6108256.4 | K89: 5931684.3 | L89: 4521188.1 | M89: 1410496.2 | N89: 176572.03 | O89: 4697760.1 | P89: 45384.35 | Q89: 45384.35 | R89: 41658.5 | S89: 3725.85 | T89: 72181.68 | U89: 53549.41 | V89: 18632.27 | W89: 72181.68 | X89: 72181.68 | Y89: 53549.41 | Z89: 18632.27 | AA89: 88712.83 | AB89: 625679.93 | AC89: 492004.33 | AD89: 154425.48 | AE89: 1797212 | AF89: 55776.63 | AG89: 31715.29 | AH89: 653234.85 | AI89: 219596.91 | AJ89: 496301 | AK89: 443578.16 | AL89: 382723.47 | AM89: 176572.03 | AN89: 274269.22 | AO89: 1409.36 | AP89: 63334.47 | AQ89: 16194.25 | AR89: 6317.01 | AS89: 2886.38 | AT89: 24812.44 | AU89: 99026.52 | AV89: 21637.79 | AW89: 4984.41 | AX89: 18732.64 | AY89: 5971.78 | AZ89: 33674.91 | BA89: 3797.16 | BB89: 2387.95 | BC89: 0 | BD89: 41265.32 | BE89: 387.91 | BF89: 3725.85 | BG89: 5.27 | BH89: 0 | BI89: 17105.78 | BJ89: 12823.28 | BK89: 3471.45 | BL89: 16428.48 | BM89: 5698.89 | BN89: 248.19 | BO89: 12415.7 | BP89: 677.49 | BQ89: 1244.79 | BR89: 1780.23 | BS89: 287.4 | BT89: 15243.16 | BU89: 11457.48 | BV89: 10169.7 | BW89: 26266.58 | BX89: 25575.91
C90: PROPIEDAD, PLANTA Y EQUIPO POR DERECHOS DE USO | D90: 3745938.9 | E90: 3627413.9 | F90: 2978168.8 | G90: 649245.08 | H90: 77348.74 | I90: 41176.32 | J90: 3618939.8 | K90: 3541591.1 | L90: 2903749.5 | M90: 637841.59 | N90: 77348.74 | O90: 2981098.2 | P90: 3355.12 | Q90: 3355.12 | R90: 289.38 | S90: 3065.74 | T90: 82467.68 | U90: 74129.93 | V90: 8337.75 | W90: 82467.68 | X90: 82467.68 | Y90: 74129.93 | Z90: 8337.75 | AA90: 41176.32 | AB90: 437378.27 | AC90: 40725.26 | AD90: 91295.15 | AE90: 1123176.6 | AF90: 0 | AG90: 209274.71 | AH90: 109124.21 | AI90: 227277.24 | AJ90: 57756.85 | AK90: 638916.28 | AL90: 185174.09 | AM90: 77348.74 | AN90: 201819.34 | AO90: 15240.67 | AP90: 11342.7 | AQ90: 29864.25 | AR90: 33968.73 | AS90: 7949.09 | AT90: 27513.63 | AU90: 2289.65 | AV90: 1217.2 | AW90: 4920.16 | AX90: 62792.37 | AY90: 11648.88 | AZ90: 991.19 | BA90: 8249.99 | BB90: 1684.57 | BC90: 0 | BD90: 196.01 | BE90: 93.37 | BF90: 3065.74 | BG90: 0 | BH90: 0 | BI90: 43710.81 | BJ90: 8751.28 | BK90: 714 | BL90: 4999.03 | BM90: 1865.07 | BN90: 433.11 | BO90: 2875.45 | BP90: 141.71 | BQ90: 14370.63 | BR90: 4606.59 | BS90: 0 | BT90: 11248.44 | BU90: 13644.98 | BV90: 1922.61 | BW90: 7647.32 | BX90: 6712.97
C91: PROPIEDADES Y EQUIPO EN ARRENDAMIENTO OPERATIVO | D91: 2050513 | E91: 2050513 | F91: 2050513 | G91: 0 | H91: 0 | I91: 0 | J91: 2050513 | K91: 2050513 | L91: 2050513 | M91: 0 | N91: 0 | O91: 2050513 | P91: 0 | Q91: 0 | R91: 0 | S91: 0 | T91: 0 | U91: 0 | V91: 0 | W91: 0 | X91: 0 | Y91: 0 | Z91: 0 | AA91: 0 | AB91: 0 | AC91: 0 | AD91: 0 | AE91: 2012663.2 | AF91: 0 | AG91: 0 | AH91: 0 | AI91: 37303.38 | AJ91: 0 | AK91: 0 | AL91: 0 | AM91: 0 | AN91: 546.43 | AO91: 0 | AP91: 0 | AQ91: 0 | AR91: 0 | AS91: 0 | AT91: 0 | AU91: 0 | AV91: 0 | AW91: 0 | AX91: 0 | AY91: 0 | AZ91: 0 | BA91: 0 | BB91: 0 | BC91: 0 | BD91: 0 | BE91: 0 | BF91: 0 | BG91: 0 | BH91: 0 | BI91: 0 | BJ91: 0 | BK91: 0 | BL91: 0 | BM91: 0 | BN91: 0 | BO91: 0 | BP91: 0 | BQ91: 0 | BR91: 0 | BS91: 0 | BT91: 0 | BU91: 0 | BV91: 0 | BW91: 0 | BX91: 0
... C99: OTROS | D99: 10097446 | E99: 9937576.6 | F99: 7257329.8 | G99: 2680246.8 | H99: 151533.53 | I99: 8335.91 | J99: 9673977.9 | K99: 9522444.4 | L99: 7045150.8 | M99: 2477293.6 | N99: 151533.53 | O99: 7196684.4 | P99: 69648.45 | Q99: 69648.45 | R99: 54983.23 | S99: 14665.22 | T99: 345483.79 | U99: 157195.74 | V99: 188288.05 | W99: 345483.79 | X99: 345483.79 | Y99: 157195.74 | Z99: 188288.05 | AA99: 8335.91 | AB99: 2070900.6 | AC99: 275055.63 | AD99: 693088.54 | AE99: 2652013.1 | AF99: 69313.58 | AG99: 259307.39 | AH99: 526999.18 | AI99: 732014.29 | AJ99: 110310.65 | AK99: 472653.71 | AL99: 683110.55 | AM99: 151533.53 | AN99: 149471.98 | AO99: 168381.58 | AP99: 60157.9 | AQ99: 35922.05 | AR99: 39763.1 | AS99: 10220.24 | AT99: 127791.43 | AU99: 30422.28 | AV99: 1361.91 | AW99: 58980.97 | AX99: 23140.29 | AY99: 108191.67 | AZ99: 30839.09 | BA99: 14867.85 | BB99: 104753.1 | BC99: 13411.79 | BD99: 25189.95 | BE99: 2590.74 | BF99: 14665.22 | BG99: 27194.75 | BH99: 7.79 | BI99: 9987.48 | BJ99: 92778.37 | BK99: 58705.23 | BL99: 17250.7 | BM99: 28182.89 | BN99: 83.75 | BO99: 3906.81 | BP99: 1515.92 | BQ99: 8912.55 | BR99: 120367.82 | BS99: 3792.27 | BT99: 1157.38 | BU99: 0.92 | BV99: 2082.87 | BW99: 3090.81 | BX99: 2003.93
A100: PASIVOS Y PATRIMONIO | D100: 8.6102156e+08 | E100: 8.2435572e+08 | F100: 6.0102194e+08 | G100: 2.2333378e+08 | H100: 32216897 | I100: 4448949.1 | J100: 8.1757085e+08 | K100: 7.8535395e+08 | L100: 5.6825555e+08 | M100: 2.170984e+08 | N100: 32216897 | O100: 6.0047244e+08 | P100: 25217277 | Q100: 25217277 | R100: 24719512 | S100: 497764.6 | T100: 13784490 | U100: 8046878.3 | V100: 5737611.8 | W100: 13784490 | X100: 13784490 | Y100: 8046878.3 | Z100: 5737611.8 | AA100: 4448949.1 | AB100: 1.0863049e+08 | AC100: 29708064 | AD100: 30417280 | AE100: 2.0896007e+08 | AF100: 12366001 | AG100: 35958041 | AH100: 79516659 | AI100: 47147802 | AJ100: 18069652 | AK100: 1.1733175e+08 | AL100: 40258759 | AM100: 32216897 | AN100: 17253831 | AO100: 2050719.5 | AP100: 2056792.6 | AQ100: 2179116.2 | AR100: 4814725.7 | AS100: 2735091.4 | AT100: 6351326.6 | AU100: 3158147.4 | AV100: 1144241.6 | AW100: 5507740.6 | AX100: 2319961.9 | AY100: 1401990 | AZ100: 2294876.3 | BA100: 3462364.7 | BB100: 156363.68 | BC100: 102086.7 | BD100: 21712809 | BE100: 2019367.6 | BF100: 497764.6 | BG100: 754207.35 | BH100: 233128.87 | BI100: 905633.27 | BJ100: 3861357.3 | BK100: 2067923.3 | BL100: 895679.42 | BM100: 522454.61 | BN100: 573600.64 | BO100: 442584.48 | BP100: 357395.61 | BQ100: 1288153.1 | BR100: 2841496.7 | BS100: 28211.61 | BT100: 525872.9 | BU100: 1284334.3 | BV100: 319207.78 | BW100: 1055168.9 | BX100: 1264365.2
A101: PASIVOS | D101: 7.4028246e+08 | E101: 7.0722648e+08 | F101: 5.0264155e+08 | G101: 2.0458493e+08 | H101: 29748598 | I101: 3307380 | J101: 7.1307413e+08 | K101: 6.8332553e+08 | L101: 4.8398523e+08 | M101: 1.993403e+08 | N101: 29748598 | O101: 5.1373383e+08 | P101: 11898625 | Q101: 11898625 | R101: 11545017 | S101: 353607.85 | T101: 12002325 | U101: 7111302.7 | V101: 4891022.4 | W101: 12002325 | X101: 12002325 | Y101: 7111302.7 | Z101: 4891022.4 | AA101: 3307380 | AB101: 83918259 | AC101: 26644593 | AD101: 27683431 | AE101: 1.7719262e+08 | AF101: 10817638 | AG101: 33535390 | AH101: 73829357 | AI101: 42477683 | AJ101: 15923098 | AK101: 1.0451711e+08 | AL101: 37389355 | AM101: 29748598 | AN101: 15584701 | AO101: 1876048.9 | AP101: 1612336.1 | AQ101: 1616547.9 | AR101: 4234443.6 | AS101: 2376819.8 | AT101: 5649825.7 | AU101: 2788458.1 | AV101: 938411.92 | AW101: 4861379.5 | AX101: 1903097.6 | AY101: 1181605.8 | AZ101: 1978299.3 | BA101: 2774817 | BB101: 9547.85 | BC101: 10646.9 | BD101: 11414739 | BE101: 55742.99 | BF101: 353607.85 | BG101: 54489.29 | BH101: 20046.28 | BI101: 768720.69 | BJ101: 3369028.6 | BK101: 1788960 | BL101: 844845.57 | BM101: 453875.77 | BN101: 498900.14 | BO101: 337117.84 | BP101: 283572.61 | BQ101: 1175931.9 | BR101: 2474790.5 | BS101: 6581.45 | BT101: 444681.67 | BU101: 697425.28 | BV101: 280265.14 | BW101: 892408.61 | BX101: 992599.27
B102: INSTRUMENTOS FINANCIEROS A COSTO AMORTIZADO | D102: 6.4989679e+08 | E102: 6.2729713e+08 | F102: 4.4578556e+08 | G102: 1.8151158e+08 | H102: 19715228 | I102: 2884427.9 | J102: 6.2700018e+08 | K102: 6.0728496e+08 | L102: 4.2813116e+08 | M102: 1.791538e+08 | N102: 19715228 | O102: 4.4784639e+08 | P102: 11550029 | Q102: 11550029 | R102: 11230369 | S102: 319659.53 | T102: 8462147.3 | U102: 6424028.7 | V102: 2038118.6 | W102: 8462147.3 | X102: 8462147.3 | Y102: 6424028.7 | Z102: 2038118.6 | AA102: 2884427.9 | AB102: 73264860 | AC102: 24487871 | AD102: 23481514 | AE102: 1.5628736e+08 | AF102: 10413787 | AG102: 31603832 | AH102: 65283239 | AI102: 37335625 | AJ102: 15214969 | AK102: 91579683 | AL102: 34314057 | AM102: 19715228 | AN102: 14922614 | AO102: 1649269.6 | AP102: 938863.82 | AQ102: 1377815.2 | AR102: 4013592.2 | AS102: 1871624.5 | AT102: 4775971.7 | AU102: 2328727.3 | AV102: 906063.88 | AW102: 4260092.4 | AX102: 1534278.7 | AY102: 882480.94 | AZ102: 1864096.1 | BA102: 2692579.7 | BB102: 94.81 | BC102: 0 | BD102: 11230369 | BE102: 0 | BF102: 319659.53 | BG102: 0 | BH102: 0 | BI102: 595286.2 | BJ102: 3054900.4 | BK102: 727062.02 | BL102: 806340.77 | BM102: 425023.48 | BN102: 464814.63 | BO102: 96431.41 | BP102: 181554.2 | BQ102: 1077663.1 | BR102: 1033071 | BS102: 0 | BT102: 396364 | BU102: 553739.26 | BV102: 240365.35 | BW102: 825491.26 | BX102: 868468.05
C103: DEPÓSITOS EN CUENTA CORRIENTE | D103: 84846247 | E103: 82749364 | F103: 61757768 | G103: 20991596 | H103: 2096882.6 | I103: 0 | J103: 84846247 | K103: 82749364 | L103: 61757768 | M103: 20991596 | N103: 2096882.6 | O103: 63854651 | P103: 0 | Q103: 0 | R103: 0 | S103: 0 | T103: 0 | U103: 0 | V103: 0 | W103: 0 | X103: 0 | Y103: 0 | Z103: 0 | AA103: 0 | AB103: 14541024 | AC103: 1129493.8 | AD103: 2344681.3 | AE103: 25729267 | AF103: 4368919.8 | AG103: 1722160.2 | AH103: 9299353.6 | AI103: 6912235.7 | AJ103: 1528890 | AK103: 10030483 | AL103: 2441793.9 | AM103: 2096882.6 | AN103: 1545282.3 | AO103: 4448.84 | AP103: 0 | AQ103: 0 | AR103: 193862.71 | AS103: 4.46 | AT103: 23005.17 | AU103: 144844.65 | AV103: 118288.47 | AW103: 507637.93 | AX103: 0 | AY103: 80.99 | AZ103: 24406.98 | BA103: 139199.57 | BB103: 0 | BC103: 0 | BD103: 0 | BE103: 0 | BF103: 0 | BG103: 0 | BH103: 0 | BI103: 0 | BJ103: 0 | BK103: 0 | BL103: 0 | BM103: 0 | BN103: 0 | BO103: 0 | BP103: 0 | BQ103: 0 | BR103: 0 | BS103: 0 | BT103: 0 | BU103: 0 | BV103: 0 | BW103: 0 | BX103: 0
C104: DEPÓSITOS SIMPLES | D104: 2005.82 | E104: 2005.82 | F104: 0 | G104: 2005.82 | H104: 0 | I104: 0 | J104: 2005.82 | K104: 2005.82 | L104: 0 | M104: 2005.82 | N104: 0 | O104: 0 | P104: 0 | Q104: 0 | R104: 0 | S104: 0 | T104: 0 | U104: 0 | V104: 0 | W104: 0 | X104: 0 | Y104: 0 | Z104: 0 | AA104: 0 | AB104: 0 | AC104: 0 | AD104: 0 | AE104: 0 | AF104: 0 | AG104: 0 | AH104: 2005.82 | AI104: 0 | AJ104: 0 | AK104: 0 | AL104: 0 | AM104: 0 | AN104: 0 | AO104: 0 | AP104: 0 | AQ104: 0 | AR104: 0 | AS104: 0 | AT104: 0 | AU104: 0 | AV104: 0 | AW104: 0 | AX104: 0 | AY104: 0 | AZ104: 0 | BA104: 0 | BB104: 0 | BC104: 0 | BD104: 0 | BE104: 0 | BF104: 0 | BG104: 0 | BH104: 0 | BI104: 0 | BJ104: 0 | BK104: 0 | BL104: 0 | BM104: 0 | BN104: 0 | BO104: 0 | BP104: 0 | BQ104: 0 | BR104: 0 | BS104: 0 | BT104: 0 | BU104: 0 | BV104: 0 | BW104: 0 | BX104: 0
C105: CERTIFICADOS DE DEPÓSITO A TERMINO | D105: 1.5287732e+08 | E105: 149675906 | F105: 1.043182e+08 | G105: 45357703 | H105: 1179376.5 | I105: 2022034.1 | J105: 1.3960737e+08 | K105: 1.38428e+08 | L105: 94301227 | M105: 44126771 | N105: 1179376.5 | O105: 95480603 | P105: 4637066.8 | Q105: 4637066.8 | R105: 4637066.8 | S105: 0 | T105: 6610841.3 | U105: 5379909.2 | V105: 1230932.1 | W105: 6610841.3 | X105: 6610841.3 | Y105: 5379909.2 | Z105: 1230932.1 | AA105: 2022034.1 | AB105: 17932769 | AC105: 7524362.3 | AD105: 5796632.3 | AE105: 26370896 | AF105: 1002.74 | AG105: 4449405.8 | AH105: 18011495 | AI105: 6371866.8 | AJ105: 4018915.1 | AK105: 19879567 | AL105: 10395815 | AM105: 1179376.5 | AN105: 2998414.8 | AO105: 1443936.7 | AP105: 584822.31 | AQ105: 597842.82 | AR105: 1873160.4 | AS105: 1477496.3 | AT105: 2991245.3 | AU105: 1237479.7 | AV105: 409641.12 | AW105: 1203541.8 | AX105: 992135.35 | AY105: 766669.16 | AZ105: 1058731.4 | BA105: 40153.34 | BB105: 0 | BC105: 0 | BD105: 4637066.8 | BE105: 0 | BF105: 0 | BG105: 0 | BH105: 0 | BI105: 391858.86 | BJ105: 2981857.8 | BK105: 424191.43 | BL105: 659288.35 | BM105: 385832.62 | BN105: 105944.14 | BO105: 95657.45 | BP105: 129760.63 | BQ105: 855127.44 | BR105: 581322.63 | BS105: 0 | BT105: 205537.18 | BU105: 484769.01 | BV105: 183935.61 | BW105: 609586.47 | BX105: 538205.88
C106: DEPÓSITOS DE AHORRO | D106: 2.9455254e+08 | E106: 2.8687953e+08 | F106: 2.0877176e+08 | G106: 78107777 | H106: 6891000.6 | I106: 782005.26 | J106: 2.9259912e+08 | K106: 2.8570812e+08 | L106: 2.0764058e+08 | M106: 78067540 | N106: 6891000.6 | O106: 2.1453158e+08 | P106: 667805.82 | Q106: 667805.82 | R106: 628037.05 | S106: 39768.77 | T106: 503604.84 | U106: 503137.09 | V106: 467.75 | W106: 503604.84 | X106: 503604.84 | Y106: 503137.09 | Z106: 467.75 | AA106: 782005.26 | AB106: 29227984 | AC106: 12208125 | AD106: 9825939.1 | AE106: 82679695 | AF106: 2879696.1 | AG106: 13645768 | AH106: 30148156 | AI106: 18916812 | AJ106: 8569034.7 | AK106: 44556765 | AL106: 17323715 | AM106: 6891000.6 | AN106: 8780791 | AO106: 11845.52 | AP106: 176671.3 | AQ106: 301732.63 | AR106: 1175894.9 | AS106: 117377.1 | AT106: 1264062.3 | AU106: 623480.67 | AV106: 376819.3 | AW106: 2343404.8 | AX106: 237757 | AY106: 100510.9 | AZ106: 202673.61 | BA106: 13317.24 | BB106: 94.81 | BC106: 0 | BD106: 628037.05 | BE106: 0 | BF106: 39768.77 | BG106: 0 | BH106: 0 | BI106: 194418.24 | BJ106: 0 | BK106: 0 | BL106: 46942.63 | BM106: 39190.86 | BN106: 49.66 | BO106: 467.75 | BP106: 0 | BQ106: 222535.7 | BR106: 0 | BS106: 0 | BT106: 156976.48 | BU106: 68970.25 | BV106: 54850.2 | BW106: 200708.24 | BX106: 300500.09
C107: CUENTAS DE AHORRO ESPECIAL | D107: 1655820.2 | E107: 1644478.4 | F107: 1078383.6 | G107: 566094.79 | H107: 0 | I107: 11341.86 | J107: 1644478.4 | K107: 1644478.4 | L107: 1078383.6 | M107: 566094.79 | N107: 0 | O107: 1078383.6 | P107: 0 | Q107: 0 | R107: 0 | S107: 0 | T107: 0 | U107: 0 | V107: 0 | W107: 0 | X107: 0 | Y107: 0 | Z107: 0 | AA107: 11341.86 | AB107: 79406.55 | AC107: 1472.91 | AD107: 0 | AE107: 697260.02 | AF107: 0 | AG107: 0 | AH107: 333841.18 | AI107: 19774.72 | AJ107: 92926.17 | AK107: 76269.23 | AL107: 232253.61 | AM107: 0 | AN107: 74896.26 | AO107: 0 | AP107: 0 | AQ107: 0 | AR107: 36377.74 | AS107: 0 | AT107: 0 | AU107: 0 | AV107: 0 | AW107: 0 | AX107: 0 | AY107: 0 | AZ107: 0 | BA107: 0 | BB107: 0 | BC107: 0 | BD107: 0 | BE107: 0 | BF107: 0 | BG107: 0 | BH107: 0 | BI107: 0 | BJ107: 0 | BK107: 0 | BL107: 0 | BM107: 0 | BN107: 0 | BO107: 0 | BP107: 0 | BQ107: 0 | BR107: 0 | BS107: 0 | BT107: 0 | BU107: 0 | BV107: 1398.91 | BW107: 9942.95 | BX107: 0
C108: CERTIFICADOS DE AHORRO DE VALOR REAL | D108: 19035.97 | E108: 19035.97 | F108: 8422.55 | G108: 10613.42 | H108: 0 | I108: 0 | J108: 19035.97 | K108: 19035.97 | L108: 8422.55 | M108: 10613.42 | N108: 0 | O108: 8422.55 | P108: 0 | Q108: 0 | R108: 0 | S108: 0 | T108: 0 | U108: 0 | V108: 0 | W108: 0 | X108: 0 | Y108: 0 | Z108: 0 | AA108: 0 | AB108: 0 | AC108: 0 | AD108: 0 | AE108: 0 | AF108: 0 | AG108: 0 | AH108: 10613.42 | AI108: 0 | AJ108: 8422.55 | AK108: 0 | AL108: 0 | AM108: 0 | AN108: 0 | AO108: 0 | AP108: 0 | AQ108: 0 | AR108: 0 | AS108: 0 | AT108: 0 | AU108: 0 | AV108: 0 | AW108: 0 | AX108: 0 | AY108: 0 | AZ108: 0 | BA108: 0 | BB108: 0 | BC108: 0 | BD108: 0 | BE108: 0 | BF108: 0 | BG108: 0 | BH108: 0 | BI108: 0 | BJ108: 0 | BK108: 0 | BL108: 0 | BM108: 0 | BN108: 0 | BO108: 0 | BP108: 0 | BQ108: 0 | BR108: 0 | BS108: 0 | BT108: 0 | BU108: 0 | BV108: 0 | BW108: 0 | BX108: 0
C109: DOCUMENTOS POR PAGAR | D109: 1236.96 | E109: 1236.96 | F109: 0 | G109: 1236.96 | H109: 0 | I109: 0 | J109: 1236.96 | K109: 1236.96 | L109: 0 | M109: 1236.96 | N109: 0 | O109: 0 | P109: 0 | Q109: 0 | R109: 0 | S109: 0 | T109: 0 | U109: 0 | V109: 0 | W109: 0 | X109: 0 | Y109: 0 | Z109: 0 | AA109: 0 | AB109: 0 | AC109: 0 | AD109: 0 | AE109: 0 | AF109: 0 | AG109: 0 | AH109: 0 | AI109: 0 | AJ109: 0 | AK109: 0 | AL109: 1236.96 | AM109: 0 | AN109: 0 | AO109: 0 | AP109: 0 | AQ109: 0 | AR109: 0 | AS109: 0 | AT109: 0 | AU109: 0 | AV109: 0 | AW109: 0 | AX109: 0 | AY109: 0 | AZ109: 0 | BA109: 0 | BB109: 0 | BC109: 0 | BD109: 0 | BE109: 0 | BF109: 0 | BG109: 0 | BH109: 0 | BI109: 0 | BJ109: 0 | BK109: 0 | BL109: 0 | BM109: 0 | BN109: 0 | BO109: 0 | BP109: 0 | BQ109: 0 | BR109: 0 | BS109: 0 | BT109: 0 | BU109: 0 | BV109: 0 | BW109: 0 | BX109: 0
C110: FONDOS EN FIDEICOMISO Y CUENTAS ESPECIALES | D110: 1157.55 | E110: 1157.55 | F110: 1157.55 | G110: 0 | H110: 0 | I110: 0 | J110: 1157.55 | K110: 1157.55 | L110: 1157.55 | M110: 0 | N110: 0 | O110: 1157.55 | P110: 0 | Q110: 0 | R110: 0 | S110: 0 | T110: 0 | U110: 0 | V110: 0 | W110: 0 | X110: 0 | Y110: 0 | Z110: 0 | AA110: 0 | AB110: 499.42 | AC110: 0 | AD110: 0 | AE110: 0 | AF110: 0 | AG110: 0 | AH110: 0 | AI110: 658.13 | AJ110: 0 | AK110: 0 | AL110: 0 | AM110: 0 | AN110: 0 | AO110: 0 | AP110: 0 | AQ110: 0 | AR110: 0 | AS110: 0 | AT110: 0 | AU110: 0 | AV110: 0 | AW110: 0 | AX110: 0 | AY110: 0 | AZ110: 0 | BA110: 0 | BB110: 0 | BC110: 0 | BD110: 0 | BE110: 0 | BF110: 0 | BG110: 0 | BH110: 0 | BI110: 0 | BJ110: 0 | BK110: 0 | BL110: 0 | BM110: 0 | BN110: 0 | BO110: 0 | BP110: 0 | BQ110: 0 | BR110: 0 | BS110: 0 | BT110: 0 | BU110: 0 | BV110: 0 | BW110: 0 | BX110: 0
C111: BANCOS Y CORRESPONSALES | D111: 20455.48 | E111: 20009.64 | F111: 12858.27 | G111: 7151.37 | H111: 445.84 | I111: 0 | J111: 20455.48 | K111: 20009.64 | L111: 12858.27 | M111: 7151.37 | N111: 445.84 | O111: 13304.11 | P111: 0 | Q111: 0 | R111: 0 | S111: 0 | T111: 0 | U111: 0 | V111: 0 | W111: 0 | X111: 0 | Y111: 0 | Z111: 0 | AA111: 0 | AB111: 2499.84 | AC111: 5905.13 | AD111: 70.05 | AE111: 0 | AF111: 4324.88 | AG111: 0 | AH111: 2756.44 | AI111: 2237.8 | AJ111: 4 | AK111: 2107.99 | AL111: 0 | AM111: 445.84 | AN111: 0 | AO111: 0 | AP111: 0 | AQ111: 0 | AR111: 0 | AS111: 0 | AT111: 0 | AU111: 0 | AV111: 0 | AW111: 0 | AX111: 0 | AY111: 0 | AZ111: 103.51 | BA111: 0 | BB111: 0 | BC111: 0 | BD111: 0 | BE111: 0 | BF111: 0 | BG111: 0 | BH111: 0 | BI111: 0 | BJ111: 0 | BK111: 0 | BL111: 0 | BM111: 0 | BN111: 0 | BO111: 0 | BP111: 0 | BQ111: 0 | BR111: 0 | BS111: 0 | BT111: 0 | BU111: 0 | BV111: 0 | BW111: 0 | BX111: 0
C112: DEPÓSITOS ESPECIALES | D112: 10227676 | E112: 2596988.3 | F112: 1602772.2 | G112: 994216.18 | H112: 7562377.8 | I112: 68310.27 | J112: 10067747 | K112: 2505369.1 | L112: 1511152.9 | M112: 994216.18 | N112: 7562377.8 | O112: 9073530.7 | P112: 91619.28 | Q112: 91619.28 | R112: 91619.28 | S112: 0 | T112: 0 | U112: 0 | V112: 0 | W112: 0 | X112: 0 | Y112: 0 | Z112: 0 | AA112: 68310.27 | AB112: 182063.46 | AC112: 26023.06 | AD112: 34673.43 | AE112: 701953.55 | AF112: 16907.37 | AG112: 15452.93 | AH112: 837485.16 | AI112: 130246.51 | AJ112: 36915.71 | AK112: 381860.2 | AL112: 46524.34 | AM112: 7562377.8 | AN112: 46577.95 | AO112: 0 | AP112: 0 | AQ112: 0 | AR112: 0 | AS112: 2613.29 | AT112: 0 | AU112: 0 | AV112: 0 | AW112: 43172.95 | AX112: 2899.15 | AY112: 0 | AZ112: 0 | BA112: 0 | BB112: 0 | BC112: 0 | BD112: 91619.28 | BE112: 0 | BF112: 0 | BG112: 0 | BH112: 0 | BI112: 0 | BJ112: 0 | BK112: 0 | BL112: 0 | BM112: 0 | BN112: 0 | BO112: 0 | BP112: 0 | BQ112: 0 | BR112: 0 | BS112: 0 | BT112: 33784.85 | BU112: 0 | BV112: 0 | BW112: 5048.08 | BX112: 29477.34
C113: EXIGIBILIDADES POR SERVICIOS | D113: 4406143.8 | E113: 4093986.8 | F113: 2904135.8 | G113: 1189851 | H113: 312157.02 | I113: 0 | J113: 4400823.3 | K113: 4088666.2 | L113: 2900730.5 | M113: 1187935.8 | N113: 312157.02 | O113: 3212887.5 | P113: 2906.12 | Q113: 2906.12 | R113: 990.87 | S113: 1915.25 | T113: 2414.44 | U113: 2414.44 | V113: 0 | W113: 2414.44 | X113: 2414.44 | Y113: 2414.44 | Z113: 0 | AA113: 0 | AB113: 277325.6 | AC113: 50258.3 | AD113: 179080.1 | AE113: 1195641.6 | AF113: 41976.82 | AG113: 81017.73 | AH113: 546516.18 | AI113: 204838.2 | AJ113: 147277.01 | AK113: 787613.12 | AL113: 298699.95 | AM113: 312157.02 | AN113: 81942.99 | AO113: 565.71 | AP113: 14865.85 | AQ113: 13435.42 | AR113: 65902.15 | AS113: 10542.72 | AT113: 15546.5 | AU113: 24890.53 | AV113: 381.38 | AW113: 207.97 | AX113: 0 | AY113: 15004.15 | AZ113: 35136.29 | BA113: 0 | BB113: 0 | BC113: 0 | BD113: 990.87 | BE113: 0 | BF113: 1915.25 | BG113: 0 | BH113: 0 | BI113: 0 | BJ113: 0 | BK113: 0 | BL113: 2414.44 | BM113: 0 | BN113: 0 | BO113: 0 | BP113: 0 | BQ113: 0 | BR113: 0 | BS113: 0 | BT113: 0 | BU113: 0 | BV113: 0 | BW113: 0 | BX113: 0
C114: SERVICIOS DE RECAUDO | D114: 97261.69 | E114: 96591.61 | F114: 80392.2 | G114: 16199.41 | H114: 0 | I114: 670.08 | J114: 96591.61 | K114: 96591.61 | L114: 80392.2 | M114: 16199.41 | N114: 0 | O114: 80392.2 | P114: 0 | Q114: 0 | R114: 0 | S114: 0 | T114: 0 | U114: 0 | V114: 0 | W114: 0 | X114: 0 | Y114: 0 | Z114: 0 | AA114: 670.08 | AB114: 63973.6 | AC114: 216.79 | AD114: 0 | AE114: 0 | AF114: 16199.41 | AG114: 0 | AH114: 0 | AI114: 1250.36 | AJ114: 0 | AK114: 0 | AL114: 0 | AM114: 0 | AN114: 14951.45 | AO114: 0 | AP114: 0 | AQ114: 0 | AR114: 0 | AS114: 0 | AT114: 0 | AU114: 0 | AV114: 0 | AW114: 0 | AX114: 0 | AY114: 0 | AZ114: 0 | BA114: 0 | BB114: 0 | BC114: 0 | BD114: 0 | BE114: 0 | BF114: 0 | BG114: 0 | BH114: 0 | BI114: 0 | BJ114: 0 | BK114: 0 | BL114: 0 | BM114: 0 | BN114: 0 | BO114: 0 | BP114: 0 | BQ114: 0 | BR114: 0 | BS114: 0 | BT114: 0 | BU114: 0 | BV114: 180.63 | BW114: 204.71 | BX114: 284.74
... C124: OPERACIONES REPO DE CONTRACCIÓN MONETARIA | D124: 0 | E124: 0 | F124: 0 | G124: 0 | H124: 0 | I124: 0 | J124: 0 | K124: 0 | L124: 0 | M124: 0 | N124: 0 | O124: 0 | P124: 0 | Q124: 0 | R124: 0 | S124: 0 | T124: 0 | U124: 0 | V124: 0 | W124: 0 | X124: 0 | Y124: 0 | Z124: 0 | AA124: 0 | AB124: 0 | AC124: 0 | AD124: 0 | AE124: 0 | AF124: 0 | AG124: 0 | AH124: 0 | AI124: 0 | AJ124: 0 | AK124: 0 | AL124: 0 | AM124: 0 | AN124: 0 | AO124: 0 | AP124: 0 | AQ124: 0 | AR124: 0 | AS124: 0 | AT124: 0 | AU124: 0 | AV124: 0 | AW124: 0 | AX124: 0 | AY124: 0 | AZ124: 0 | BA124: 0 | BB124: 0 | BC124: 0 | BD124: 0 | BE124: 0 | BF124: 0 | BG124: 0 | BH124: 0 | BI124: 0 | BJ124: 0 | BK124: 0 | BL124: 0 | BM124: 0 | BN124: 0 | BO124: 0 | BP124: 0 | BQ124: 0 | BR124: 0 | BS124: 0 | BT124: 0 | BU124: 0 | BV124: 0 | BW124: 0 | BX124: 0
B125: INSTRUMENTOS FINANCIEROS A VALOR RAZONABLE | D125: 8393762.3 | E125: 8393477.4 | F125: 3734945.4 | G125: 4658532 | H125: 284.94 | I125: 0 | J125: 8215653 | K125: 8215368.1 | L125: 3561613.4 | M125: 4653754.7 | N125: 284.94 | O125: 3561898.4 | P125: 125766.73 | Q125: 125766.73 | R125: 120989.45 | S125: 4777.28 | T125: 52342.55 | U125: 52342.55 | V125: 0 | W125: 52342.55 | X125: 52342.55 | Y125: 52342.55 | Z125: 0 | AA125: 0 | AB125: 427324.46 | AC125: 13264.65 | AD125: 340822.47 | AE125: 1950641.7 | AF125: 121223.41 | AG125: 11413.63 | AH125: 3454783.1 | AI125: 517292.53 | AJ125: 0 | AK125: 648107.83 | AL125: 579592.35 | AM125: 284.94 | AN125: 4971.6 | AO125: 0 | AP125: 0 | AQ125: 10.68 | AR125: 0 | AS125: 0 | AT125: 0 | AU125: 0 | AV125: 0 | AW125: 114793.59 | AX125: 0 | AY125: 0 | AZ125: 0 | BA125: 31126.1 | BB125: 0 | BC125: 0 | BD125: 112521.1 | BE125: 0 | BF125: 4777.28 | BG125: 8468.35 | BH125: 0 | BI125: 52340.31 | BJ125: 0 | BK125: 0 | BL125: 2.24 | BM125: 0 | BN125: 0 | BO125: 0 | BP125: 0 | BQ125: 0 | BR125: 0 | BS125: 0 | BT125: 0 | BU125: 0 | BV125: 0 | BW125: 0 | BX125: 0
C126: CONTRATOS FORWARD - DE NEGOCIACIÓN | D126: 3306590.3 | E126: 3306489.8 | F126: 1491821.8 | G126: 1814668.1 | H126: 100.41 | I126: 0 | J126: 3202789.4 | K126: 3202689 | L126: 1392481.9 | M126: 1810207.2 | N126: 100.41 | O126: 1392582.3 | P126: 103800.83 | Q126: 103800.83 | R126: 99339.93 | S126: 4460.9 | T126: 0 | U126: 0 | V126: 0 | W126: 0 | X126: 0 | Y126: 0 | Z126: 0 | AA126: 0 | AB126: 205382.18 | AC126: 13264.65 | AD126: 87543.78 | AE126: 629401.96 | AF126: 109202.61 | AG126: 41.13 | AH126: 1194587.2 | AI126: 345148.77 | AJ126: 0 | AK126: 199284.29 | AL126: 297082.39 | AM126: 100.41 | AN126: 0 | AO126: 0 | AP126: 0 | AQ126: 0 | AR126: 0 | AS126: 0 | AT126: 0 | AU126: 0 | AV126: 0 | AW126: 99538.85 | AX126: 0 | AY126: 0 | AZ126: 0 | BA126: 22211.23 | BB126: 0 | BC126: 0 | BD126: 93378.27 | BE126: 0 | BF126: 4460.9 | BG126: 5961.66 | BH126: 0 | BI126: 0 | BJ126: 0 | BK126: 0 | BL126: 0 | BM126: 0 | BN126: 0 | BO126: 0 | BP126: 0 | BQ126: 0 | BR126: 0 | BS126: 0 | BT126: 0 | BU126: 0 | BV126: 0 | BW126: 0 | BX126: 0
C127: CONTRATOS DE FUTUROS – DE NEGOCIACIÓN | D127: 12070.86 | E127: 12070.86 | F127: 4971.6 | G127: 7099.26 | H127: 0 | I127: 0 | J127: 12070.86 | K127: 12070.86 | L127: 4971.6 | M127: 7099.26 | N127: 0 | O127: 4971.6 | P127: 0 | Q127: 0 | R127: 0 | S127: 0 | T127: 0 | U127: 0 | V127: 0 | W127: 0 | X127: 0 | Y127: 0 | Z127: 0 | AA127: 0 | AB127: 0 | AC127: 0 | AD127: 0 | AE127: 0 | AF127: 0 | AG127: 0 | AH127: 0 | AI127: 0 | AJ127: 0 | AK127: 0 | AL127: 0 | AM127: 0 | AN127: 4971.6 | AO127: 0 | AP127: 0 | AQ127: 0 | AR127: 0 | AS127: 0 | AT127: 0 | AU127: 0 | AV127: 0 | AW127: 0 | AX127: 0 | AY127: 0 | AZ127: 0 | BA127: 7099.26 | BB127: 0 | BC127: 0 | BD127: 0 | BE127: 0 | BF127: 0 | BG127: 0 | BH127: 0 | BI127: 0 | BJ127: 0 | BK127: 0 | BL127: 0 | BM127: 0 | BN127: 0 | BO127: 0 | BP127: 0 | BQ127: 0 | BR127: 0 | BS127: 0 | BT127: 0 | BU127: 0 | BV127: 0 | BW127: 0 | BX127: 0
C128: SWAPS – DE NEGOCIACIÓN | D128: 4768235.4 | E128: 4768050.8 | F128: 2002693 | G128: 2765357.9 | H128: 184.53 | I128: 0 | J128: 4763691.4 | K128: 4763506.8 | L128: 1998149 | M128: 2765357.9 | N128: 184.53 | O128: 1998333.5 | P128: 4544 | Q128: 4544 | R128: 4544 | S128: 0 | T128: 0 | U128: 0 | V128: 0 | W128: 0 | X128: 0 | Y128: 0 | Z128: 0 | AA128: 0 | AB128: 134971.42 | AC128: 0 | AD128: 213655.98 | AE128: 1259933.1 | AF128: 7339.69 | AG128: 363.65 | AH128: 2251545.3 | AI128: 161244.16 | AJ128: 0 | AK128: 442000.34 | AL128: 277441.89 | AM128: 184.53 | AN128: 0 | AO128: 0 | AP128: 0 | AQ128: 0 | AR128: 0 | AS128: 0 | AT128: 0 | AU128: 0 | AV128: 0 | AW128: 15011.37 | AX128: 0 | AY128: 0 | AZ128: 0 | BA128: 0 | BB128: 0 | BC128: 0 | BD128: 4544 | BE128: 0 | BF128: 0 | BG128: 0 | BH128: 0 | BI128: 0 | BJ128: 0 | BK128: 0 | BL128: 0 | BM128: 0 | BN128: 0 | BO128: 0 | BP128: 0 | BQ128: 0 | BR128: 0 | BS128: 0 | BT128: 0 | BU128: 0 | BV128: 0 | BW128: 0 | BX128: 0
C129: OPCIONES DE NEGOCIACIÓN | D129: 165216.89 | E129: 165216.89 | F129: 147280.39 | G129: 17936.5 | H129: 0 | I129: 0 | J129: 150655.08 | K129: 150655.08 | L129: 132718.58 | M129: 17936.5 | N129: 0 | O129: 132718.58 | P129: 14561.81 | Q129: 14561.81 | R129: 14561.81 | S129: 0 | T129: 0 | U129: 0 | V129: 0 | W129: 0 | X129: 0 | Y129: 0 | Z129: 0 | AA129: 0 | AB129: 53892.69 | AC129: 0 | AD129: 1681.57 | AE129: 61209.22 | AF129: 4041.43 | AG129: 0 | AH129: 7862.07 | AI129: 10899.6 | AJ129: 0 | AK129: 6717.07 | AL129: 4351.43 | AM129: 0 | AN129: 0 | AO129: 0 | AP129: 0 | AQ129: 0 | AR129: 0 | AS129: 0 | AT129: 0 | AU129: 0 | AV129: 0 | AW129: 0 | AX129: 0 | AY129: 0 | AZ129: 0 | BA129: 0 | BB129: 0 | BC129: 0 | BD129: 14561.81 | BE129: 0 | BF129: 0 | BG129: 0 | BH129: 0 | BI129: 0 | BJ129: 0 | BK129: 0 | BL129: 0 | BM129: 0 | BN129: 0 | BO129: 0 | BP129: 0 | BQ129: 0 | BR129: 0 | BS129: 0 | BT129: 0 | BU129: 0 | BV129: 0 | BW129: 0 | BX129: 0
C130: CONTRATOS FORWARD - DE COBERTURA | D130: 68171.77 | E130: 68171.77 | F130: 35523.28 | G130: 32648.49 | H130: 0 | I130: 0 | J130: 65664.7 | K130: 65664.7 | L130: 33016.21 | M130: 32648.49 | N130: 0 | O130: 33016.21 | P130: 2506.69 | Q130: 2506.69 | R130: 2506.69 | S130: 0 | T130: 0.38 | U130: 0.38 | V130: 0 | W130: 0.38 | X130: 0.38 | Y130: 0.38 | Z130: 0 | AA130: 0 | AB130: 33016.21 | AC130: 0 | AD130: 32648.49 | AE130: 0 | AF130: 0 | AG130: 0 | AH130: 0 | AI130: 0 | AJ130: 0 | AK130: 0 | AL130: 0 | AM130: 0 | AN130: 0 | AO130: 0 | AP130: 0 | AQ130: 0 | AR130: 0 | AS130: 0 | AT130: 0 | AU130: 0 | AV130: 0 | AW130: 0 | AX130: 0 | AY130: 0 | AZ130: 0 | BA130: 0 | BB130: 0 | BC130: 0 | BD130: 0 | BE130: 0 | BF130: 0 | BG130: 2506.69 | BH130: 0 | BI130: 0 | BJ130: 0 | BK130: 0 | BL130: 0.38 | BM130: 0 | BN130: 0 | BO130: 0 | BP130: 0 | BQ130: 0 | BR130: 0 | BS130: 0 | BT130: 0 | BU130: 0 | BV130: 0 | BW130: 0 | BX130: 0
C131: CONTRATOS DE FUTUROS – DE COBERTURA | D131: 0 | E131: 0 | F131: 0 | G131: 0 | H131: 0 | I131: 0 | J131: 0 | K131: 0 | L131: 0 | M131: 0 | N131: 0 | O131: 0 | P131: 0 | Q131: 0 | R131: 0 | S131: 0 | T131: 0 | U131: 0 | V131: 0 | W131: 0 | X131: 0 | Y131: 0 | Z131: 0 | AA131: 0 | AB131: 0 | AC131: 0 | AD131: 0 | AE131: 0 | AF131: 0 | AG131: 0 | AH131: 0 | AI131: 0 | AJ131: 0 | AK131: 0 | AL131: 0 | AM131: 0 | AN131: 0 | AO131: 0 | AP131: 0 | AQ131: 0 | AR131: 0 | AS131: 0 | AT131: 0 | AU131: 0 | AV131: 0 | AW131: 0 | AX131: 0 | AY131: 0 | AZ131: 0 | BA131: 0 | BB131: 0 | BC131: 0 | BD131: 0 | BE131: 0 | BF131: 0 | BG131: 0 | BH131: 0 | BI131: 0 | BJ131: 0 | BK131: 0 | BL131: 0 | BM131: 0 | BN131: 0 | BO131: 0 | BP131: 0 | BQ131: 0 | BR131: 0 | BS131: 0 | BT131: 0 | BU131: 0 | BV131: 0 | BW131: 0 | BX131: 0
C132: SWAPS – DE COBERTURA | D132: 5993.11 | E132: 5993.11 | F132: 0 | G132: 5993.11 | H132: 0 | I132: 0 | J132: 5993.11 | K132: 5993.11 | L132: 0 | M132: 5993.11 | N132: 0 | O132: 0 | P132: 0 | Q132: 0 | R132: 0 | S132: 0 | T132: 0 | U132: 0 | V132: 0 | W132: 0 | X132: 0 | Y132: 0 | Z132: 0 | AA132: 0 | AB132: 0 | AC132: 0 | AD132: 5292.65 | AE132: 0 | AF132: 0 | AG132: 0 | AH132: 0 | AI132: 0 | AJ132: 0 | AK132: 0 | AL132: 700.46 | AM132: 0 | AN132: 0 | AO132: 0 | AP132: 0 | AQ132: 0 | AR132: 0 | AS132: 0 | AT132: 0 | AU132: 0 | AV132: 0 | AW132: 0 | AX132: 0 | AY132: 0 | AZ132: 0 | BA132: 0 | BB132: 0 | BC132: 0 | BD132: 0 | BE132: 0 | BF132: 0 | BG132: 0 | BH132: 0 | BI132: 0 | BJ132: 0 | BK132: 0 | BL132: 0 | BM132: 0 | BN132: 0 | BO132: 0 | BP132: 0 | BQ132: 0 | BR132: 0 | BS132: 0 | BT132: 0 | BU132: 0 | BV132: 0 | BW132: 0 | BX132: 0
C133: OPCIONES DE COBERTURA | D133: 0 | E133: 0 | F133: 0 | G133: 0 | H133: 0 | I133: 0 | J133: 0 | K133: 0 | L133: 0 | M133: 0 | N133: 0 | O133: 0 | P133: 0 | Q133: 0 | R133: 0 | S133: 0 | T133: 0 | U133: 0 | V133: 0 | W133: 0 | X133: 0 | Y133: 0 | Z133: 0 | AA133: 0 | AB133: 0 | AC133: 0 | AD133: 0 | AE133: 0 | AF133: 0 | AG133: 0 | AH133: 0 | AI133: 0 | AJ133: 0 | AK133: 0 | AL133: 0 | AM133: 0 | AN133: 0 | AO133: 0 | AP133: 0 | AQ133: 0 | AR133: 0 | AS133: 0 | AT133: 0 | AU133: 0 | AV133: 0 | AW133: 0 | AX133: 0 | AY133: 0 | AZ133: 0 | BA133: 0 | BB133: 0 | BC133: 0 | BD133: 0 | BE133: 0 | BF133: 0 | BG133: 0 | BH133: 0 | BI133: 0 | BJ133: 0 | BK133: 0 | BL133: 0 | BM133: 0 | BN133: 0 | BO133: 0 | BP133: 0 | BQ133: 0 | BR133: 0 | BS133: 0 | BT133: 0 | BU133: 0 | BV133: 0 | BW133: 0 | BX133: 0
C134: TÍTULOS DE INVERSIÓN EN CIRCULACIÓN | D134: 0 | E134: 0 | F134: 0 | G134: 0 | H134: 0 | I134: 0 | J134: 0 | K134: 0 | L134: 0 | M134: 0 | N134: 0 | O134: 0 | P134: 0 | Q134: 0 | R134: 0 | S134: 0 | T134: 0 | U134: 0 | V134: 0 | W134: 0 | X134: 0 | Y134: 0 | Z134: 0 | AA134: 0 | AB134: 0 | AC134: 0 | AD134: 0 | AE134: 0 | AF134: 0 | AG134: 0 | AH134: 0 | AI134: 0 | AJ134: 0 | AK134: 0 | AL134: 0 | AM134: 0 | AN134: 0 | AO134: 0 | AP134: 0 | AQ134: 0 | AR134: 0 | AS134: 0 | AT134: 0 | AU134: 0 | AV134: 0 | AW134: 0 | AX134: 0 | AY134: 0 | AZ134: 0 | BA134: 0 | BB134: 0 | BC134: 0 | BD134: 0 | BE134: 0 | BF134: 0 | BG134: 0 | BH134: 0 | BI134: 0 | BJ134: 0 | BK134: 0 | BL134: 0 | BM134: 0 | BN134: 0 | BO134: 0 | BP134: 0 | BQ134: 0 | BR134: 0 | BS134: 0 | BT134: 0 | BU134: 0 | BV134: 0 | BW134: 0 | BX134: 0
C135: OPERACIONES DE CONTADO | D135: 67484.06 | E135: 67484.06 | F135: 52655.39 | G135: 14828.67 | H135: 0 | I135: 0 | J135: 14788.49 | K135: 14788.49 | L135: 276.2 | M135: 14512.29 | N135: 0 | O135: 276.2 | P135: 353.4 | Q135: 353.4 | R135: 37.02 | S135: 316.38 | T135: 52342.17 | U135: 52342.17 | V135: 0 | W135: 52342.17 | X135: 52342.17 | Y135: 52342.17 | Z135: 0 | AA135: 0 | AB135: 61.96 | AC135: 0 | AD135: 0 | AE135: 97.43 | AF135: 639.68 | AG135: 11008.85 | AH135: 788.6 | AI135: 0 | AJ135: 0 | AK135: 106.13 | AL135: 16.18 | AM135: 0 | AN135: 0 | AO135: 0 | AP135: 0 | AQ135: 10.68 | AR135: 0 | AS135: 0 | AT135: 0 | AU135: 0 | AV135: 0 | AW135: 243.37 | AX135: 0 | AY135: 0 | AZ135: 0 | BA135: 1815.61 | BB135: 0 | BC135: 0 | BD135: 37.02 | BE135: 0 | BF135: 316.38 | BG135: 0 | BH135: 0 | BI135: 52340.31 | BJ135: 0 | BK135: 0 | BL135: 1.86 | BM135: 0 | BN135: 0 | BO135: 0 | BP135: 0 | BQ135: 0 | BR135: 0 | BS135: 0 | BT135: 0 | BU135: 0 | BV135: 0 | BW135: 0 | BX135: 0
B136: APORTES DE CAPITAL | D136: 24075.07 | E136: 16323.07 | F136: 16323.07 | G136: 0 | H136: 0 | I136: 7752 | J136: 16323.07 | K136: 16323.07 | L136: 16323.07 | M136: 0 | N136: 0 | O136: 16323.07 | P136: 0 | Q136: 0 | R136: 0 | S136: 0 | T136: 0 | U136: 0 | V136: 0 | W136: 0 | X136: 0 | Y136: 0 | Z136: 0 | AA136: 7752 | AB136: 0 | AC136: 0 | AD136: 0 | AE136: 0 | AF136: 0 | AG136: 0 | AH136: 0 | AI136: 0 | AJ136: 0 | AK136: 0 | AL136: 0 | AM136: 0 | AN136: 0 | AO136: 0 | AP136: 0 | AQ136: 0 | AR136: 0 | AS136: 0 | AT136: 0 | AU136: 0 | AV136: 16323.07 | AW136: 0 | AX136: 0 | AY136: 0 | AZ136: 0 | BA136: 0 | BB136: 0 | BC136: 0 | BD136: 0 | BE136: 0 | BF136: 0 | BG136: 0 | BH136: 0 | BI136: 0 | BJ136: 0 | BK136: 0 | BL136: 0 | BM136: 0 | BN136: 0 | BO136: 0 | BP136: 0 | BQ136: 0 | BR136: 0 | BS136: 0 | BT136: 1848.76 | BU136: 0 | BV136: 690.48 | BW136: 5212.76 | BX136: 0
B137: CRÉDITOS DE BANCOS Y OTRAS OBLIGACIONES FINANCIERAS | D137: 52722787 | E137: 43361213 | F137: 30781984 | G137: 12579229 | H137: 9178901.4 | I137: 182672.83 | J137: 49793207 | K137: 40614305 | L137: 30673843 | M137: 9940462.6 | N137: 9178901.4 | O137: 39852744 | P137: 43948.25 | Q137: 43948.25 | R137: 43948.25 | S137: 0 | T137: 2702959.4 | U137: 64193.01 | V137: 2638766.4 | W137: 2702959.4 | X137: 2702959.4 | Y137: 64193.01 | Z137: 2638766.4 | AA137: 182672.83 | AB137: 6210242.8 | AC137: 954284.8 | AD137: 2833833.4 | AE137: 9022340.2 | AF137: 0 | AG137: 1363570.8 | AH137: 2974166.1 | AI137: 3427188 | AJ137: 121674.69 | AK137: 9029583.3 | AL137: 1586317.7 | AM137: 9178901.4 | AN137: 125326.87 | AO137: 138361.08 | AP137: 524802.03 | AQ137: 85180.72 | AR137: 74105.94 | AS137: 408442.46 | AT137: 483079.75 | AU137: 363416.03 | AV137: 7045.54 | AW137: 336064.11 | AX137: 217088.01 | AY137: 248374.97 | AZ137: 79801.12 | BA137: 0 | BB137: 0 | BC137: 14.72 | BD137: 0 | BE137: 0 | BF137: 0 | BG137: 43948.25 | BH137: 0 | BI137: 4665.35 | BJ137: 51.39 | BK137: 958686.27 | BL137: 0 | BM137: 1605.97 | BN137: 25163.36 | BO137: 213079.36 | BP137: 100100.3 | BQ137: 32706.94 | BR137: 1366888.4 | BS137: 12.09 | BT137: 23650.42 | BU137: 0 | BV137: 33479.61 | BW137: 25301.23 | BX137: 100241.57
C138: BANCO DE LA REPÚBLICA | D138: 0 | E138: 0 | F138: 0 | G138: 0 | H138: 0 | I138: 0 | J138: 0 | K138: 0 | L138: 0 | M138: 0 | N138: 0 | O138: 0 | P138: 0 | Q138: 0 | R138: 0 | S138: 0 | T138: 0 | U138: 0 | V138: 0 | W138: 0 | X138: 0 | Y138: 0 | Z138: 0 | AA138: 0 | AB138: 0 | AC138: 0 | AD138: 0 | AE138: 0 | AF138: 0 | AG138: 0 | AH138: 0 | AI138: 0 | AJ138: 0 | AK138: 0 | AL138: 0 | AM138: 0 | AN138: 0 | AO138: 0 | AP138: 0 | AQ138: 0 | AR138: 0 | AS138: 0 | AT138: 0 | AU138: 0 | AV138: 0 | AW138: 0 | AX138: 0 | AY138: 0 | AZ138: 0 | BA138: 0 | BB138: 0 | BC138: 0 | BD138: 0 | BE138: 0 | BF138: 0 | BG138: 0 | BH138: 0 | BI138: 0 | BJ138: 0 | BK138: 0 | BL138: 0 | BM138: 0 | BN138: 0 | BO138: 0 | BP138: 0 | BQ138: 0 | BR138: 0 | BS138: 0 | BT138: 0 | BU138: 0 | BV138: 0 | BW138: 0 | BX138: 0
C139: BANCO DE COMERCIO EXTERIOR (BANCOLDEX) | D139: 4407857.2 | E139: 4252527.4 | F139: 3230129.2 | G139: 1022398.2 | H139: 79412.51 | I139: 75917.25 | J139: 4236202.9 | K139: 4156790.4 | L139: 3207631.6 | M139: 949158.83 | N139: 79412.51 | O139: 3287044.1 | P139: 0 | Q139: 0 | R139: 0 | S139: 0 | T139: 95736.98 | U139: 22497.62 | V139: 73239.36 | W139: 95736.98 | X139: 95736.98 | Y139: 22497.62 | Z139: 73239.36 | AA139: 75917.25 | AB139: 425456.53 | AC139: 75298.81 | AD139: 104786.12 | AE139: 876498.31 | AF139: 0 | AG139: 131584.08 | AH139: 502652.32 | AI139: 318270.34 | AJ139: 121665.54 | AK139: 612814.19 | AL139: 89447.08 | AM139: 79412.51 | AN139: 3922.51 | AO139: 823.7 | AP139: 66504.16 | AQ139: 84889.09 | AR139: 29264.6 | AS139: 240821.37 | AT139: 0 | AU139: 106747.9 | AV139: 6841.1 | AW139: 13941.33 | AX139: 134397.54 | AY139: 177553.41 | AZ139: 32610.4 | BA139: 0 | BB139: 0 | BC139: 0 | BD139: 0 | BE139: 0 | BF139: 0 | BG139: 0 | BH139: 0 | BI139: 0 | BJ139: 0 | BK139: 0 | BL139: 0 | BM139: 735.51 | BN139: 1983.5 | BO139: 73239.36 | BP139: 0 | BQ139: 19778.61 | BR139: 0 | BS139: 0 | BT139: 1094.72 | BU139: 0 | BV139: 19391.81 | BW139: 0 | BX139: 55430.72
C140: FONDOS DE GARANTÍAS | D140: 0 | E140: 0 | F140: 0 | G140: 0 | H140: 0 | I140: 0 | J140: 0 | K140: 0 | L140: 0 | M140: 0 | N140: 0 | O140: 0 | P140: 0 | Q140: 0 | R140: 0 | S140: 0 | T140: 0 | U140: 0 | V140: 0 | W140: 0 | X140: 0 | Y140: 0 | Z140: 0 | AA140: 0 | AB140: 0 | AC140: 0 | AD140: 0 | AE140: 0 | AF140: 0 | AG140: 0 | AH140: 0 | AI140: 0 | AJ140: 0 | AK140: 0 | AL140: 0 | AM140: 0 | AN140: 0 | AO140: 0 | AP140: 0 | AQ140: 0 | AR140: 0 | AS140: 0 | AT140: 0 | AU140: 0 | AV140: 0 | AW140: 0 | AX140: 0 | AY140: 0 | AZ140: 0 | BA140: 0 | BB140: 0 | BC140: 0 | BD140: 0 | BE140: 0 | BF140: 0 | BG140: 0 | BH140: 0 | BI140: 0 | BJ140: 0 | BK140: 0 | BL140: 0 | BM140: 0 | BN140: 0 | BO140: 0 | BP140: 0 | BQ140: 0 | BR140: 0 | BS140: 0 | BT140: 0 | BU140: 0 | BV140: 0 | BW140: 0 | BX140: 0
C141: FINAGRO | D141: 11369275 | E141: 2280595.5 | F141: 1681135.1 | G141: 599460.4 | H141: 9055947.5 | I141: 32731.72 | J141: 11326350 | K141: 2270402.1 | L141: 1680264.6 | M141: 590137.52 | N141: 9055947.5 | O141: 10736212 | P141: 0 | Q141: 0 | R141: 0 | S141: 0 | T141: 10193.33 | U141: 870.45 | V141: 9322.88 | W141: 10193.33 | X141: 10193.33 | Y141: 870.45 | Z141: 9322.88 | AA141: 32731.72 | AB141: 272979.52 | AC141: 87321 | AD141: 6463.68 | AE141: 836184.77 | AF141: 0 | AG141: 11458.33 | AH141: 527922.7 | AI141: 34069.8 | AJ141: 9.15 | AK141: 375776.96 | AL141: 44292.81 | AM141: 9055947.5 | AN141: 20.86 | AO141: 0 | AP141: 38109.81 | AQ141: 291.63 | AR141: 0 | AS141: 52.05 | AT141: 0 | AU141: 0 | AV141: 11.25 | AW141: 0 | AX141: 0 | AY141: 0 | AZ141: 35437.81 | BA141: 0 | BB141: 0 | BC141: 0 | BD141: 0 | BE141: 0 | BF141: 0 | BG141: 0 | BH141: 0 | BI141: 0 | BJ141: 0 | BK141: 0 | BL141: 0 | BM141: 870.45 | BN141: 0 | BO141: 9322.88 | BP141: 0 | BQ141: 0 | BR141: 0 | BS141: 0 | BT141: 16934.94 | BU141: 0 | BV141: 0 | BW141: 3796.15 | BX141: 12000.63
C142: FINDETER | D142: 8166418.8 | E142: 8113631.5 | F142: 6126167.8 | G142: 1987463.7 | H142: 43420.4 | I142: 9366.88 | J142: 8149181.6 | K142: 8105761.2 | L142: 6118297.6 | M142: 1987463.7 | N142: 43420.4 | O142: 6161718 | P142: 0 | Q142: 0 | R142: 0 | S142: 0 | T142: 7870.26 | U142: 7870.26 | V142: 0 | W142: 7870.26 | X142: 7870.26 | Y142: 7870.26 | Z142: 0 | AA142: 9366.88 | AB142: 1088441.5 | AC142: 300092.71 | AD142: 263932.45 | AE142: 2259714 | AF142: 0 | AG142: 514885.16 | AH142: 1048112 | AI142: 599485.37 | AJ142: 0 | AK142: 1809386.9 | AL142: 77136.14 | AM142: 43420.4 | AN142: 4877.67 | AO142: 0 | AP142: 0 | AQ142: 0 | AR142: 44546.55 | AS142: 0 | AT142: 0 | AU142: 75622.06 | AV142: 0 | AW142: 7775.83 | AX142: 0 | AY142: 0 | AZ142: 11752.91 | BA142: 0 | BB142: 0 | BC142: 0 | BD142: 0 | BE142: 0 | BF142: 0 | BG142: 0 | BH142: 0 | BI142: 0 | BJ142: 0 | BK142: 0 | BL142: 0 | BM142: 0 | BN142: 7870.26 | BO142: 0 | BP142: 0 | BQ142: 0 | BR142: 0 | BS142: 0 | BT142: 0 | BU142: 0 | BV142: 0 | BW142: 9366.88 | BX142: 0
C143: FINANCIERA ENERGÉTICA NACIONAL (FEN) | D143: 0 | E143: 0 | F143: 0 | G143: 0 | H143: 0 | I143: 0 | J143: 0 | K143: 0 | L143: 0 | M143: 0 | N143: 0 | O143: 0 | P143: 0 | Q143: 0 | R143: 0 | S143: 0 | T143: 0 | U143: 0 | V143: 0 | W143: 0 | X143: 0 | Y143: 0 | Z143: 0 | AA143: 0 | AB143: 0 | AC143: 0 | AD143: 0 | AE143: 0 | AF143: 0 | AG143: 0 | AH143: 0 | AI143: 0 | AJ143: 0 | AK143: 0 | AL143: 0 | AM143: 0 | AN143: 0 | AO143: 0 | AP143: 0 | AQ143: 0 | AR143: 0 | AS143: 0 | AT143: 0 | AU143: 0 | AV143: 0 | AW143: 0 | AX143: 0 | AY143: 0 | AZ143: 0 | BA143: 0 | BB143: 0 | BC143: 0 | BD143: 0 | BE143: 0 | BF143: 0 | BG143: 0 | BH143: 0 | BI143: 0 | BJ143: 0 | BK143: 0 | BL143: 0 | BM143: 0 | BN143: 0 | BO143: 0 | BP143: 0 | BQ143: 0 | BR143: 0 | BS143: 0 | BT143: 0 | BU143: 0 | BV143: 0 | BW143: 0 | BX143: 0
C144: FONDO DE DESARROLLO ELÉCTRICO | D144: 0 | E144: 0 | F144: 0 | G144: 0 | H144: 0 | I144: 0 | J144: 0 | K144: 0 | L144: 0 | M144: 0 | N144: 0 | O144: 0 | P144: 0 | Q144: 0 | R144: 0 | S144: 0 | T144: 0 | U144: 0 | V144: 0 | W144: 0 | X144: 0 | Y144: 0 | Z144: 0 | AA144: 0 | AB144: 0 | AC144: 0 | AD144: 0 | AE144: 0 | AF144: 0 | AG144: 0 | AH144: 0 | AI144: 0 | AJ144: 0 | AK144: 0 | AL144: 0 | AM144: 0 | AN144: 0 | AO144: 0 | AP144: 0 | AQ144: 0 | AR144: 0 | AS144: 0 | AT144: 0 | AU144: 0 | AV144: 0 | AW144: 0 | AX144: 0 | AY144: 0 | AZ144: 0 | BA144: 0 | BB144: 0 | BC144: 0 | BD144: 0 | BE144: 0 | BF144: 0 | BG144: 0 | BH144: 0 | BI144: 0 | BJ144: 0 | BK144: 0 | BL144: 0 | BM144: 0 | BN144: 0 | BO144: 0 | BP144: 0 | BQ144: 0 | BR144: 0 | BS144: 0 | BT144: 0 | BU144: 0 | BV144: 0 | BW144: 0 | BX144: 0
C145: OTROS BANCOS Y ENTIDADES FINANCIERAS PAÍS | D145: 3745762.5 | E145: 3682214.6 | F145: 586565.63 | G145: 3095649 | H145: 0 | I145: 63547.93 | J145: 1251567.6 | K145: 1251567.6 | L145: 553610.95 | M145: 697956.62 | N145: 0 | O145: 553610.95 | P145: 0 | Q145: 0 | R145: 0 | S145: 0 | T145: 2430647 | U145: 32954.68 | V145: 2397692.3 | W145: 2430647 | X145: 2430647 | Y145: 32954.68 | Z145: 2397692.3 | AA145: 63547.93 | AB145: 0 | AC145: 0 | AD145: 0 | AE145: 0 | AF145: 0 | AG145: 33855.11 | AH145: 0 | AI145: 0 | AJ145: 0 | AK145: 0 | AL145: 0 | AM145: 0 | AN145: 0 | AO145: 39534.16 | AP145: 360076.78 | AQ145: 0 | AR145: 294.79 | AS145: 0 | AT145: 483079.75 | AU145: 181007.04 | AV145: 193.19 | AW145: 0 | AX145: 82690.47 | AY145: 70821.56 | AZ145: 0 | BA145: 0 | BB145: 0 | BC145: 14.72 | BD145: 0 | BE145: 0 | BF145: 0 | BG145: 0 | BH145: 0 | BI145: 4665.35 | BJ145: 51.39 | BK145: 958686.27 | BL145: 0 | BM145: 0 | BN145: 15309.6 | BO145: 39462.68 | BP145: 32655 | BQ145: 12928.34 | BR145: 1366888.4 | BS145: 0 | BT145: 4511.72 | BU145: 0 | BV145: 14087.8 | BW145: 12138.2 | BX145: 32810.21
...

Sheet 2022
C1: Identificador | D1: +1+2+4+32+22-0-0-0-0-0-0-0-0 | E1: 0-+1-0-0-0-0-0-0-0 | F1: 0-+1-+1-0-0-0-0-0-0 | G1: 0-+1-+2-0-0-0-0-0-0 | H1: 0-+2-0-0-0-0-0-0-0 | I1: 32-3-0-0-0-0-0-0-0 | J1: 1-0-0-0-0-0-0-0-0 | K1: 1-1-0-0-0-0-0-0-0 | L1: 0-0-0-0-0-+200-0-0-0 | M1: +1-0-+2-0-0-0-0-0-0 | N1: 0-0-0-0-0-+100-0-0-0 | O1: 1-0-1-0-0-0-0-0-0 | P1: 2-0-0-0-0-0-0-0-0 | Q1: 2-1-0-0-0-0-0-0-0 | R1: 2-1-1-0-0-0-0-0-0 | S1: 2-1-2-0-0-0-0-0-0 | T1: +4-0-0-0-0-0-0-0-0 | U1: 4-0-1-0-0-0-0-0-0 | V1: 4-0-2-0-0-0-0-0-0 | W1: 4-0-0-1-0-0-0-0-0 | X1: 4-1-0-1-0-0-0-0-0 | Y1: 4-1-1-1-0-0-0-0-0 | Z1: 4-1-2-1-0-0-0-0-0 | AA1: +32-3-0-0-0-0-0-0-0 | AB1: 1-1-1-1-1-200-1-1- | AC1: 1-1-1-1-2-200-1-1- | AD1: 1-1-2-1-6-0-1-1- | AE1: 1-1-1-1-7-200-1-2- | AF1: 1-1-2-1-9-0-1-3- | AG1: 1-1-2-1-12-0-1-3- | AH1: 1-1-2-1-13-0-1-3- | AI1: 1-1-1-1-23-200-1-1- | AJ1: 1-1-1-2-30-200-7-3- | AK1: 1-1-1-2-39-200-7-2- | AL1: 1-1-2-2-42-0-7-3- | AM1: 1-2-1-1-43-100-1-2- | AN1: 1-1-1-2-49-200-7-1- | AO1: 1-1-1-1-51-200-6-3- | AP1: 1-1-1-1-52-200-6-3- | AQ1: 1-1-1-1-53-200-6-3- | AR1: 1-1-1-1-54-200-6-3- | AS1: 1-1-1-1-55-200-6-3- | AT1: 1-1-2-1-56-0-6-3- | AU1: 1-1-2-1-57-0-6-3- | AV1: 1-1-1-1-58-200-1-3- | AW1: 1-1-2-1-59-0-1-1- | AX1: 1-1-1-1-60-200-1-1- | AY1: 1-1-1-1-62-200-1-1- | AZ1: 1-1-1-1-63-200-1-1- | BA1: 1-1-2-1-64-0-1-1- | BB1: 1-1-1-1-65-200-1-1- | BC1: 1-1-2-1-66-0-1-1- | BD1: 1-1-1-1-67-200-1-1- | BE1: 2-1-1-4-11-0-1-1- | BF1: 2-1-1-4-37-0-1-2- | BG1: 2-1-2-4-42-0-2-0- | BH1: 2-1-1-4-48-0-2-0- | BI1: 2-1-1-4-49-0-2-0- | BJ1: 4-1-1-1-26-0-1-2- | BK1: 4-1-2-1-31-0-1-3- | BL1: 4-1-1-1-46-0-6-1- | BM1: 4-1-1-1-108-0-1-2- | BN1: 4-1-1-1-117-0-0-3- | BO1: 4-1-2-1-118-0-0-3- | BP1: 4-1-2-1-120-0-0-3- | BQ1: 4-1-1-1-121-0-0-3- | BR1: 4-1-2-1-122-0-0-3- | BS1: 4-1-2-1-123-0-0-3- | BT1: 4-1-2-1-125-0-0-3- | BU1: 32-3-1-1-1-0-1-1-300 | BV1: 32-3-1-1-2-0-1-3-300 | BW1: 32-3-1-1-3-0-1-2-300 | BX1: 32-3-1-1-4-0-1-2-300 | BY1: 32-3-1-1-5-0-1-3-300
C2: Tipo | D2: +1+2+4+32+22 | E2: 0 | F2: 0 | G2: 0 | H2: 0 | I2: 32 | J2: 1 | K2: 1 | L2: 0 | M2: +1 | N2: 0 | O2: 1 | P2: 2 | Q2: 2 | R2: 2 | S2: 2 | T2: +4 | U2: 4 | V2: 4 | W2: 4 | X2: 4 | Y2: 4 | Z2: 4 | AA2: +32 | AB2: 1 | AC2: 1 | AD2: 1 | AE2: 1 | AF2: 1 | AG2: 1 | AH2: 1 | AI2: 1 | AJ2: 1 | AK2: 1 | AL2: 1 | AM2: 1 | AN2: 1 | AO2: 1 | AP2: 1 | AQ2: 1 | AR2: 1 | AS2: 1 | AT2: 1 | AU2: 1 | AV2: 1 | AW2: 1 | AX2: 1 | AY2: 1 | AZ2: 1 | BA2: 1 | BB2: 1 | BC2: 1 | BD2: 1 | BE2: 2 | BF2: 2 | BG2: 2 | BH2: 2 | BI2: 2 | BJ2: 4 | BK2: 4 | BL2: 4 | BM2: 4 | BN2: 4 | BO2: 4 | BP2: 4 | BQ2: 4 | BR2: 4 | BS2: 4 | BT2: 4 | BU2: 32 | BV2: 32 | BW2: 32 | BX2: 32 | BY2: 32
C3: Clase | D3: 0 | E3: +1 | F3: +1 | G3: +1 | H3: +2 | I3: 3 | J3: 0 | K3: 1 | L3: 0 | M3: 0 | N3: 0 | O3: 0 | P3: 0 | Q3: 1 | R3: 1 | S3: 1 | T3: 0 | U3: 0 | V3: 0 | W3: 0 | X3: 1 | Y3: 1 | Z3: 1 | AA3: 3 | AB3: 1 | AC3: 1 | AD3: 1 | AE3: 1 | AF3: 1 | AG3: 1 | AH3: 1 | AI3: 1 | AJ3: 1 | AK3: 1 | AL3: 1 | AM3: 2 | AN3: 1 | AO3: 1 | AP3: 1 | AQ3: 1 | AR3: 1 | AS3: 1 | AT3: 1 | AU3: 1 | AV3: 1 | AW3: 1 | AX3: 1 | AY3: 1 | AZ3: 1 | BA3: 1 | BB3: 1 | BC3: 1 | BD3: 1 | BE3: 1 | BF3: 1 | BG3: 1 | BH3: 1 | BI3: 1 | BJ3: 1 | BK3: 1 | BL3: 1 | BM3: 1 | BN3: 1 | BO3: 1 | BP3: 1 | BQ3: 1 | BR3: 1 | BS3: 1 | BT3: 1 | BU3: 3 | BV3: 3 | BW3: 3 | BX3: 3 | BY3: 3
C4: Origen | D4: 0 | E4: 0 | F4: +1 | G4: +2 | H4: 0 | I4: 0 | J4: 0 | K4: 0 | L4: 0 | M4: +2 | N4: 0 | O4: 1 | P4: 0 | Q4: 0 | R4: 1 | S4: 2 | T4: 0 | U4: 1 | V4: 2 | W4: 0 | X4: 0 | Y4: 1 | Z4: 2 | AA4: 0 | AB4: 1 | AC4: 1 | AD4: 2 | AE4: 1 | AF4: 2 | AG4: 2 | AH4: 2 | AI4: 1 | AJ4: 1 | AK4: 1 | AL4: 2 | AM4: 1 | AN4: 1 | AO4: 1 | AP4: 1 | AQ4: 1 | AR4: 1 | AS4: 1 | AT4: 2 | AU4: 2 | AV4: 1 | AW4: 2 | AX4: 1 | AY4: 1 | AZ4: 1 | BA4: 2 | BB4: 1 | BC4: 2 | BD4: 1 | BE4: 1 | BF4: 1 | BG4: 2 | BH4: 1 | BI4: 1 | BJ4: 1 | BK4: 2 | BL4: 1 | BM4: 1 | BN4: 1 | BO4: 2 | BP4: 2 | BQ4: 1 | BR4: 2 | BS4: 2 | BT4: 2 | BU4: 1 | BV4: 1 | BW4: 1 | BX4: 1 | BY4: 1
C5: Categoría | D5: 0 | E5: 0 | F5: 0 | G5: 0 | H5: 0 | I5: 0 | J5: 0 | K5: 0 | L5: 0 | M5: 0 | N5: 0 | O5: 0 | P5: 0 | Q5: 0 | R5: 0 | S5: 0 | T5: 0 | U5: 0 | V5: 0 | W5: 1 | X5: 1 | Y5: 1 | Z5: 1 | AA5: 0 | AB5: 1 | AC5: 1 | AD5: 1 | AE5: 1 | AF5: 1 | AG5: 1 | AH5: 1 | AI5: 1 | AJ5: 2 | AK5: 2 | AL5: 2 | AM5: 1 | AN5: 2 | AO5: 1 | AP5: 1 | AQ5: 1 | AR5: 1 | AS5: 1 | AT5: 1 | AU5: 1 | AV5: 1 | AW5: 1 | AX5: 1 | AY5: 1 | AZ5: 1 | BA5: 1 | BB5: 1 | BC5: 1 | BD5: 1 | BE5: 4 | BF5: 4 | BG5: 4 | BH5: 4 | BI5: 4 | BJ5: 1 | BK5: 1 | BL5: 1 | BM5: 1 | BN5: 1 | BO5: 1 | BP5: 1 | BQ5: 1 | BR5: 1 | BS5: 1 | BT5: 1 | BU5: 1 | BV5: 1 | BW5: 1 | BX5: 1 | BY5: 1
C6: Código | D6: 0 | E6: 0 | F6: 0 | G6: 0 | H6: 0 | I6: 0 | J6: 0 | K6: 0 | L6: 0 | M6: 0 | N6: 0 | O6: 0 | P6: 0 | Q6: 0 | R6: 0 | S6: 0 | T6: 0 | U6: 0 | V6: 0 | W6: 0 | X6: 0 | Y6: 0 | Z6: 0 | AA6: 0 | AB6: 1 | AC6: 2 | AD6: 6 | AE6: 7 | AF6: 9 | AG6: 12 | AH6: 13 | AI6: 23 | AJ6: 30 | AK6: 39 | AL6: 42 | AM6: 43 | AN6: 49 | AO6: 51 | AP6: 52 | AQ6: 53 | AR6: 54 | AS6: 55 | AT6: 56 | AU6: 57 | AV6: 58 | AW6: 59 | AX6: 60 | AY6: 62 | AZ6: 63 | BA6: 64 | BB6: 65 | BC6: 66 | BD6: 67 | BE6: 11 | BF6: 37 | BG6: 42 | BH6: 48 | BI6: 49 | BJ6: 26 | BK6: 31 | BL6: 46 | BM6: 108 | BN6: 117 | BO6: 118 | BP6: 120 | BQ6: 121 | BR6: 122 | BS6: 123 | BT6: 125 | BU6: 1 | BV6: 2 | BW6: 3 | BX6: 4 | BY6: 5
C7: Gupo | D7: 0 | E7: 0 | F7: 0 | G7: 0 | H7: 0 | I7: 0 | J7: 0 | K7: 0 | L7: +200 | M7: 0 | N7: +100 | O7: 0 | P7: 0 | Q7: 0 | R7: 0 | S7: 0 | T7: 0 | U7: 0 | V7: 0 | W7: 0 | X7: 0 | Y7: 0 | Z7: 0 | AA7: 0 | AB7: 200 | AC7: 200 | AD7: 0 | AE7: 200 | AF7: 0 | AG7: 0 | AH7: 0 | AI7: 200 | AJ7: 200 | AK7: 200 | AL7: 0 | AM7: 100 | AN7: 200 | AO7: 200 | AP7: 200 | AQ7: 200 | AR7: 200 | AS7: 200 | AT7: 0 | AU7: 0 | AV7: 200 | AW7: 0 | AX7: 200 | AY7: 200 | AZ7: 200 | BA7: 0 | BB7: 200 | BC7: 0 | BD7: 200 | BE7: 0 | BF7: 0 | BG7: 0 | BH7: 0 | BI7: 0 | BJ7: 0 | BK7: 0 | BL7: 0 | BM7: 0 | BN7: 0 | BO7: 0 | BP7: 0 | BQ7: 0 | BR7: 0 | BS7: 0 | BT7: 0 | BU7: 0 | BV7: 0 | BW7: 0 | BX7: 0 | BY7: 0
C8: Estado | D8: 0 | E8: 0 | F8: 0 | G8: 0 | H8: 0 | I8: 0 | J8: 0 | K8: 0 | L8: 0 | M8: 0 | N8: 0 | O8: 0 | P8: 0 | Q8: 0 | R8: 0 | S8: 0 | T8: 0 | U8: 0 | V8: 0 | W8: 0 | X8: 0 | Y8: 0 | Z8: 0 | AA8: 0 | AB8: 1 | AC8: 1 | AD8: 1 | AE8: 1 | AF8: 1 | AG8: 1 | AH8: 1 | AI8: 1 | AJ8: 7 | AK8: 7 | AL8: 7 | AM8: 1 | AN8: 7 | AO8: 6 | AP8: 6 | AQ8: 6 | AR8: 6 | AS8: 6 | AT8: 6 | AU8: 6 | AV8: 1 | AW8: 1 | AX8: 1 | AY8: 1 | AZ8: 1 | BA8: 1 | BB8: 1 | BC8: 1 | BD8: 1 | BE8: 1 | BF8: 1 | BG8: 2 | BH8: 2 | BI8: 2 | BJ8: 1 | BK8: 1 | BL8: 6 | BM8: 1 | BN8: 0 | BO8: 0 | BP8: 0 | BQ8: 0 | BR8: 0 | BS8: 0 | BT8: 0 | BU8: 1 | BV8: 1 | BW8: 1 | BX8: 1 | BY8: 1
C9: Delegatura | D9: 0 | E9: 0 | F9: 0 | G9: 0 | H9: 0 | I9: 0 | J9: 0 | K9: 0 | L9: 0 | M9: 0 | N9: 0 | O9: 0 | P9: 0 | Q9: 0 | R9: 0 | S9: 0 | T9: 0 | U9: 0 | V9: 0 | W9: 0 | X9: 0 | Y9: 0 | Z9: 0 | AA9: 0 | AB9: 1 | AC9: 1 | AD9: 1 | AE9: 2 | AF9: 3 | AG9: 3 | AH9: 3 | AI9: 1 | AJ9: 3 | AK9: 2 | AL9: 3 | AM9: 2 | AN9: 1 | AO9: 3 | AP9: 3 | AQ9: 3 | AR9: 3 | AS9: 3 | AT9: 3 | AU9: 3 | AV9: 3 | AW9: 1 | AX9: 1 | AY9: 1 | AZ9: 1 | BA9: 1 | BB9: 1 | BC9: 1 | BD9: 1 | BE9: 1 | BF9: 2 | BG9: 0 | BH9: 0 | BI9: 0 | BJ9: 2 | BK9: 3 | BL9: 1 | BM9: 2 | BN9: 3 | BO9: 3 | BP9: 3 | BQ9: 3 | BR9: 3 | BS9: 3 | BT9: 3 | BU9: 1 | BV9: 3 | BW9: 2 | BX9: 2 | BY9: 3
C10: Director Técnico | D10: 0 | E10: 0 | F10: 0 | G10: 0 | H10: 0 | I10: 0 | J10: 0 | K10: 0 | L10: 0 | M10: 0 | N10: 0 | O10: 0 | P10: 0 | Q10: 0 | R10: 0 | S10: 0 | T10: 0 | U10: 0 | V10: 0 | W10: 0 | X10: 0 | Y10: 0 | Z10: 0 | AA10: 0 | AB10: 0 | AC10: 0 | AD10: 0 | AE10: 0 | AF10: 0 | AG10: 0 | AH10: 0 | AI10: 0 | AJ10: 0 | AK10: 0 | AL10: 0 | AM10: 0 | AN10: 0 | AO10: 0 | AP10: 0 | AQ10: 0 | AR10: 0 | AS10: 0 | AT10: 0 | AU10: 0 | AV10: 0 | AW10: 0 | AX10: 0 | AY10: 0 | AZ10: 0 | BA10: 0 | BB10: 0 | BC10: 0 | BD10: 0 | BE10: 0 | BF10: 0 | BG10: 0 | BH10: 0 | BI10: 0 | BJ10: 0 | BK10: 0 | BL10: 0 | BM10: 0 | BN10: 0 | BO10: 0 | BP10: 0 | BQ10: 0 | BR10: 0 | BS10: 0 | BT10: 0 | BU10: 300 | BV10: 300 | BW10: 300 | BX10: 300 | BY10: 300
C11: Nombre de la entidad | D11: Total Entidades Establecimientos de crédito sin IOE'S | E11: Total Sector Privado | F11: Total Sector Privado Nacional | G11: Total Sector Privado Extranjero | H11: Total Sector Público | I11: Total Sector Cooperativas | J11: Total Bancos | K11: Bancos Privados | L11: Bancos Privados Nacionales | M11: Bancos Privados Extranjeros | N11: Bancos Públicos | O11: Bancos Nacionales | P11: Total CFIs | Q11: CFIs Privadas | R11: CFIs Privadas Nacionales | S11: CFIs Privadas Extranjeras | T11: Total CFs | U11: Total CFs Nacionales (Tradicionales+Leasing) | V11: Total CFs Extranjeras (Tradicionales+Leasing) | W11: Total CFs Tradicionales | X11: CFs Privadas | Y11: CFs Privadas Nacionales | Z11: CFs Privadas Extranjeras | AA11: Total Cooperativas | AB11: BANCO DE BOGOTA | AC11: BANCO POPULAR | AD11: ITAÚ CORPBANCA COLOMBIA S.A. | AE11: BANCOLOMBIA | AF11: CITIBANK-COLOMBIA | AG11: GNB SUDAMERIS | AH11: BBVA COLOMBIA | AI11: OCCIDENTE | AJ11: BANCO CAJA SOCIAL | AK11: DAVIVIENDA | AL11: SCOTIABANK COLPATRIA S.A | AM11: BANAGRARIO | AN11: BANCO AV VILLAS | AO11: BANCO CREDIFINANCIERA | AP11: BANCAMIA | AQ11: BANCO W S.A. | AR11: BANCOOMEVA | AS11: BANCO FINANDINA | AT11: BANCO FALABELLA S.A. | AU11: BANCO PICHINCHA S.A. | AV11: COOPCENTRAL | AW11: BANCO SANTANDER DE NEGOCIOS COLOMBIA | AX11: BANCO MUNDO MUJER S.A. | AY11: MIBANCO S.A. | AZ11: BANCO SERFINANZA S.A. | BA11: BANCO J.P: MORGAN COLOMBIA S.A. | BB11: LULO BANK S.A. | BC11: BANCO BTG PACTUAL | BD11: BANCO UNION | BE11: CORFICOLOMBIANA | BF11: B INV BANCOLOMBIA | BG11: BNP PARIBAS COLOMBIA | BH11: CORPORACIÓN FINANCIERA GNB SUDAMERIS S.A | BI11: CORPORACIÓN FINANCIERA DAVIVIENDA | BJ11: COMPAÑÍA DE FINANCIAMIENTO TUYA | BK11: GM FINANCIAL COLOMBIA S.A. | BL11: COLTEFINANCIERA | BM11: IRIS CF | BN11: CREDIFAMILIA | BO11: CREZCAMOS S.A. | BP11: LA HIPOTECARIA | BQ11: FINANCIERA JURISCOOP S.A. | BR11: RCI COLOMBIA S.A. | BS11: BANCAR TECNOLOGIA CO S.A. | BT11: SANTANDER CONSUMER S.A. C.F.C | BU11: COOP FINAN DE ANTIOQUIA | BV11: JFK COOPERATIVA FINANCIERA | BW11: COOP FINAN COOFINEP | BX11: COOP FINAN COTRAFA | BY11: COOP FINAN CONFIAR
C12: Cifras con corte a 01-feb-2023 | D12: dic-22 | E12: dic-22 | F12: dic-22 | G12: dic-22 | H12: dic-22 | I12: dic-22 | J12: dic-22 | K12: dic-22 | L12: dic-22 | M12: dic-22 | N12: dic-22 | O12: dic-22 | P12: dic-22 | Q12: dic-22 | R12: dic-22 | S12: dic-22 | T12: dic-22 | U12: dic-22 | V12: dic-22 | W12: dic-22 | X12: dic-22 | Y12: dic-22 | Z12: dic-22 | AA12: dic-22 | AB12: dic-22 | AC12: dic-22 | AD12: dic-22 | AE12: dic-22 | AF12: dic-22 | AG12: dic-22 | AH12: dic-22 | AI12: dic-22 | AJ12: dic-22 | AK12: dic-22 | AL12: dic-22 | AM12: dic-22 | AN12: dic-22 | AO12: dic-22 | AP12: dic-22 | AQ12: dic-22 | AR12: dic-22 | AS12: dic-22 | AT12: dic-22 | AU12: dic-22 | AV12: dic-22 | AW12: dic-22 | AX12: dic-22 | AY12: dic-22 | AZ12: dic-22 | BA12: dic-22 | BB12: dic-22 | BC12: dic-22 | BD12: dic-22 | BE12: dic-22 | BF12: dic-22 | BG12: dic-22 | BH12: dic-22 | BI12: dic-22 | BJ12: dic-22 | BK12: dic-22 | BL12: dic-22 | BM12: dic-22 | BN12: dic-22 | BO12: dic-22 | BP12: dic-22 | BQ12: dic-22 | BR12: dic-22 | BS12: dic-22 | BT12: dic-22 | BU12: dic-22 | BV12: dic-22 | BW12: dic-22 | BX12: dic-22 | BY12: dic-22
A13: BALANCE (cifras en $ millones)
A14: ACTIVOS | D14: 9.7296518e+08 | E14: 9.3421939e+08 | F14: 6.8139182e+08 | G14: 2.5282757e+08 | H14: 33933046 | I14: 4812741.5 | J14: 9.2412105e+08 | K14: 8.9018801e+08 | L14: 6.4523797e+08 | M14: 2.4495003e+08 | N14: 33933046 | O14: 6.7917102e+08 | P14: 27525820 | Q14: 27525820 | R14: 27161044 | S14: 364775.9 | T14: 16505562 | U14: 8992802.7 | V14: 7512759.1 | W14: 16505562 | X14: 16505562 | Y14: 8992802.7 | Z14: 7512759.1 | AA14: 4812741.5 | AB14: 1.1035704e+08 | AC14: 32567740 | AD14: 28861832 | AE14: 2.4576572e+08 | AF14: 13619573 | AG14: 36757106 | AH14: 99238481 | AI14: 54637784 | AJ14: 19621760 | AK14: 1.3722038e+08 | AL14: 43190425 | AM14: 33933046 | AN14: 19420816 | AO14: 2238576.4 | AP14: 2257602.7 | AQ14: 2143375.7 | AR14: 4995411.7 | AS14: 3652847.8 | AT14: 7721628.9 | AU14: 3036406.3 | AV14: 1344272 | AW14: 7567597.5 | AX14: 3078571.7 | AY14: 1930366.7 | AZ14: 2553359.2 | BA14: 4220039.6 | BB14: 450075.58 | BC14: 736942.9 | BD14: 1002268.1 | BE14: 23473166 | BF14: 2119015.8 | BG14: 364775.9 | BH14: 1150659.7 | BI14: 418203.03 | BJ14: 5035508.6 | BK14: 2675528.2 | BL14: 1282273.4 | BM14: 621741.13 | BN14: 663574.21 | BO14: 401664.22 | BP14: 415006.95 | BQ14: 1389705.4 | BR14: 3868208.2 | BS14: 36692.72 | BT14: 115658.91 | BU14: 542945.38 | BV14: 1464108.6 | BW14: 349610.59 | BX14: 1090780.1 | BY14: 1365296.8
B15: DISPONIBLE | D15: 62457690 | E15: 60567309 | F15: 39129063 | G15: 21438245 | H15: 1429664.9 | I15: 460716.5 | J15: 58321487 | K15: 56891822 | L15: 35947035 | M15: 20944787 | N15: 1429664.9 | O15: 37376700 | P15: 2329704.5 | Q15: 2329704.5 | R15: 2311230.8 | S15: 18473.72 | T15: 1345782.1 | U15: 870797.16 | V15: 474984.98 | W15: 1345782.1 | X15: 1345782.1 | Y15: 870797.16 | Z15: 474984.98 | AA15: 460716.5 | AB15: 6396893 | AC15: 1709214.2 | AD15: 1507589.8 | AE15: 13066341 | AF15: 1436429.1 | AG15: 4322634.6 | AH15: 9375035.2 | AI15: 2651625.3 | AJ15: 1071993.7 | AK15: 7698210.1 | AL15: 2946243.2 | AM15: 1429664.9 | AN15: 869833.57 | AO15: 282986.95 | AP15: 152121.64 | AQ15: 204952.03 | AR15: 342159.28 | AS15: 223181.14 | AT15: 274574.07 | AU15: 161741.44 | AV15: 234660.62 | AW15: 590131.66 | AX15: 281088.32 | AY15: 222423.25 | AZ15: 316735.2 | BA15: 8107.94 | BB15: 85861.22 | BC15: 322299.67 | BD15: 136754.62 | BE15: 1858766.6 | BF15: 398687.86 | BG15: 18473.72 | BH15: 35306.73 | BI15: 18469.58 | BJ15: 523835.38 | BK15: 104454 | BL15: 82531.28 | BM15: 82376.91 | BN15: 62149.71 | BO15: 15670.63 | BP15: 51177.6 | BQ15: 119903.88 | BR15: 179914.9 | BS15: 14046.82 | BT15: 109721.03 | BU15: 69470.38 | BV15: 163305.98 | BW15: 39710.72 | BX15: 86565.62 | BY15: 101663.8
B16: POSICIONES ACTIVAS EN OPERACIONES DE MERCADO MONETARIO Y RELACIONADAS | D16: 21768179 | E16: 21497472 | F16: 10008920 | G16: 11488552 | H16: 270706.68 | I16: 0 | J16: 21450493 | K16: 21179786 | L16: 9759143.4 | M16: 11420643 | N16: 270706.68 | O16: 10029850 | P16: 317661.85 | Q16: 317661.85 | R16: 249752.87 | S16: 67908.98 | T16: 23.64 | U16: 23.64 | V16: 0 | W16: 23.64 | X16: 23.64 | Y16: 23.64 | Z16: 0 | AA16: 0 | AB16: 4450600.6 | AC16: 9091.28 | AD16: 668504.59 | AE16: 3167463 | AF16: 897664.42 | AG16: 6853173.2 | AH16: 899080.68 | AI16: 976218.83 | AJ16: 620520.22 | AK16: 416488.48 | AL16: 514651.84 | AM16: 270706.68 | AN16: 47127.19 | AO16: 0 | AP16: 12007.43 | AQ16: 22592.75 | AR16: 34030.88 | AS16: 0 | AT16: 0 | AU16: 14656.52 | AV16: 0 | AW16: 455336.9 | AX16: 0 | AY16: 3002.78 | AZ16: 0 | BA16: 1117575 | BB16: 0 | BC16: 0 | BD16: 0 | BE16: 249752.87 | BF16: 0 | BG16: 67908.98 | BH16: 0 | BI16: 0 | BJ16: 23.64 | BK16: 0 | BL16: 0 | BM16: 0 | BN16: 0 | BO16: 0 | BP16: 0 | BQ16: 0 | BR16: 0 | BS16: 0 | BT16: 0 | BU16: 0 | BV16: 0 | BW16: 0 | BX16: 0 | BY16: 0
C17: INTERBANCARIOS | D17: 2176542.1 | E17: 2096417.8 | F17: 1423374.8 | G17: 673043.01 | H17: 80124.33 | I17: 0 | J17: 2114822.4 | K17: 2034698.1 | L17: 1374667.2 | M17: 660030.94 | N17: 80124.33 | O17: 1454791.5 | P17: 61696.02 | Q17: 61696.02 | R17: 48683.95 | S17: 13012.07 | T17: 23.64 | U17: 23.64 | V17: 0 | W17: 23.64 | X17: 23.64 | Y17: 23.64 | Z17: 0 | AA17: 0 | AB17: 170159.34 | AC17: 9091.28 | AD17: 117844.97 | AE17: 350515.23 | AF17: 0 | AG17: 330620.17 | AH17: 120167.19 | AI17: 209370.9 | AJ17: 620520.22 | AK17: 0 | AL17: 0 | AM17: 80124.33 | AN17: 0 | AO17: 0 | AP17: 12007.43 | AQ17: 0 | AR17: 0 | AS17: 0 | AT17: 0 | AU17: 0 | AV17: 0 | AW17: 91398.61 | AX17: 0 | AY17: 3002.78 | AZ17: 0 | BA17: 0 | BB17: 0 | BC17: 0 | BD17: 0 | BE17: 48683.95 | BF17: 0 | BG17: 13012.07 | BH17: 0 | BI17: 0 | BJ17: 23.64 | BK17: 0 | BL17: 0 | BM17: 0 | BN17: 0 | BO17: 0 | BP17: 0 | BQ17: 0 | BR17: 0 | BS17: 0 | BT17: 0 | BU17: 0 | BV17: 0 | BW17: 0 | BX17: 0 | BY17: 0
C18: OPERACIONES DE REPORTO O REPO | D18: 35271.51 | E18: 35271.51 | F18: 35271.51 | G18: 0 | H18: 0 | I18: 0 | J18: 35271.51 | K18: 35271.51 | L18: 35271.51 | M18: 0 | N18: 0 | O18: 35271.51 | P18: 0 | Q18: 0 | R18: 0 | S18: 0 | T18: 0 | U18: 0 | V18: 0 | W18: 0 | X18: 0 | Y18: 0 | Z18: 0 | AA18: 0 | AB18: 0 | AC18: 0 | AD18: 0 | AE18: 35271.51 | AF18: 0 | AG18: 0 | AH18: 0 | AI18: 0 | AJ18: 0 | AK18: 0 | AL18: 0 | AM18: 0 | AN18: 0 | AO18: 0 | AP18: 0 | AQ18: 0 | AR18: 0 | AS18: 0 | AT18: 0 | AU18: 0 | AV18: 0 | AW18: 0 | AX18: 0 | AY18: 0 | AZ18: 0 | BA18: 0 | BB18: 0 | BC18: 0 | BD18: 0 | BE18: 0 | BF18: 0 | BG18: 0 | BH18: 0 | BI18: 0 | BJ18: 0 | BK18: 0 | BL18: 0 | BM18: 0 | BN18: 0 | BO18: 0 | BP18: 0 | BQ18: 0 | BR18: 0 | BS18: 0 | BT18: 0 | BU18: 0 | BV18: 0 | BW18: 0 | BX18: 0 | BY18: 0
C19: OPERACIONES SIMULTÁNEAS | D19: 19281282 | E19: 19090699 | F19: 8550273.7 | G19: 10540426 | H19: 190582.35 | I19: 0 | J19: 19025316 | K19: 18834733 | L19: 8349204.7 | M19: 10485529 | N19: 190582.35 | O19: 8539787.1 | P19: 255965.83 | Q19: 255965.83 | R19: 201068.92 | S19: 54896.91 | T19: 0 | U19: 0 | V19: 0 | W19: 0 | X19: 0 | Y19: 0 | Z19: 0 | AA19: 0 | AB19: 4280441.3 | AC19: 0 | AD19: 550659.62 | AE19: 2781676.2 | AF19: 897664.42 | AG19: 6522553 | AH19: 778913.49 | AI19: 766847.94 | AJ19: 0 | AK19: 416488.48 | AL19: 514651.84 | AM19: 190582.35 | AN19: 47127.19 | AO19: 0 | AP19: 0 | AQ19: 22592.75 | AR19: 34030.88 | AS19: 0 | AT19: 0 | AU19: 14656.52 | AV19: 0 | AW19: 363938.29 | AX19: 0 | AY19: 0 | AZ19: 0 | BA19: 842491.57 | BB19: 0 | BC19: 0 | BD19: 0 | BE19: 201068.92 | BF19: 0 | BG19: 54896.91 | BH19: 0 | BI19: 0 | BJ19: 0 | BK19: 0 | BL19: 0 | BM19: 0 | BN19: 0 | BO19: 0 | BP19: 0 | BQ19: 0 | BR19: 0 | BS19: 0 | BT19: 0 | BU19: 0 | BV19: 0 | BW19: 0 | BX19: 0 | BY19: 0
C20: OPERACIONES DE TRANSFERENCIA TEMPORAL DE VALORES | D20: 275083.4 | E20: 275083.4 | F20: 0 | G20: 275083.4 | H20: 0 | I20: 0 | J20: 275083.4 | K20: 275083.4 | L20: 0 | M20: 275083.4 | N20: 0 | O20: 0 | P20: 0 | Q20: 0 | R20: 0 | S20: 0 | T20: 0 | U20: 0 | V20: 0 | W20: 0 | X20: 0 | Y20: 0 | Z20: 0 | AA20: 0 | AB20: 0 | AC20: 0 | AD20: 0 | AE20: 0 | AF20: 0 | AG20: 0 | AH20: 0 | AI20: 0 | AJ20: 0 | AK20: 0 | AL20: 0 | AM20: 0 | AN20: 0 | AO20: 0 | AP20: 0 | AQ20: 0 | AR20: 0 | AS20: 0 | AT20: 0 | AU20: 0 | AV20: 0 | AW20: 0 | AX20: 0 | AY20: 0 | AZ20: 0 | BA20: 275083.4 | BB20: 0 | BC20: 0 | BD20: 0 | BE20: 0 | BF20: 0 | BG20: 0 | BH20: 0 | BI20: 0 | BJ20: 0 | BK20: 0 | BL20: 0 | BM20: 0 | BN20: 0 | BO20: 0 | BP20: 0 | BQ20: 0 | BR20: 0 | BS20: 0 | BT20: 0 | BU20: 0 | BV20: 0 | BW20: 0 | BX20: 0 | BY20: 0
C21: OTRAS POSICIONES ACTIVAS EN OPERACIONES DE MERCADO MONETARIO | D21: -0.02 | E21: -0.02 | F21: -0.0099999998 | G21: -0.0099999979 | H21: 0 | I21: 0 | J21: -0.020000003 | K21: -0.02 | L21: -0.0099999998 | M21: -0.0099999979 | N21: 0 | O21: -0.0099999998 | P21: 0 | Q21: 0 | R21: 0 | S21: 0 | T21: 0 | U21: 0 | V21: 0 | W21: 0 | X21: 0 | Y21: 0 | Z21: 0 | AA21: 0 | AB21: 0 | AC21: 0 | AD21: 0 | AE21: 0 | AF21: 0 | AG21: -0.0099999998 | AH21: 0 | AI21: -0.01 | AJ21: 0 | AK21: 0 | AL21: 0 | AM21: 0 | AN21: 0 | AO21: 0 | AP21: 0 | AQ21: 0 | AR21: 0 | AS21: 0 | AT21: 0 | AU21: 0 | AV21: 0 | AW21: 0 | AX21: 0 | AY21: 0 | AZ21: 0 | BA21: 0 | BB21: 0 | BC21: 0 | BD21: 0 | BE21: 0 | BF21: 0 | BG21: 0 | BH21: 0 | BI21: 0 | BJ21: 0 | BK21: 0 | BL21: 0 | BM21: 0 | BN21: 0 | BO21: 0 | BP21: 0 | BQ21: 0 | BR21: 0 | BS21: 0 | BT21: 0 | BU21: 0 | BV21: 0 | BW21: 0 | BX21: 0 | BY21: 0
B22: INVERSIONES Y OPERACIONES CON DERIVADOS | D22: 2.0579325e+08 | E22: 1.9103657e+08 | F22: 1.3663629e+08 | G22: 54400278 | H22: 14482699 | I22: 273988.83 | J22: 1.8081764e+08 | K22: 1.6633495e+08 | L22: 1.121709e+08 | M22: 54164045 | N22: 14482699 | O22: 1.266536e+08 | P22: 24136183 | Q22: 24136183 | R22: 23982309 | S22: 153873.97 | T22: 565439.2 | U22: 483080.42 | V22: 82358.78 | W22: 565439.2 | X22: 565439.2 | Y22: 483080.42 | Z22: 82358.78 | AA22: 273988.83 | AB22: 22490700 | AC22: 5565424.2 | AD22: 5256224.7 | AE22: 48012963 | AF22: 6895422.6 | AG22: 12486554 | AH22: 19168598 | AI22: 8897114.3 | AJ22: 2576247.5 | AK22: 19952088 | AL22: 4846030.3 | AM22: 14482699 | AN22: 3213458.1 | AO22: 76601.82 | AP22: 26114.93 | AQ22: 52269.55 | AR22: 469023.99 | AS22: 126576.24 | AT22: 658898.33 | AU22: 569797.09 | AV22: 94658.34 | AW22: 1218776.6 | AX22: 337884.69 | AY22: 48323.11 | AZ22: 53753 | BA22: 3054279.5 | BB22: 16263.5 | BC22: 9464.76 | BD22: 161435.19 | BE22: 20818583 | BF22: 1692798.5 | BG22: 153873.97 | BH22: 1072064.4 | BI22: 398862.96 | BJ22: 182497.76 | BK22: 22706.13 | BL22: 121687.2 | BM22: 16758.19 | BN22: 14560.58 | BO22: 7132.02 | BP22: 17634.63 | BQ22: 147576.69 | BR22: 18529.74 | BS22: 16356.26 | BT22: 0 | BU22: 28334.35 | BV22: 44417 | BW22: 24232.18 | BX22: 80845.73 | BY22: 96159.57
C23: INVERSIONES A VALOR RAZONABLE CON CAMBIOS EN RESULTADOS - INSTRUMENTOS REPRESENTATIVOS DE DEUDA | D23: 20554210 | E23: 17946447 | F23: 11720091 | G23: 6226355.6 | H23: 2584561 | I23: 23201.95 | J23: 20225995 | K23: 17641434 | L23: 11461096 | M23: 6180337.6 | N23: 2584561 | O23: 14045657 | P23: 193355.84 | Q23: 193355.84 | R23: 168444.63 | S23: 24911.21 | T23: 111657.16 | U23: 90550.29 | V23: 21106.87 | W23: 111657.16 | X23: 111657.16 | Y23: 90550.29 | Z23: 21106.87 | AA23: 23201.95 | AB23: 347218.46 | AC23: 164363.66 | AD23: 925688.04 | AE23: 6315428.1 | AF23: 1702811.4 | AG23: 41113.36 | AH23: 1599744.8 | AI23: 686114.18 | AJ23: 120965.51 | AK23: 3298241.6 | AL23: 293546.3 | AM23: 2584561 | AN23: 86241.93 | AO23: 0 | AP23: 26113.87 | AQ23: 8141.84 | AR23: 196145.71 | AS23: 32613.73 | AT23: 3394.91 | AU23: 7987.51 | AV23: 34200.73 | AW23: 227360.75 | AX23: 143657.67 | AY23: 1017.73 | AZ23: 0 | BA23: 1369225.7 | BB23: 0 | BC23: 9464.76 | BD23: 631.67 | BE23: 168444.63 | BF23: 0 | BG23: 24911.21 | BH23: 0 | BI23: 0 | BJ23: 0 | BK23: 0 | BL23: 0 | BM23: 0 | BN23: 4384.09 | BO23: 0 | BP23: 5460.27 | BQ23: 86166.2 | BR23: 0 | BS23: 15646.6 | BT23: 0 | BU23: 0 | BV23: 0 | BW23: 0 | BX23: 19697.31 | BY23: 3504.64
C24: INVERSIONES A VALOR RAZONABLE CON CAMBIOS EN RESULTADOS - INSTRUMENTOS DE PATRIMONIO | D24: 2744674.9 | E24: 2705225.5 | F24: 2063325.2 | G24: 641900.26 | H24: 0 | I24: 39449.46 | J24: 2596626.9 | K24: 2596626.9 | L24: 1962689.1 | M24: 633937.82 | N24: 0 | O24: 1962689.1 | P24: 85805.21 | Q24: 85805.21 | R24: 85805.21 | S24: 0 | T24: 22793.37 | U24: 14830.93 | V24: 7962.44 | W24: 22793.37 | X24: 22793.37 | Y24: 14830.93 | Z24: 7962.44 | AA24: 39449.46 | AB24: 881765.56 | AC24: 153869.12 | AD24: 28332.56 | AE24: 11120.6 | AF24: 0 | AG24: 603487.07 | AH24: 0 | AI24: 512883.31 | AJ24: 1394.55 | AK24: 16221.41 | AL24: 0 | AM24: 0 | AN24: 201749.77 | AO24: 3990.33 | AP24: 1.06 | AQ24: 1843.15 | AR24: 0 | AS24: 20277.24 | AT24: 0 | AU24: 2118.19 | AV24: 2239.33 | AW24: 0 | AX24: 150655.56 | AY24: 3470.9 | AZ24: 1207.18 | BA24: 0 | BB24: 0 | BC24: 0 | BD24: 0 | BE24: 81055.47 | BF24: 4749.74 | BG24: 0 | BH24: 0 | BI24: 0 | BJ24: 11293.08 | BK24: 14.55 | BL24: 0 | BM24: 0 | BN24: 667 | BO24: 2471.15 | BP24: 1239.11 | BQ24: 2870.85 | BR24: 3527.97 | BS24: 709.66 | BT24: 0 | BU24: 17110.89 | BV24: 0 | BW24: 11652.56 | BX24: 2346.93 | BY24: 8339.08
C25: INVERSIONES A COSTO AMORTIZADO | D25: 33166409 | E25: 22662053 | F25: 15574856 | G25: 7087197 | H25: 10316207 | I25: 188149.18 | J25: 32621298 | K25: 22305091 | L25: 15262476 | M25: 7042614.6 | N25: 10316207 | O25: 25578683 | P25: 2200.93 | Q25: 2200.93 | R25: 2200.93 | S25: 0 | T25: 354761.12 | U25: 310178.65 | V25: 44582.47 | W25: 354761.12 | X25: 354761.12 | Y25: 310178.65 | Z25: 44582.47 | AA25: 188149.18 | AB25: 2109457.2 | AC25: 1274194.1 | AD25: 1716368.4 | AE25: 3457606 | AF25: 0 | AG25: 0 | AH25: 3013783.1 | AI25: 1822712.5 | AJ25: 1370754 | AK25: 4076115.7 | AL25: 1537409.2 | AM25: 10316207 | AN25: 586922.13 | AO25: 56690.49 | AP25: 0 | AQ25: 31425.79 | AR25: 214034.81 | AS25: 40332.54 | AT25: 441523.6 | AU25: 104979.02 | AV25: 54660.07 | AW25: 228551.26 | AX25: 43571.46 | AY25: 43719.35 | AZ25: 52545.82 | BA25: 0 | BB25: 751.33 | BC25: 0 | BD25: 26983 | BE25: 2110.1 | BF25: 90.83 | BG25: 0 | BH25: 0 | BI25: 0 | BJ25: 171204.68 | BK25: 22691.58 | BL25: 59665.39 | BM25: 16746.77 | BN25: 9488.8 | BO25: 4660.87 | BP25: 2228.25 | BQ25: 53073.01 | BR25: 15001.77 | BS25: 0 | BT25: 0 | BU25: 6415.89 | BV25: 44417 | BW25: 12205.05 | BX25: 43373.9 | BY25: 81737.34
C26: INVERSIONES A VALOR RAZONABLE CON CAMBIOS EN EL ORI - INSTRUMENTOS DE PATRIMONIO | D26: 3706429.5 | E26: 3524355.4 | F26: 3056292.1 | G26: 468063.29 | H26: 175918.84 | I26: 6155.24 | J26: 2732803.5 | K26: 2556884.6 | L26: 2088821.3 | M26: 468063.29 | N26: 175918.84 | O26: 2264740.2 | P26: 922957.29 | Q26: 922957.29 | R26: 922957.29 | S26: 0 | T26: 44513.53 | U26: 44513.53 | V26: 0 | W26: 44513.53 | X26: 44513.53 | Y26: 44513.53 | Z26: 0 | AA26: 6155.24 | AB26: 823710.86 | AC26: 177209.79 | AD26: 25279.49 | AE26: 160687.68 | AF26: 86940.39 | AG26: 0 | AH26: 294184.52 | AI26: 120576.68 | AJ26: 143599.66 | AK26: 535707.27 | AL26: 61543.76 | AM26: 175918.84 | AN26: 109314.25 | AO26: 2579.99 | AP26: 0 | AQ26: 0 | AR26: 13905.71 | AS26: 1414.31 | AT26: 0 | AU26: 115.13 | AV26: 0 | AW26: 0 | AX26: 0 | AY26: 115.13 | AZ26: 0 | BA26: 0 | BB26: 0 | BC26: 0 | BD26: 0 | BE26: 894895.97 | BF26: 28061.32 | BG26: 0 | BH26: 0 | BI26: 0 | BJ26: 0 | BK26: 0 | BL26: 42115.45 | BM26: 0 | BN26: 0 | BO26: 0 | BP26: 0 | BQ26: 2398.08 | BR26: 0 | BS26: 0 | BT26: 0 | BU26: 919.04 | BV26: 0 | BW26: 374.57 | BX26: 1553.69 | BY26: 3307.94
C27: INVERSIONES A VALOR RAZONABLE CON CAMBIOS EN RESULTADOS ENTREGADOS EN OPERACIONES DE MERCADO MONETARIO - INSTRUMENTOS REPRESENTATIVOS DE DEUDA (DERECHOS DE TRANSFERENCIA) | D27: 7463984.8 | E27: 6287526.5 | F27: 1991445.7 | G27: 4296080.7 | H27: 1176458.3 | I27: 0 | J27: 6099350.6 | K27: 4922892.3 | L27: 633913.94 | M27: 4288978.4 | N27: 1176458.3 | O27: 1810372.2 | P27: 1364634.2 | Q27: 1364634.2 | R27: 1357531.8 | S27: 7102.35 | T27: 0 | U27: 0 | V27: 0 | W27: 0 | X27: 0 | Y27: 0 | Z27: 0 | AA27: 0 | AB27: 0 | AC27: 0 | AD27: 37103.21 | AE27: 30382.8 | AF27: 488585.05 | AG27: 1401503.6 | AH27: 582378.66 | AI27: 595801.74 | AJ27: 0 | AK27: 0 | AL27: 239908.48 | AM27: 1176458.3 | AN27: 0 | AO27: 0 | AP27: 0 | AQ27: 0 | AR27: 7729.4 | AS27: 0 | AT27: 0 | AU27: 0 | AV27: 0 | AW27: 3797.85 | AX27: 0 | AY27: 0 | AZ27: 0 | BA27: 1535701.6 | BB27: 0 | BC27: 0 | BD27: 0 | BE27: 1357531.8 | BF27: 0 | BG27: 7102.35 | BH27: 0 | BI27: 0 | BJ27: 0 | BK27: 0 | BL27: 0 | BM27: 0 | BN27: 0 | BO27: 0 | BP27: 0 | BQ27: 0 | BR27: 0 | BS27: 0 | BT27: 0 | BU27: 0 | BV27: 0 | BW27: 0 | BX27: 0 | BY27: 0
C28: INVERSIONES A VALOR RAZONABLE CON CAMBIOS EN RESULTADOS ENTREGADOS EN OPERACIONES DE MERCADO MONETARIO - INSTRUMENTOS DE PATRIMONIO (DERECHOS DE TRANSFERENCIA) | D28: 0 | E28: 0 | F28: 0 | G28: 0 | H28: 0 | I28: 0 | J28: 0 | K28: 0 | L28: 0 | M28: 0 | N28: 0 | O28: 0 | P28: 0 | Q28: 0 | R28: 0 | S28: 0 | T28: 0 | U28: 0 | V28: 0 | W28: 0 | X28: 0 | Y28: 0 | Z28: 0 | AA28: 0 | AB28: 0 | AC28: 0 | AD28: 0 | AE28: 0 | AF28: 0 | AG28: 0 | AH28: 0 | AI28: 0 | AJ28: 0 | AK28: 0 | AL28: 0 | AM28: 0 | AN28: 0 | AO28: 0 | AP28: 0 | AQ28: 0 | AR28: 0 | AS28: 0 | AT28: 0 | AU28: 0 | AV28: 0 | AW28: 0 | AX28: 0 | AY28: 0 | AZ28: 0 | BA28: 0 | BB28: 0 | BC28: 0 | BD28: 0 | BE28: 0 | BF28: 0 | BG28: 0 | BH28: 0 | BI28: 0 | BJ28: 0 | BK28: 0 | BL28: 0 | BM28: 0 | BN28: 0 | BO28: 0 | BP28: 0 | BQ28: 0 | BR28: 0 | BS28: 0 | BT28: 0 | BU28: 0 | BV28: 0 | BW28: 0 | BX28: 0 | BY28: 0
C29: INVERSIONES A COSTO AMORTIZADO CON CAMBIOS EN RESULTADOS ENTREGADOS EN OPERACIONES DE MERCADO MONETARIO - INSTRUMENTOS REPRESENTATIVOS DE DEUDA (DERECHOS DE TRANSFERENCIA) | D29: 2469912.7 | E29: 2469912.7 | F29: 1297634.1 | G29: 1172278.5 | H29: 0 | I29: 0 | J29: 2347060.1 | K29: 2347060.1 | L29: 1174781.6 | M29: 1172278.5 | N29: 0 | O29: 1174781.6 | P29: 119473.83 | Q29: 119473.83 | R29: 119473.83 | S29: 0 | T29: 3378.75 | U29: 3378.75 | V29: 0 | W29: 3378.75 | X29: 3378.75 | Y29: 3378.75 | Z29: 0 | AA29: 0 | AB29: 1021155.6 | AC29: 0 | AD29: 0 | AE29: 0 | AF29: 0 | AG29: 1172278.5 | AH29: 0 | AI29: 0 | AJ29: 153626 | AK29: 0 | AL29: 0 | AM29: 0 | AN29: 0 | AO29: 0 | AP29: 0 | AQ29: 0 | AR29: 0 | AS29: 0 | AT29: 0 | AU29: 0 | AV29: 0 | AW29: 0 | AX29: 0 | AY29: 0 | AZ29: 0 | BA29: 0 | BB29: 0 | BC29: 0 | BD29: 0 | BE29: 119473.83 | BF29: 0 | BG29: 0 | BH29: 0 | BI29: 0 | BJ29: 0 | BK29: 0 | BL29: 0 | BM29: 0 | BN29: 0 | BO29: 0 | BP29: 0 | BQ29: 3378.75 | BR29: 0 | BS29: 0 | BT29: 0 | BU29: 0 | BV29: 0 | BW29: 0 | BX29: 0 | BY29: 0
C30: INVERSIONES A VALOR RAZONABLE CON CAMBIOS EN EL ORI ENTREGADOS EN OPERACIONES DE MERCADO MONETARIO - INSTRUMENTOS DE PATRIMONIO | D30: 0 | E30: 0 | F30: 0 | G30: 0 | H30: 0 | I30: 0 | J30: 0 | K30: 0 | L30: 0 | M30: 0 | N30: 0 | O30: 0 | P30: 0 | Q30: 0 | R30: 0 | S30: 0 | T30: 0 | U30: 0 | V30: 0 | W30: 0 | X30: 0 | Y30: 0 | Z30: 0 | AA30: 0 | AB30: 0 | AC30: 0 | AD30: 0 | AE30: 0 | AF30: 0 | AG30: 0 | AH30: 0 | AI30: 0 | AJ30: 0 | AK30: 0 | AL30: 0 | AM30: 0 | AN30: 0 | AO30: 0 | AP30: 0 | AQ30: 0 | AR30: 0 | AS30: 0 | AT30: 0 | AU30: 0 | AV30: 0 | AW30: 0 | AX30: 0 | AY30: 0 | AZ30: 0 | BA30: 0 | BB30: 0 | BC30: 0 | BD30: 0 | BE30: 0 | BF30: 0 | BG30: 0 | BH30: 0 | BI30: 0 | BJ30: 0 | BK30: 0 | BL30: 0 | BM30: 0 | BN30: 0 | BO30: 0 | BP30: 0 | BQ30: 0 | BR30: 0 | BS30: 0 | BT30: 0 | BU30: 0 | BV30: 0 | BW30: 0 | BX30: 0 | BY30: 0
C31: INVERSIONES A VALOR RAZONABLE CON CAMBIOS EN RESULTADOS ENTREGADAS EN GARANTÍA DE OPERACIONES CON INSTRUMENTOS DERIVADOS - INSTRUMENTOS REPRESENTATIVOS DE DEUDA | D31: 1023753.5 | E31: 858555 | F31: 590359.8 | G31: 268195.2 | H31: 165198.54 | I31: 0 | J31: 1016281.8 | K31: 851083.23 | L31: 582888.03 | M31: 268195.2 | N31: 165198.54 | O31: 748086.57 | P31: 7471.77 | Q31: 7471.77 | R31: 7471.77 | S31: 0 | T31: 0 | U31: 0 | V31: 0 | W31: 0 | X31: 0 | Y31: 0 | Z31: 0 | AA31: 0 | AB31: 0 | AC31: 0 | AD31: 98681.31 | AE31: 570908.32 | AF31: 5088.65 | AG31: 0 | AH31: 0 | AI31: 0 | AJ31: 0 | AK31: 0 | AL31: 63556.06 | AM31: 165198.54 | AN31: 0 | AO31: 11979.71 | AP31: 0 | AQ31: 0 | AR31: 0 | AS31: 0 | AT31: 0 | AU31: 0 | AV31: 0 | AW31: 0 | AX31: 0 | AY31: 0 | AZ31: 0 | BA31: 100869.18 | BB31: 0 | BC31: 0 | BD31: 0 | BE31: 7471.77 | BF31: 0 | BG31: 0 | BH31: 0 | BI31: 0 | BJ31: 0 | BK31: 0 | BL31: 0 | BM31: 0 | BN31: 0 | BO31: 0 | BP31: 0 | BQ31: 0 | BR31: 0 | BS31: 0 | BT31: 0 | BU31: 0 | BV31: 0 | BW31: 0 | BX31: 0 | BY31: 0
C32: INVERSIONES A VALOR RAZONABLE CON CAMBIOS EN RESULTADOS ENTREGADOS EN GARANTÍA DE OPERACIONES CON INSTRUMENTOS DERIVADOS - INSTRUMENTOS DE PATRIMONIO | D32: 0 | E32: 0 | F32: 0 | G32: 0 | H32: 0 | I32: 0 | J32: 0 | K32: 0 | L32: 0 | M32: 0 | N32: 0 | O32: 0 | P32: 0 | Q32: 0 | R32: 0 | S32: 0 | T32: 0 | U32: 0 | V32: 0 | W32: 0 | X32: 0 | Y32: 0 | Z32: 0 | AA32: 0 | AB32: 0 | AC32: 0 | AD32: 0 | AE32: 0 | AF32: 0 | AG32: 0 | AH32: 0 | AI32: 0 | AJ32: 0 | AK32: 0 | AL32: 0 | AM32: 0 | AN32: 0 | AO32: 0 | AP32: 0 | AQ32: 0 | AR32: 0 | AS32: 0 | AT32: 0 | AU32: 0 | AV32: 0 | AW32: 0 | AX32: 0 | AY32: 0 | AZ32: 0 | BA32: 0 | BB32: 0 | BC32: 0 | BD32: 0 | BE32: 0 | BF32: 0 | BG32: 0 | BH32: 0 | BI32: 0 | BJ32: 0 | BK32: 0 | BL32: 0 | BM32: 0 | BN32: 0 | BO32: 0 | BP32: 0 | BQ32: 0 | BR32: 0 | BS32: 0 | BT32: 0 | BU32: 0 | BV32: 0 | BW32: 0 | BX32: 0 | BY32: 0
C33: INVERSIONES A COSTO AMORTIZADO CON CAMBIOS EN RESULTADOS ENTREGADOS EN GARANTÍA DE OPERACIONES CON INSTRUMENTOS DERIVADOS - INSTRUMENTOS REPRESENTATIVOS DE DEUDA | D33: 141082.99 | E33: 141082.99 | F33: 1361.3 | G33: 139721.69 | H33: 0 | I33: 0 | J33: 141082.99 | K33: 141082.99 | L33: 1361.3 | M33: 139721.69 | N33: 0 | O33: 1361.3 | P33: 0 | Q33: 0 | R33: 0 | S33: 0 | T33: 0 | U33: 0 | V33: 0 | W33: 0 | X33: 0 | Y33: 0 | Z33: 0 | AA33: 0 | AB33: 0 | AC33: 0 | AD33: 0 | AE33: 0 | AF33: 0 | AG33: 0 | AH33: 0 | AI33: 0 | AJ33: 0 | AK33: 0 | AL33: 0 | AM33: 0 | AN33: 0 | AO33: 1361.3 | AP33: 0 | AQ33: 0 | AR33: 0 | AS33: 0 | AT33: 0 | AU33: 0 | AV33: 0 | AW33: 139721.69 | AX33: 0 | AY33: 0 | AZ33: 0 | BA33: 0 | BB33: 0 | BC33: 0 | BD33: 0 | BE33: 0 | BF33: 0 | BG33: 0 | BH33: 0 | BI33: 0 | BJ33: 0 | BK33: 0 | BL33: 0 | BM33: 0 | BN33: 0 | BO33: 0 | BP33: 0 | BQ33: 0 | BR33: 0 | BS33: 0 | BT33: 0 | BU33: 0 | BV33: 0 | BW33: 0 | BX33: 0 | BY33: 0
C34: INVERSIONES A VALOR RAZONABLE CON CAMBIOS EN EL ORI ENTREGADOS EN GARANTÍA DE OPERACIONES CON INSTRUMENTOS DERIVADOS - INSTRUMENTOS DE PATRIMONIO | D34: 0 | E34: 0 | F34: 0 | G34: 0 | H34: 0 | I34: 0 | J34: 0 | K34: 0 | L34: 0 | M34: 0 | N34: 0 | O34: 0 | P34: 0 | Q34: 0 | R34: 0 | S34: 0 | T34: 0 | U34: 0 | V34: 0 | W34: 0 | X34: 0 | Y34: 0 | Z34: 0 | AA34: 0 | AB34: 0 | AC34: 0 | AD34: 0 | AE34: 0 | AF34: 0 | AG34: 0 | AH34: 0 | AI34: 0 | AJ34: 0 | AK34: 0 | AL34: 0 | AM34: 0 | AN34: 0 | AO34: 0 | AP34: 0 | AQ34: 0 | AR34: 0 | AS34: 0 | AT34: 0 | AU34: 0 | AV34: 0 | AW34: 0 | AX34: 0 | AY34: 0 | AZ34: 0 | BA34: 0 | BB34: 0 | BC34: 0 | BD34: 0 | BE34: 0 | BF34: 0 | BG34: 0 | BH34: 0 | BI34: 0 | BJ34: 0 | BK34: 0 | BL34: 0 | BM34: 0 | BN34: 0 | BO34: 0 | BP34: 0 | BQ34: 0 | BR34: 0 | BS34: 0 | BT34: 0 | BU34: 0 | BV34: 0 | BW34: 0 | BX34: 0 | BY34: 0
... C63: DETERIORO EN INVERSIONES A VALOR RAZONABLE | D63: 126322.77 | E63: 126026.25 | F63: 126026.25 | G63: 0 | H63: 0 | I63: 296.52 | J63: 25233.97 | K63: 25233.97 | L63: 25233.97 | M63: 0 | N63: 0 | O63: 25233.97 | P63: 100792.28 | Q63: 100792.28 | R63: 100792.28 | S63: 0 | T63: 0 | U63: 0 | V63: 0 | W63: 0 | X63: 0 | Y63: 0 | Z63: 0 | AA63: 296.52 | AB63: 24008.56 | AC63: 689.97 | AD63: 0 | AE63: 0 | AF63: 0 | AG63: 0 | AH63: 0 | AI63: 423.62 | AJ63: 0 | AK63: 0 | AL63: 0 | AM63: 0 | AN63: 0 | AO63: 0 | AP63: 0 | AQ63: 0 | AR63: 0 | AS63: 0 | AT63: 0 | AU63: 0 | AV63: 111.82 | AW63: 0 | AX63: 0 | AY63: 0 | AZ63: 0 | BA63: 0 | BB63: 0 | BC63: 0 | BD63: 0 | BE63: 100792.28 | BF63: 0 | BG63: 0 | BH63: 0 | BI63: 0 | BJ63: 0 | BK63: 0 | BL63: 0 | BM63: 0 | BN63: 0 | BO63: 0 | BP63: 0 | BQ63: 0 | BR63: 0 | BS63: 0 | BT63: 0 | BU63: 0 | BV63: 0 | BW63: 0 | BX63: 35 | BY63: 261.52
B64: CARTERA DE CREDITOS Y OPERACIONES DE LEASING | D64: 6.2236186e+08 | E64: 6.0227527e+08 | F64: 4.4926624e+08 | G64: 1.5300903e+08 | H64: 16285269 | I64: 3801320 | J64: 6.0524902e+08 | K64: 5.8896375e+08 | L64: 4.4237673e+08 | M64: 1.4658703e+08 | N64: 16285269 | O64: 4.5866199e+08 | P64: 0 | Q64: 0 | R64: 0 | S64: 0 | T64: 13311519 | U64: 6889513.4 | V64: 6422005.6 | W64: 13311519 | X64: 13311519 | Y64: 6889513.4 | Z64: 6422005.6 | AA64: 3801320 | AB64: 68880702 | AC64: 23668405 | AD64: 19555000 | AE64: 1.6239104e+08 | AF64: 4052466.8 | AG64: 11321649 | AH64: 65701100 | AI64: 39237021 | AJ64: 13924550 | AK64: 1.0083662e+08 | AL64: 32370276 | AM64: 16285269 | AN64: 14030509 | AO64: 1594112.6 | AP64: 1777296.1 | AQ64: 1475334.4 | AR64: 3935588.1 | AS64: 3193048.9 | AT64: 6269655.1 | AU64: 2022739.1 | AV64: 936870.43 | AW64: 4926469.4 | AX64: 2277865.6 | AY64: 1463392.8 | AZ64: 1993517.4 | BA64: 0 | BB64: 186078.92 | BC64: 367669.6 | BD64: 574769.82 | BE64: 0 | BF64: 0 | BG64: 0 | BH64: 0 | BI64: 0 | BJ64: 3874332.4 | BK64: 2361557 | BL64: 946110.34 | BM64: 463144.87 | BN64: 576162.04 | BO64: 318749.45 | BP64: 328654.91 | BQ64: 1029763.7 | BR64: 3413044.2 | BS64: 0 | BT64: 0 | BU64: 382679.78 | BV64: 1209057.8 | BW64: 263325.34 | BX64: 859141.53 | BY64: 1087115.5
C65: CARTERA DE CREDITOS | D65: 6.6116358e+08 | E65: 6.3922399e+08 | F65: 4.7815404e+08 | G65: 1.6106995e+08 | H65: 17694570 | I65: 4245020.7 | J65: 6.424728e+08 | K65: 6.2477823e+08 | L65: 4.7046206e+08 | M65: 1.5431617e+08 | N65: 17694570 | O65: 4.8815663e+08 | P65: 0 | Q65: 0 | R65: 0 | S65: 0 | T65: 14445764 | U65: 7691978 | V65: 6753785.6 | W65: 14445764 | X65: 14445764 | Y65: 7691978 | Z65: 6753785.6 | AA65: 4245020.7 | AB65: 73440870 | AC65: 24939622 | AD65: 20745122 | AE65: 1.7311422e+08 | AF65: 4094428.6 | AG65: 11779302 | AH65: 69263206 | AI65: 41303375 | AJ65: 14802879 | AK65: 1.0741468e+08 | AL65: 33928751 | AM65: 17694570 | AN65: 14671871 | AO65: 1704578.2 | AP65: 1883661 | AQ65: 1581183.5 | AR65: 4187504.5 | AS65: 3491720.8 | AT65: 6821669.7 | AU65: 2274988.7 | AV65: 980112.19 | AW65: 5037149 | AX65: 2432008.1 | AY65: 1532497.1 | AZ65: 2161534.1 | BA65: 0 | BB65: 195387.45 | BC65: 371550.85 | BD65: 624356.75 | BE65: 0 | BF65: 0 | BG65: 0 | BH65: 0 | BI65: 0 | BJ65: 4533666.3 | BK65: 2455224.7 | BL65: 981073.78 | BM65: 496005.31 | BN65: 597402.55 | BO65: 344721.16 | BP65: 341083.03 | BQ65: 1083830.1 | BR65: 3612756.7 | BS65: 0 | BT65: 0 | BU65: 447086.36 | BV65: 1451956.7 | BW65: 279658.47 | BX65: 916230.33 | BY65: 1150088.9
C66: CARTERA Y OPERACIONES DE LEASING COMERCIALES | D66: 3.3398312e+08 | E66: 3.2547772e+08 | F66: 2.5126768e+08 | G66: 74210041 | H66: 7906906 | I66: 598496.02 | J66: 3.3068602e+08 | K66: 3.2277911e+08 | L66: 2.5024338e+08 | M66: 72535737 | N66: 7906906 | O66: 2.5815028e+08 | P66: 0 | Q66: 0 | R66: 0 | S66: 0 | T66: 2698605.2 | U66: 1024300.7 | V66: 1674304.5 | W66: 2698605.2 | X66: 2698605.2 | Y66: 1024300.7 | Z66: 1674304.5 | AA66: 598496.02 | AB66: 48468294 | AC66: 7159807.3 | AD66: 12718439 | AE66: 1.1286686e+08 | AF66: 4094428.6 | AG66: 6217000.5 | AH66: 29427960 | AI66: 27948359 | AJ66: 2433899.8 | AK66: 44561589 | AL66: 15233934 | AM66: 7906906 | AN66: 3114297.9 | AO66: 71241.46 | AP66: 148799.76 | AQ66: 176838.52 | AR66: 718307.59 | AS66: 293454.81 | AT66: 0 | AU66: 648673.7 | AV66: 851780.35 | AW66: 3823751 | AX66: 357556.15 | AY66: 377977.01 | AZ66: 680209.36 | BA66: 0 | BB66: 0 | BC66: 371550.85 | BD66: 14106.34 | BE66: 0 | BF66: 0 | BG66: 0 | BH66: 0 | BI66: 0 | BJ66: 0 | BK66: 970024.89 | BL66: 670567.56 | BM66: 259880.19 | BN66: 2730.51 | BO66: 73386.13 | BP66: 0 | BQ66: 91122.46 | BR66: 630893.49 | BS66: 0 | BT66: 0 | BU66: 142416.77 | BV66: 83947.05 | BW66: 64193.86 | BX66: 35798.89 | BY66: 272139.45
C67: CARTERA Y OPERACIONES DE LEASING DE CONSUMO | D67: 2.1394576e+08 | E67: 2.0971814e+08 | F67: 1.4802478e+08 | G67: 61693354 | H67: 1469977.6 | I67: 2757643.5 | J67: 2.0058155e+08 | K67: 1.9911158e+08 | L67: 1.4194835e+08 | M67: 57163229 | N67: 1469977.6 | O67: 1.4341832e+08 | P67: 0 | Q67: 0 | R67: 0 | S67: 0 | T67: 10606563 | U67: 6076438.5 | V67: 4530124.7 | W67: 10606563 | X67: 10606563 | Y67: 6076438.5 | Z67: 4530124.7 | AA67: 2757643.5 | AB67: 17328308 | AC67: 16552122 | AD67: 4400404.4 | AE67: 40210811 | AF67: 0 | AG67: 5521209.9 | AH67: 25649554 | AI67: 10919698 | AJ67: 4144673.1 | AK67: 34438913 | AL67: 12016597 | AM67: 1469977.6 | AN67: 9065705 | AO67: 1506942.8 | AP67: 7688.6 | AQ67: 100157.43 | AR67: 1920636.6 | AS67: 3197141.1 | AT67: 6821669.7 | AU67: 1626315 | AV67: 119567.95 | AW67: 1127479.7 | AX67: 254141.41 | AY67: 3539.13 | AZ67: 1481324.8 | BA67: 0 | BB67: 195387.45 | BC67: 0 | BD67: 501589.07 | BE67: 0 | BF67: 0 | BG67: 0 | BH67: 0 | BI67: 0 | BJ67: 4533666.3 | BK67: 1485199.8 | BL67: 307506.14 | BM67: 236125.12 | BN67: 6433.32 | BO67: 18282.37 | BP67: 44779.33 | BQ67: 992707.68 | BR67: 2981863.2 | BS67: 0 | BT67: 0 | BU67: 157933.3 | BV67: 1278616.4 | BW67: 175948.55 | BX67: 760576.04 | BY67: 384569.21
C68: CARTERA Y LEASING DE MICROCRÉDITOS | D68: 16670589 | E68: 8150579.8 | F68: 7811607.4 | G68: 338972.39 | H68: 8149926.2 | I68: 370083.09 | J68: 16047453 | K68: 7897527.1 | L68: 7811607.4 | M68: 85919.73 | N68: 8149926.2 | O68: 15961534 | P68: 0 | Q68: 0 | R68: 0 | S68: 0 | T68: 253052.66 | U68: 0 | V68: 253052.66 | W68: 253052.66 | X68: 253052.66 | Y68: 0 | Z68: 253052.66 | AA68: 370083.09 | AB68: 244969.76 | AC68: 1664.92 | AD68: 0 | AE68: 549962.19 | AF68: 0 | AG68: 0 | AH68: 1.51 | AI68: 0 | AJ68: 945094 | AK68: 1386.23 | AL68: 0 | AM68: 8149926.2 | AN68: 143.29 | AO68: 126393.91 | AP68: 1706704.4 | AQ68: 1304187.5 | AR68: 0 | AS68: 7.03 | AT68: 0 | AU68: 0 | AV68: 8763.89 | AW68: 85918.22 | AX68: 1820310.6 | AY68: 1102019.7 | AZ68: 0 | BA68: 0 | BB68: 0 | BC68: 0 | BD68: 0 | BE68: 0 | BF68: 0 | BG68: 0 | BH68: 0 | BI68: 0 | BJ68: 0 | BK68: 0 | BL68: 0 | BM68: 0 | BN68: 0 | BO68: 253052.66 | BP68: 0 | BQ68: 0 | BR68: 0 | BS68: 0 | BT68: 0 | BU68: 136003.62 | BV68: 89342.31 | BW68: 3464.81 | BX68: 29854.64 | BY68: 111417.71
C69: CARTERA DE VIVIENDA Y OPERACIONES DE LEASING HABITACIONAL | D69: 96564114 | E69: 95877555 | F69: 71049971 | G69: 24827585 | H69: 167760.17 | I69: 518798.08 | J69: 95157773 | K69: 94990013 | L69: 70458732 | M69: 24531281 | N69: 167760.17 | O69: 70626492 | P69: 0 | Q69: 0 | R69: 0 | S69: 0 | T69: 887542.5 | U69: 591238.8 | V69: 296303.7 | W69: 887542.5 | X69: 887542.5 | Y69: 591238.8 | Z69: 296303.7 | AA69: 518798.08 | AB69: 7399299 | AC69: 1226028.6 | AD69: 3626278.7 | AE69: 19486588 | AF69: 0 | AG69: 41091.86 | AH69: 14185690 | AI69: 2435317.9 | AJ69: 7279212 | AK69: 28412793 | AL69: 6678220.5 | AM69: 167760.17 | AN69: 2491724.4 | AO69: 0 | AP69: 20468.27 | AQ69: 0 | AR69: 1548560.3 | AS69: 1117.93 | AT69: 0 | AU69: 0 | AV69: 0 | AW69: 0 | AX69: 0 | AY69: 48961.31 | AZ69: 0 | BA69: 0 | BB69: 0 | BC69: 0 | BD69: 108661.34 | BE69: 0 | BF69: 0 | BG69: 0 | BH69: 0 | BI69: 0 | BJ69: 0 | BK69: 0 | BL69: 3000.08 | BM69: 0 | BN69: 588238.72 | BO69: 0 | BP69: 296303.7 | BQ69: 0 | BR69: 0 | BS69: 0 | BT69: 0 | BU69: 10732.67 | BV69: 50.89 | BW69: 36051.25 | BX69: 90000.76 | BY69: 381962.51
C70: DETERIORO | D70: 33595058 | E70: 31916809 | F70: 25091614 | G70: 6825195.1 | H70: 1317130.1 | I70: 361118.24 | J70: 32283874 | K70: 30966744 | L70: 24397391 | M70: 6569352.5 | N70: 1317130.1 | O70: 25714521 | P70: 0 | Q70: 0 | R70: 0 | S70: 0 | T70: 950065.37 | U70: 694222.79 | V70: 255842.58 | W70: 950065.37 | X70: 950065.37 | Y70: 694222.79 | Z70: 255842.58 | AA70: 361118.24 | AB70: 4073722.2 | AC70: 1031623.1 | AD70: 1044747.4 | AE70: 9428493.5 | AF70: 31995.08 | AG70: 333511.34 | AH70: 3012212.3 | AI70: 1746970 | AJ70: 804120.79 | AK70: 5674848 | AL70: 1417534.9 | AM70: 1317130.1 | AN70: 504793.31 | AO70: 85466 | AP70: 103857.46 | AQ70: 101263.29 | AR70: 205168.46 | AS70: 210499.57 | AT70: 424581.87 | AU70: 221246.41 | AV70: 32474.2 | AW70: 80894.05 | AX70: 145551.33 | AY70: 62979.84 | AZ70: 136243.25 | BA70: 0 | BB70: 6469.77 | BC70: 2629.14 | BD70: 42847.19 | BE70: 0 | BF70: 0 | BG70: 0 | BH70: 0 | BI70: 0 | BJ70: 575441.69 | BK70: 70018.93 | BL70: 30046.66 | BM70: 26718.2 | BN70: 21076.4 | BO70: 24503.53 | BP70: 11352.06 | BQ70: 40939.84 | BR70: 149968.06 | BS70: 0 | BT70: 0 | BU70: 59976.61 | BV70: 186050.64 | BW70: 12616.85 | BX70: 46964.06 | BY70: 55510.08
C71: DETERIORO (DETERIORO) CRÉDITOS Y OPERACIONES DE LEASING COMERCIALES | D71: 15006577 | E71: 14109401 | F71: 11819452 | G71: 2289949.1 | H71: 845918.44 | I71: 51257.44 | J71: 14874437 | K71: 14028519 | L71: 11783500 | M71: 2245018.7 | N71: 845918.44 | O71: 12629418 | P71: 0 | Q71: 0 | R71: 0 | S71: 0 | T71: 80882.54 | U71: 35952.22 | V71: 44930.32 | W71: 80882.54 | X71: 80882.54 | Y71: 35952.22 | Z71: 44930.32 | AA71: 51257.44 | AB71: 2627066.8 | AC71: 265007.86 | AD71: 533125.05 | AE71: 5191745.3 | AF71: 26608.34 | AG71: 156139.62 | AH71: 758570.85 | AI71: 1108356.5 | AJ71: 138566.87 | AK71: 2209993 | AL71: 665619.64 | AM71: 845918.44 | AN71: 76552.62 | AO71: 13734.85 | AP71: 6044.15 | AQ71: 19627.03 | AR71: 29226.2 | AS71: 17472.44 | AT71: 0 | AU71: 55426.71 | AV71: 21492.61 | AW71: 46899.39 | AX71: 15249.03 | AY71: 13526.48 | AZ71: 28544.24 | BA71: 0 | BB71: 0 | BC71: 2629.14 | BD71: 1293.85 | BE71: 0 | BF71: 0 | BG71: 0 | BH71: 0 | BI71: 0 | BJ71: 0 | BK71: 21682.18 | BL71: 17642.72 | BM71: 11716.94 | BN71: 21.57 | BO71: 4868.3 | BP71: 0 | BQ71: 6570.99 | BR71: 18379.84 | BS71: 0 | BT71: 0 | BU71: 15649.43 | BV71: 20746 | BW71: 3695.33 | BX71: 1161.5 | BY71: 10005.18
C72: DETERIORO (DETERIORO) CARTERA Y OPERACIONES DE LEASING DE CONSUMO | D72: 13906974 | E72: 13585255 | F72: 9917546.6 | G72: 3667708.6 | H72: 92571.59 | I72: 229147.46 | J72: 12854589 | K72: 12762018 | L72: 9279645.5 | M72: 3482372.4 | N72: 92571.59 | O72: 9372217.1 | P72: 0 | Q72: 0 | R72: 0 | S72: 0 | T72: 823237.34 | U72: 637901.08 | V72: 185336.26 | W72: 823237.34 | X72: 823237.34 | Y72: 637901.08 | Z72: 185336.26 | AA72: 229147.46 | AB72: 883176.21 | AC72: 732848.53 | AD72: 349915.99 | AE72: 3292155.7 | AF72: 0 | AG72: 176117.62 | AH72: 1773543.6 | AI72: 566142.55 | AJ72: 171688.91 | AK72: 2711437.4 | AL72: 562855.95 | AM72: 92571.59 | AN72: 357404.62 | AO72: 54808.91 | AP72: 284.98 | AQ72: 4140.57 | AR72: 133660.84 | AS72: 193015.53 | AT72: 424581.87 | AU72: 165819.7 | AV72: 10416.49 | AW72: 29537.62 | AX72: 15438.57 | AY72: 338.14 | AZ72: 107699.01 | BA72: 0 | BB72: 6469.77 | BC72: 0 | BD72: 38518.77 | BE72: 0 | BF72: 0 | BG72: 0 | BH72: 0 | BI72: 0 | BJ72: 575441.69 | BK72: 48336.75 | BL72: 12221.18 | BM72: 15001.26 | BN72: 868.1 | BO72: 1901.02 | BP72: 3510.27 | BQ72: 34368.85 | BR72: 131588.22 | BS72: 0 | BT72: 0 | BU72: 23852.08 | BV72: 131307.46 | BW72: 7424 | BX72: 42136.14 | BY72: 24427.78
C73: DETERIORO (DETERIORO) MICROCRÉDITOS | D73: 936418.7 | E73: 501988.05 | F73: 481838.71 | G73: 20149.34 | H73: 373392.62 | I73: 61038.03 | J73: 857646.46 | K73: 484253.84 | L73: 481838.71 | M73: 2415.13 | N73: 373392.62 | O73: 855231.33 | P73: 0 | Q73: 0 | R73: 0 | S73: 0 | T73: 17734.21 | U73: 0 | V73: 17734.21 | W73: 17734.21 | X73: 17734.21 | Y73: 0 | Z73: 17734.21 | AA73: 61038.03 | AB73: 24572.77 | AC73: 156.62 | AD73: 0 | AE73: 67215.23 | AF73: 0 | AG73: 0 | AH73: 1.51 | AI73: 0 | AJ73: 54077.76 | AK73: 86.77 | AL73: 0 | AM73: 373392.62 | AN73: 26.87 | AO73: 16922.24 | AP73: 97087.95 | AQ73: 64472.97 | AR73: 0 | AS73: 0.42 | AT73: 0 | AU73: 0 | AV73: 565.1 | AW73: 2413.62 | AX73: 114863.73 | AY73: 41790.28 | AZ73: 0 | BA73: 0 | BB73: 0 | BC73: 0 | BD73: 0 | BE73: 0 | BF73: 0 | BG73: 0 | BH73: 0 | BI73: 0 | BJ73: 0 | BK73: 0 | BL73: 0 | BM73: 0 | BN73: 0 | BO73: 17734.21 | BP73: 0 | BQ73: 0 | BR73: 0 | BS73: 0 | BT73: 0 | BU73: 16279.13 | BV73: 33996.16 | BW73: 312.29 | BX73: 1894.3 | BY73: 8556.15
C74: DETERIORO (DETERIORO) CARTERA DE VIVIENDA Y LEASING HABITACIONAL | D74: 3227696.6 | E74: 3208079.8 | F74: 2422421.9 | G74: 785657.86 | H74: 5247.47 | I74: 14369.31 | J74: 3189473.1 | K74: 3184225.7 | L74: 2406409.6 | M74: 777816.07 | N74: 5247.47 | O74: 2411657.1 | P74: 0 | Q74: 0 | R74: 0 | S74: 0 | T74: 23854.13 | U74: 16012.34 | V74: 7841.79 | W74: 23854.13 | X74: 23854.13 | Y74: 16012.34 | Z74: 7841.79 | AA74: 14369.31 | AB74: 192116.7 | AC74: 33609.94 | AD74: 107406.38 | AE74: 797267.29 | AF74: 0 | AG74: 1254.1 | AH74: 480096.33 | AI74: 72470.96 | AJ74: 439787.25 | AK74: 753330.77 | AL74: 189059.26 | AM74: 5247.47 | AN74: 70809.2 | AO74: 0 | AP74: 426.38 | AQ74: 0 | AR74: 42281.42 | AS74: 11.18 | AT74: 0 | AU74: 0 | AV74: 0 | AW74: 0 | AX74: 0 | AY74: 1263.94 | AZ74: 0 | BA74: 0 | BB74: 0 | BC74: 0 | BD74: 3034.57 | BE74: 0 | BF74: 0 | BG74: 0 | BH74: 0 | BI74: 0 | BJ74: 0 | BK74: 0 | BL74: 182.76 | BM74: 0 | BN74: 15829.58 | BO74: 0 | BP74: 7841.79 | BQ74: 0 | BR74: 0 | BS74: 0 | BT74: 0 | BU74: 535.97 | BV74: 1.02 | BW74: 855.23 | BX74: 1772.12 | BY74: 11204.97
C75: OTROS DETERIOROS | D75: 517391.03 | E75: 512085.03 | F75: 450354.87 | G75: 61730.16 | H75: 0 | I75: 5306 | J75: 507727.88 | K75: 507727.88 | L75: 445997.72 | M75: 61730.16 | N75: 0 | O75: 445997.72 | P75: 0 | Q75: 0 | R75: 0 | S75: 0 | T75: 4357.15 | U75: 4357.15 | V75: 0 | W75: 4357.15 | X75: 4357.15 | Y75: 4357.15 | Z75: 0 | AA75: 5306 | AB75: 346789.76 | AC75: 0.17 | AD75: 54300 | AE75: 80110.07 | AF75: 5386.74 | AG75: 0 | AH75: 0 | AI75: 0 | AJ75: 0 | AK75: 0 | AL75: 0 | AM75: 0 | AN75: 0 | AO75: 0 | AP75: 14 | AQ75: 13022.72 | AR75: 0 | AS75: 0 | AT75: 0 | AU75: 0 | AV75: 0 | AW75: 2043.42 | AX75: 0 | AY75: 6061 | AZ75: 0 | BA75: 0 | BB75: 0 | BC75: 0 | BD75: 0 | BE75: 0 | BF75: 0 | BG75: 0 | BH75: 0 | BI75: 0 | BJ75: 0 | BK75: 0 | BL75: 0 | BM75: 0 | BN75: 4357.15 | BO75: 0 | BP75: 0 | BQ75: 0 | BR75: 0 | BS75: 0 | BT75: 0 | BU75: 3660 | BV75: 0 | BW75: 330 | BX75: 0 | BY75: 1316
C76: DETERIORO COMPONENTE CONTRACICLICO | D76: 5206665.1 | E76: 5031912.3 | F76: 3796185.8 | G76: 1235726.5 | H76: 92170.39 | I76: 82582.47 | J76: 4939903.4 | K76: 4847733 | L76: 3687943.9 | M76: 1159789.1 | N76: 92170.39 | O76: 3780114.3 | P76: 0 | Q76: 0 | R76: 0 | S76: 0 | T76: 184179.31 | U76: 108241.86 | V76: 75937.45 | W76: 184179.31 | X76: 184179.31 | Y76: 108241.86 | Z76: 75937.45 | AA76: 82582.47 | AB76: 486446.5 | AC76: 239594.58 | AD76: 145374.13 | AE76: 1294681.5 | AF76: 9966.69 | AG76: 124141.72 | AH76: 549893.27 | AI76: 319384.12 | AJ76: 74208.16 | AK76: 903211.98 | AL76: 140939.63 | AM76: 92170.39 | AN76: 136568.68 | AO76: 24999.58 | AP76: 2507.53 | AQ76: 4585.79 | AR76: 46747.97 | AS76: 88172.33 | AT76: 127432.73 | AU76: 31003.22 | AV76: 10767.56 | AW76: 29785.56 | AX76: 8591.17 | AY76: 6124.53 | AZ76: 31773.43 | BA76: 0 | BB76: 2838.76 | BC76: 1252.11 | BD76: 6739.74 | BE76: 0 | BF76: 0 | BG76: 0 | BH76: 0 | BI76: 0 | BJ76: 83892.13 | BK76: 23648.73 | BL76: 4916.78 | BM76: 6142.24 | BN76: 164.11 | BO76: 1468.18 | BP76: 1076.06 | BQ76: 13126.6 | BR76: 49744.48 | BS76: 0 | BT76: 0 | BU76: 4429.97 | BV76: 56848.22 | BW76: 3716.28 | BX76: 10124.74 | BY76: 7463.26
... C78: CRÉDITOS Y OPERACIONES DE LEASING COMERCIALES | D78: 1857185.5 | E78: 1775832.1 | F78: 1429187.6 | G78: 346644.51 | H78: 69132.97 | I78: 12220.43 | J78: 1824879.8 | K78: 1755746.9 | L78: 1422749.9 | M78: 332996.95 | N78: 69132.97 | O78: 1491882.9 | P78: 0 | Q78: 0 | R78: 0 | S78: 0 | T78: 20085.27 | U78: 6437.71 | V78: 13647.56 | W78: 20085.27 | X78: 20085.27 | Y78: 6437.71 | Z78: 13647.56 | AA78: 12220.43 | AB78: 236132.23 | AC78: 30765.82 | AD78: 71764.06 | AE78: 652931.28 | AF78: 9966.69 | AG78: 34779.37 | AH78: 162986.92 | AI78: 159494.98 | AJ78: 16388.87 | AK78: 268479.52 | AL78: 30824.94 | AM78: 69132.97 | AN78: 14442.64 | AO78: 1082.39 | AP78: 2387.66 | AQ78: 2920.05 | AR78: 4873.39 | AS78: 7601.93 | AT78: 0 | AU78: 6070.14 | AV78: 8562.15 | AW78: 15352.72 | AX78: 4859.03 | AY78: 6076.87 | AZ78: 5579.37 | BA78: 0 | BB78: 0 | BC78: 1252.11 | BD78: 171.75 | BE78: 0 | BF78: 0 | BG78: 0 | BH78: 0 | BI78: 0 | BJ78: 0 | BK78: 6559.24 | BL78: 3376.1 | BM78: 2475.52 | BN78: 11.69 | BO78: 1104.45 | BP78: 0 | BQ78: 574.4 | BR78: 5983.87 | BS78: 0 | BT78: 0 | BU78: 1938.21 | BV78: 6731.92 | BW78: 887.93 | BX78: 281.42 | BY78: 2380.95
B79: OTROS ACTIVOS | D79: 60584193 | E79: 58842770 | F79: 46351309 | G79: 12491461 | H79: 1464706.7 | I79: 276716.16 | J79: 58282408 | K79: 56817701 | L79: 44984169 | M79: 11833532 | N79: 1464706.7 | O79: 46448876 | P79: 742270.83 | Q79: 742270.83 | R79: 617751.6 | S79: 124519.23 | T79: 1282797.9 | U79: 749388.08 | V79: 533409.82 | W79: 1282797.9 | X79: 1282797.9 | Y79: 749388.08 | Z79: 533409.82 | AA79: 276716.16 | AB79: 8138145.4 | AC79: 1615605.3 | AD79: 1874512.6 | AE79: 19127911 | AF79: 337589.79 | AG79: 1773095 | AH79: 4094667.9 | AI79: 2875804.9 | AJ79: 1428448.9 | AK79: 8316975.4 | AL79: 2513223.9 | AM79: 1464706.7 | AN79: 1259888.5 | AO79: 284874.97 | AP79: 290062.69 | AQ79: 388226.94 | AR79: 214609.46 | AS79: 110041.47 | AT79: 518501.39 | AU79: 267472.15 | AV79: 78082.59 | AW79: 376883.06 | AX79: 181733.1 | AY79: 193224.8 | AZ79: 189353.55 | BA79: 40077.14 | BB79: 161871.94 | BC79: 37508.87 | BD79: 129308.51 | BE79: 546063.13 | BF79: 27529.39 | BG79: 124519.23 | BH79: 43288.59 | BI79: 870.49 | BJ79: 454819.35 | BK79: 186811.03 | BL79: 131944.55 | BM79: 59461.16 | BN79: 10701.88 | BO79: 60112.12 | BP79: 17539.81 | BQ79: 92461.14 | BR79: 256719.34 | BS79: 6289.64 | BT79: 5937.88 | BU79: 62460.87 | BV79: 47327.78 | BW79: 22342.35 | BX79: 64227.26 | BY79: 80357.9
C80: CUENTAS POR COBRAR | D80: 29720248 | E80: 28744394 | F80: 22555373 | G80: 6189020.9 | H80: 863875.29 | I80: 111978.35 | J80: 28348918 | K80: 27485043 | L80: 21638456 | M80: 5846587.5 | N80: 863875.29 | O80: 22502331 | P80: 529850.4 | Q80: 529850.4 | R80: 434051.37 | S80: 95799.03 | T80: 729500.4 | U80: 482866.08 | V80: 246634.32 | W80: 729500.4 | X80: 729500.4 | Y80: 482866.08 | Z80: 246634.32 | AA80: 111978.35 | AB80: 4042032.1 | AC80: 659967.1 | AD80: 793868.25 | AE80: 8661395.4 | AF80: 95789.37 | AG80: 899423.7 | AH80: 2427902.9 | AI80: 1429316.2 | AJ80: 610245.1 | AK80: 4869682.4 | AL80: 930034.2 | AM80: 863875.29 | AN80: 521654.06 | AO80: 73161.27 | AP80: 115110.83 | AQ80: 121245.32 | AR80: 144110.37 | AS80: 79463.63 | AT80: 318091.98 | AU80: 104128.74 | AV80: 32783.07 | AW80: 259397.18 | AX80: 56137.98 | AY80: 57776.35 | AZ80: 104742.02 | BA80: 4608.45 | BB80: 4227.89 | BC80: 13342.71 | BD80: 55404.59 | BE80: 405971.2 | BF80: 24372.57 | BG80: 95799.03 | BH80: 3536.11 | BI80: 171.49 | BJ80: 319360.97 | BK80: 110439.62 | BL80: 67950.57 | BM80: 13590.87 | BN80: 10276.91 | BO80: 34173.47 | BP80: 12687.21 | BQ80: 71686.76 | BR80: 87820.9 | BS80: 1093.9 | BT80: 419.22 | BU80: 28957.08 | BV80: 19669.59 | BW80: 6564.25 | BX80: 20144.28 | BY80: 36643.15
C81: ACTIVOS NO CORRIENTES MANTENIDOS PARA LA VENTA | D81: 552389.57 | E81: 544725.78 | F81: 365600.45 | G81: 179125.33 | H81: 5380.69 | I81: 2283.1 | J81: 519108.03 | K81: 513727.34 | L81: 353707.27 | M81: 160020.07 | N81: 5380.69 | O81: 359087.96 | P81: 0 | Q81: 0 | R81: 0 | S81: 0 | T81: 30998.44 | U81: 11893.18 | V81: 19105.26 | W81: 30998.44 | X81: 30998.44 | Y81: 11893.18 | Z81: 19105.26 | AA81: 2283.1 | AB81: 8683.73 | AC81: 0 | AD81: 41747.51 | AE81: 248001.09 | AF81: 0 | AG81: 58561.64 | AH81: 37470.38 | AI81: 0 | AJ81: 265.13 | AK81: 73010.67 | AL81: 21950.38 | AM81: 5380.69 | AN81: 5113.11 | AO81: 591.28 | AP81: 0 | AQ81: 0 | AR81: 958.11 | AS81: 4081.06 | AT81: 0 | AU81: 290.16 | AV81: 766.55 | AW81: 0 | AX81: 166.14 | AY81: 0 | AZ81: 10238.23 | BA81: 0 | BB81: 0 | BC81: 0 | BD81: 1832.17 | BE81: 0 | BF81: 0 | BG81: 0 | BH81: 0 | BI81: 0 | BJ81: 0 | BK81: 5788.51 | BL81: 5052.46 | BM81: 4124.63 | BN81: 55.19 | BO81: 74.21 | BP81: 326.51 | BQ81: 2660.9 | BR81: 12916.03 | BS81: 0 | BT81: 0 | BU81: 0 | BV81: 0 | BW81: 0 | BX81: 2283.1 | BY81: 0
C82: BIENES RECIBIDOS EN PAGO | D82: 483798.91 | E82: 449152.94 | F82: 111894.63 | G82: 337258.31 | H82: 34096.21 | I82: 549.76 | J82: 446212.06 | K82: 412115.85 | L82: 97255.37 | M82: 314860.48 | N82: 34096.21 | O82: 131351.58 | P82: 0 | Q82: 0 | R82: 0 | S82: 0 | T82: 37037.09 | U82: 14639.26 | V82: 22397.83 | W82: 37037.09 | X82: 37037.09 | Y82: 14639.26 | Z82: 22397.83 | AA82: 549.76 | AB82: 19431.5 | AC82: 0 | AD82: 70752.74 | AE82: 24305.41 | AF82: 0 | AG82: 184855.75 | AH82: 34691.93 | AI82: 0 | AJ82: 308.21 | AK82: 22060.72 | AL82: 23342.42 | AM82: 34096.21 | AN82: 473.91 | AO82: 1207.48 | AP82: 0 | AQ82: 0 | AR82: 4767.63 | AS82: 4015.61 | AT82: 0 | AU82: 1217.64 | AV82: 1674.53 | AW82: 0 | AX82: 200.68 | AY82: 0 | AZ82: 15979.83 | BA82: 0 | BB82: 0 | BC82: 0 | BD82: 2829.86 | BE82: 0 | BF82: 0 | BG82: 0 | BH82: 0 | BI82: 0 | BJ82: 0 | BK82: 7214.69 | BL82: 202.08 | BM82: 5599.56 | BN82: 91.19 | BO82: 371.04 | BP82: 439.58 | BQ82: 8746.43 | BR82: 14372.52 | BS82: 0 | BT82: 0 | BU82: 0 | BV82: 0 | BW82: 0 | BX82: 420 | BY82: 129.76
C83: BIENES RESTITUIDOS DE CONTRATOS DE LEASING | D83: 640989.22 | E83: 640989.22 | F83: 546659.1 | G83: 94330.12 | H83: 0 | I83: 0 | J83: 623557.33 | K83: 623557.33 | L83: 529227.21 | M83: 94330.12 | N83: 0 | O83: 529227.21 | P83: 0 | Q83: 0 | R83: 0 | S83: 0 | T83: 17431.89 | U83: 17431.89 | V83: 0 | W83: 17431.89 | X83: 17431.89 | Y83: 17431.89 | Z83: 0 | AA83: 0 | AB83: 4914.75 | AC83: 0 | AD83: 46053.12 | AE83: 457981.7 | AF83: 0 | AG83: 0 | AH83: 44320.25 | AI83: 0 | AJ83: 1215.6 | AK83: 62677.84 | AL83: 3895.85 | AM83: 0 | AN83: 0 | AO83: 0 | AP83: 0 | AQ83: 0 | AR83: 0 | AS83: 409.68 | AT83: 0 | AU83: 60.9 | AV83: 0 | AW83: 0 | AX83: 0 | AY83: 0 | AZ83: 2001.39 | BA83: 0 | BB83: 0 | BC83: 0 | BD83: 26.25 | BE83: 0 | BF83: 0 | BG83: 0 | BH83: 0 | BI83: 0 | BJ83: 0 | BK83: 0 | BL83: 5434.67 | BM83: 11997.22 | BN83: 0 | BO83: 0 | BP83: 0 | BQ83: 0 | BR83: 0 | BS83: 0 | BT83: 0 | BU83: 0 | BV83: 0 | BW83: 0 | BX83: 0 | BY83: 0
C84: OPERACIONES DISCONTINUADAS | D84: 0 | E84: 0 | F84: 0 | G84: 0 | H84: 0 | I84: 0 | J84: 0 | K84: 0 | L84: 0 | M84: 0 | N84: 0 | O84: 0 | P84: 0 | Q84: 0 | R84: 0 | S84: 0 | T84: 0 | U84: 0 | V84: 0 | W84: 0 | X84: 0 | Y84: 0 | Z84: 0 | AA84: 0 | AB84: 0 | AC84: 0 | AD84: 0 | AE84: 0 | AF84: 0 | AG84: 0 | AH84: 0 | AI84: 0 | AJ84: 0 | AK84: 0 | AL84: 0 | AM84: 0 | AN84: 0 | AO84: 0 | AP84: 0 | AQ84: 0 | AR84: 0 | AS84: 0 | AT84: 0 | AU84: 0 | AV84: 0 | AW84: 0 | AX84: 0 | AY84: 0 | AZ84: 0 | BA84: 0 | BB84: 0 | BC84: 0 | BD84: 0 | BE84: 0 | BF84: 0 | BG84: 0 | BH84: 0 | BI84: 0 | BJ84: 0 | BK84: 0 | BL84: 0 | BM84: 0 | BN84: 0 | BO84: 0 | BP84: 0 | BQ84: 0 | BR84: 0 | BS84: 0 | BT84: 0 | BU84: 0 | BV84: 0 | BW84: 0 | BX84: 0 | BY84: 0
C85: ACTIVOS NO CORRIENTES MANTENIDOS PARA DISTRIBUIR A LOS PROPIETARIOS | D85: 0 | E85: 0 | F85: 0 | G85: 0 | H85: 0 | I85: 0 | J85: 0 | K85: 0 | L85: 0 | M85: 0 | N85: 0 | O85: 0 | P85: 0 | Q85: 0 | R85: 0 | S85: 0 | T85: 0 | U85: 0 | V85: 0 | W85: 0 | X85: 0 | Y85: 0 | Z85: 0 | AA85: 0 | AB85: 0 | AC85: 0 | AD85: 0 | AE85: 0 | AF85: 0 | AG85: 0 | AH85: 0 | AI85: 0 | AJ85: 0 | AK85: 0 | AL85: 0 | AM85: 0 | AN85: 0 | AO85: 0 | AP85: 0 | AQ85: 0 | AR85: 0 | AS85: 0 | AT85: 0 | AU85: 0 | AV85: 0 | AW85: 0 | AX85: 0 | AY85: 0 | AZ85: 0 | BA85: 0 | BB85: 0 | BC85: 0 | BD85: 0 | BE85: 0 | BF85: 0 | BG85: 0 | BH85: 0 | BI85: 0 | BJ85: 0 | BK85: 0 | BL85: 0 | BM85: 0 | BN85: 0 | BO85: 0 | BP85: 0 | BQ85: 0 | BR85: 0 | BS85: 0 | BT85: 0 | BU85: 0 | BV85: 0 | BW85: 0 | BX85: 0 | BY85: 0
C86: OTROS ACTIVOS NO CORRIENTES MANTENIDOS PARA LA VENTA | D86: 25095.44 | E86: 23232.34 | F86: 5171.24 | G86: 18061.1 | H86: 0 | I86: 1863.1 | J86: 22786.96 | K86: 22786.96 | L86: 4725.86 | M86: 18061.1 | N86: 0 | O86: 4725.86 | P86: 0 | Q86: 0 | R86: 0 | S86: 0 | T86: 445.38 | U86: 445.38 | V86: 0 | W86: 445.38 | X86: 445.38 | Y86: 445.38 | Z86: 0 | AA86: 1863.1 | AB86: 0 | AC86: 0 | AD86: 1386.47 | AE86: 0 | AF86: 0 | AG86: 0 | AH86: 16674.63 | AI86: 0 | AJ86: 0 | AK86: 0 | AL86: 0 | AM86: 0 | AN86: 4725.86 | AO86: 0 | AP86: 0 | AQ86: 0 | AR86: 0 | AS86: 0 | AT86: 0 | AU86: 0 | AV86: 0 | AW86: 0 | AX86: 0 | AY86: 0 | AZ86: 0 | BA86: 0 | BB86: 0 | BC86: 0 | BD86: 0 | BE86: 0 | BF86: 0 | BG86: 0 | BH86: 0 | BI86: 0 | BJ86: 0 | BK86: 0 | BL86: 0 | BM86: 0 | BN86: 0 | BO86: 0 | BP86: 0 | BQ86: 445.38 | BR86: 0 | BS86: 0 | BT86: 0 | BU86: 0 | BV86: 0 | BW86: 0 | BX86: 1863.1 | BY86: 0
C87: DETERIORO ACTIVOS NO CORRIENTES MANTENIDOS PARA LA VENTA | D87: 597494 | E87: 568648.72 | F87: 298124.52 | G87: 270524.2 | H87: 28715.52 | I87: 129.76 | J87: 573448.32 | K87: 544732.8 | L87: 277501.17 | M87: 267231.63 | N87: 28715.52 | O87: 306216.69 | P87: 0 | Q87: 0 | R87: 0 | S87: 0 | T87: 23915.92 | U87: 20623.35 | V87: 3292.57 | W87: 23915.92 | X87: 23915.92 | Y87: 20623.35 | Z87: 3292.57 | AA87: 129.76 | AB87: 15662.52 | AC87: 0 | AD87: 76444.82 | AE87: 234286.02 | AF87: 0 | AG87: 126294.11 | AH87: 58216.43 | AI87: 0 | AJ87: 1258.68 | AK87: 11727.89 | AL87: 5287.89 | AM87: 28715.52 | AN87: 86.66 | AO87: 616.2 | AP87: 0 | AQ87: 0 | AR87: 3809.52 | AS87: 344.23 | AT87: 0 | AU87: 988.38 | AV87: 907.98 | AW87: 0 | AX87: 34.54 | AY87: 0 | AZ87: 7742.99 | BA87: 0 | BB87: 0 | BC87: 0 | BD87: 1023.94 | BE87: 0 | BF87: 0 | BG87: 0 | BH87: 0 | BI87: 0 | BJ87: 0 | BK87: 1426.18 | BL87: 584.29 | BM87: 13472.15 | BN87: 36 | BO87: 296.83 | BP87: 113.07 | BQ87: 6530.91 | BR87: 1456.49 | BS87: 0 | BT87: 0 | BU87: 0 | BV87: 0 | BW87: 0 | BX87: 0 | BY87: 129.76
C88: ACTIVOS MATERIALES | D88: 14770417 | E88: 14279419 | F88: 12187160 | G88: 2092259.1 | H88: 342924.73 | I88: 148073.34 | J88: 14414037 | K88: 14071112 | L88: 12018074 | M88: 2053038.2 | N88: 342924.73 | O88: 12360999 | P88: 97077.41 | Q88: 97077.41 | R88: 91810.42 | S88: 5266.99 | T88: 111229.33 | U88: 77275.45 | V88: 33953.88 | W88: 111229.33 | X88: 111229.33 | Y88: 77275.45 | Z88: 33953.88 | AA88: 148073.34 | AB88: 1126377.2 | AC88: 556106.1 | AD88: 221538.93 | AE88: 6848336.2 | AF88: 60127.75 | AG88: 244628.13 | AH88: 759573.36 | AI88: 590260.87 | AJ88: 633981.66 | AK88: 1285235.8 | AL88: 599939.58 | AM88: 342924.73 | AN88: 523216.97 | AO88: 15010.71 | AP88: 82706.09 | AQ88: 58257.01 | AR88: 29155.52 | AS88: 10792.18 | AT88: 50480.59 | AU88: 97432.89 | AV88: 36383.73 | AW88: 8203.65 | AX88: 88787.61 | AY88: 35201.83 | AZ88: 33260.73 | BA88: 10460.34 | BB88: 6542.07 | BC88: 652.96 | BD88: 58461.91 | BE88: 91395.61 | BF88: 410.9 | BG88: 5266.99 | BH88: 3.91 | BI88: 0 | BJ88: 17030.59 | BK88: 4528.64 | BL88: 37463.38 | BM88: 7042.38 | BN88: 268.61 | BO88: 19953.41 | BP88: 3574.32 | BQ88: 15470.49 | BR88: 4794.99 | BS88: 276.28 | BT88: 826.24 | BU88: 31240.37 | BV88: 25213.06 | BW88: 13302.95 | BX88: 37031.89 | BY88: 41285.07
C89: PROPIEDAD, PLANTA Y EQUIPO | D89: 6236282.5 | E89: 5935916 | F89: 4557882.5 | G89: 1378033.5 | H89: 203767.67 | I89: 96598.83 | J89: 6004790 | K89: 5801022.3 | L89: 4446409 | M89: 1354613.3 | N89: 203767.67 | O89: 4650176.7 | P89: 54162.8 | Q89: 54162.8 | R89: 51048.8 | S89: 3114 | T89: 80730.93 | U89: 60424.71 | V89: 20306.22 | W89: 80730.93 | X89: 80730.93 | Y89: 60424.71 | Z89: 20306.22 | AA89: 96598.83 | AB89: 583526.01 | AC89: 475339.74 | AD89: 124627.73 | AE89: 1768021.1 | AF89: 60127.75 | AG89: 30392.98 | AH89: 644968.03 | AI89: 174033.96 | AJ89: 499229.47 | AK89: 496434.35 | AL89: 366278.08 | AM89: 203767.67 | AN89: 247649.54 | AO89: 724.65 | AP89: 69387.3 | AQ89: 16159.3 | AR89: 6367.76 | AS89: 3280.07 | AT89: 24266.79 | AU89: 96786.44 | AV89: 23362.59 | AW89: 4010.51 | AX89: 21130.64 | AY89: 7368.45 | AZ89: 31711.63 | BA89: 3037.66 | BB89: 4205.56 | BC89: 117.31 | BD89: 18476.85 | BE89: 50677.96 | BF89: 366.93 | BG89: 3114 | BH89: 3.91 | BI89: 0 | BJ89: 11176.49 | BK89: 4126.8 | BL89: 32180.86 | BM89: 5857.03 | BN89: 228.94 | BO89: 13430.03 | BP89: 927.12 | BQ89: 10981.39 | BR89: 1545.99 | BS89: 276.28 | BT89: 0 | BU89: 14756.4 | BV89: 11790.71 | BW89: 9685.44 | BX89: 28371.29 | BY89: 31994.99
C90: PROPIEDAD, PLANTA Y EQUIPO POR DERECHOS DE USO | D90: 3729508.2 | E90: 3563221.5 | F90: 2965574 | G90: 597647.52 | H90: 119167.7 | I90: 47119.01 | J90: 3654851.6 | K90: 3535683.9 | L90: 2950621.3 | M90: 585062.61 | N90: 119167.7 | O90: 3069789 | P90: 3183.23 | Q90: 3183.23 | R90: 1030.24 | S90: 2152.99 | T90: 24354.34 | U90: 13922.42 | V90: 10431.92 | W90: 24354.34 | X90: 24354.34 | Y90: 13922.42 | Z90: 10431.92 | AA90: 47119.01 | AB90: 431199.68 | AC90: 34031.01 | AD90: 73450.88 | AE90: 1116653.1 | AF90: 0 | AG90: 214235.15 | AH90: 98757.23 | AI90: 226104.05 | AJ90: 70499.53 | AK90: 626760 | AL90: 164473.41 | AM90: 119167.7 | AN90: 224267.65 | AO90: 14136.04 | AP90: 8865.72 | AQ90: 41887.78 | AR90: 22787.76 | AS90: 7512.11 | AT90: 22437.85 | AU90: 646.45 | AV90: 660.99 | AW90: 3103.31 | AX90: 59959.43 | AY90: 23348.71 | AZ90: 972.99 | BA90: 7422.68 | BB90: 989.76 | BC90: 535.65 | BD90: 39985.06 | BE90: 986.27 | BF90: 43.97 | BG90: 2152.99 | BH90: 0 | BI90: 0 | BJ90: 5837.42 | BK90: 401.84 | BL90: 4489.91 | BM90: 1185.35 | BN90: 39.67 | BO90: 4765.93 | BP90: 1258.53 | BQ90: 2370.07 | BR90: 3249 | BS90: 0 | BT90: 756.62 | BU90: 15494.65 | BV90: 13422.35 | BW90: 3617.51 | BX90: 6203.37 | BY90: 8381.13
C91: PROPIEDADES Y EQUIPO EN ARRENDAMIENTO OPERATIVO | D91: 3586665.4 | E91: 3586665.4 | F91: 3586665.4 | G91: 0 | H91: 0 | I91: 0 | J91: 3586665.4 | K91: 3586665.4 | L91: 3586665.4 | M91: 0 | N91: 0 | O91: 3586665.4 | P91: 0 | Q91: 0 | R91: 0 | S91: 0 | T91: 0 | U91: 0 | V91: 0 | W91: 0 | X91: 0 | Y91: 0 | Z91: 0 | AA91: 0 | AB91: 0 | AC91: 0 | AD91: 0 | AE91: 3504808.3 | AF91: 0 | AG91: 0 | AH91: 0 | AI91: 57079.06 | AJ91: 0 | AK91: 0 | AL91: 0 | AM91: 0 | AN91: 24778.02 | AO91: 0 | AP91: 0 | AQ91: 0 | AR91: 0 | AS91: 0 | AT91: 0 | AU91: 0 | AV91: 0 | AW91: 0 | AX91: 0 | AY91: 0 | AZ91: 0 | BA91: 0 | BB91: 0 | BC91: 0 | BD91: 0 | BE91: 0 | BF91: 0 | BG91: 0 | BH91: 0 | BI91: 0 | BJ91: 0 | BK91: 0 | BL91: 0 | BM91: 0 | BN91: 0 | BO91: 0 | BP91: 0 | BQ91: 0 | BR91: 0 | BS91: 0 | BT91: 0 | BU91: 0 | BV91: 0 | BW91: 0 | BX91: 0 | BY91: 0
... C99: OTROS | D99: 13643413 | E99: 13376506 | F99: 9474180.6 | G99: 3902325 | H99: 252526.03 | I99: 14381.37 | J99: 13102619 | K99: 12850093 | L99: 9204937.4 | M99: 3645155.4 | N99: 252526.03 | O99: 9457463.4 | P99: 115343.02 | Q99: 115343.02 | R99: 91889.81 | S99: 23453.21 | T99: 411069.73 | U99: 177353.37 | V99: 233716.36 | W99: 411069.73 | X99: 411069.73 | Y99: 177353.37 | Z99: 233716.36 | AA99: 14381.37 | AB99: 2495147.5 | AC99: 399532.11 | AD99: 817357.88 | AE99: 3370178.4 | AF99: 181672.67 | AG99: 554725.15 | AH99: 869721.18 | AI99: 833504.13 | AJ99: 183956.98 | AK99: 1008271.4 | AL99: 848325.6 | AM99: 252526.03 | AN99: 209904.32 | AO99: 196111.71 | AP99: 60931.39 | AQ99: 40447.82 | AR99: 40385.46 | AS99: 15704.6 | AT99: 149928.82 | AU99: 65620.36 | AV99: 8149.24 | AW99: 109282.23 | AX99: 36641.37 | AY99: 100246.62 | AZ99: 41112.57 | BA99: 25008.35 | BB99: 151101.98 | BC99: 23513.2 | BD99: 13609.84 | BE99: 48696.32 | BF99: 2745.92 | BG99: 23453.21 | BH99: 39748.57 | BI99: 699 | BJ99: 118427.79 | BK99: 66054.26 | BL99: 21478.14 | BM99: 34703.28 | BN99: 101.17 | BO99: 5911.03 | BP99: 951.77 | BQ99: 2642.99 | BR99: 151187.42 | BS99: 4919.46 | BT99: 4692.42 | BU99: 2263.42 | BV99: 2445.13 | BW99: 2475.15 | BX99: 4767.99 | BY99: 2429.68
A100: PASIVOS Y PATRIMONIO | D100: 9.7296518e+08 | E100: 9.3421939e+08 | F100: 6.8139182e+08 | G100: 2.5282757e+08 | H100: 33933046 | I100: 4812741.4 | J100: 9.2412105e+08 | K100: 8.9018801e+08 | L100: 6.4523797e+08 | M100: 2.4495003e+08 | N100: 33933046 | O100: 6.7917102e+08 | P100: 27525820 | Q100: 27525820 | R100: 27161044 | S100: 364775.92 | T100: 16505562 | U100: 8992802.7 | V100: 7512759.1 | W100: 16505562 | X100: 16505562 | Y100: 8992802.7 | Z100: 7512759.1 | AA100: 4812741.4 | AB100: 1.1035704e+08 | AC100: 32567740 | AD100: 28861832 | AE100: 2.4576572e+08 | AF100: 13619573 | AG100: 36757106 | AH100: 99238481 | AI100: 54637784 | AJ100: 19621760 | AK100: 1.3722038e+08 | AL100: 43190425 | AM100: 33933046 | AN100: 19420816 | AO100: 2238576.3 | AP100: 2257602.7 | AQ100: 2143375.7 | AR100: 4995411.7 | AS100: 3652847.8 | AT100: 7721628.9 | AU100: 3036406.3 | AV100: 1344272 | AW100: 7567597.6 | AX100: 3078571.8 | AY100: 1930366.7 | AZ100: 2553359.2 | BA100: 4220039.6 | BB100: 450075.56 | BC100: 736942.9 | BD100: 1002268.1 | BE100: 23473166 | BF100: 2119015.8 | BG100: 364775.92 | BH100: 1150659.7 | BI100: 418203.02 | BJ100: 5035508.6 | BK100: 2675528.2 | BL100: 1282273.4 | BM100: 621741.13 | BN100: 663574.2 | BO100: 401664.22 | BP100: 415006.96 | BQ100: 1389705.4 | BR100: 3868208.1 | BS100: 36692.72 | BT100: 115658.89 | BU100: 542945.35 | BV100: 1464108.6 | BW100: 349610.59 | BX100: 1090780.1 | BY100: 1365296.8
A101: PASIVOS | D101: 8.494189e+08 | E101: 8.1437453e+08 | F101: 5.8209593e+08 | G101: 2.322786e+08 | H101: 31505449 | I101: 3538920.2 | J101: 8.1874527e+08 | K101: 7.8723983e+08 | L101: 5.6167066e+08 | M101: 2.2556916e+08 | N101: 31505449 | O101: 5.9317611e+08 | P101: 12517176 | Q101: 12517176 | R101: 12328712 | S101: 188463.59 | T101: 14617531 | U101: 8096559.9 | V101: 6520971 | W101: 14617531 | X101: 14617531 | Y101: 8096559.9 | Z101: 6520971 | AA101: 3538920.2 | AB101: 95306865 | AC101: 29668025 | AD101: 26074077 | AE101: 2.0702394e+08 | AF101: 11897622 | AG101: 34061951 | AH101: 93071571 | AI101: 49891626 | AJ101: 17492294 | AK101: 1.2275806e+08 | AL101: 40328606 | AM101: 31505449 | AN101: 17798480 | AO101: 2030947 | AP101: 1791118.8 | AQ101: 1573595.8 | AR101: 4428093 | AS101: 3271555.2 | AT101: 6746071.2 | AU101: 2840241.4 | AV101: 1123548.8 | AW101: 6920749.2 | AX101: 2674494 | AY101: 1635622.4 | AZ101: 2213532.5 | BA101: 3328415.5 | BB101: 139740.09 | BC101: 299860.41 | BD101: 849122.36 | BE101: 12057091 | BF101: 80161.7 | BG101: 188463.59 | BH101: 143362.66 | BI101: 48096.14 | BJ101: 4522439.9 | BK101: 2376935.2 | BL101: 1191340 | BM101: 550367.83 | BN101: 568540.12 | BO101: 295200.09 | BP101: 336231.09 | BQ101: 1263872 | BR101: 3493924.5 | BS101: 14104.87 | BT101: 4575.35 | BU101: 450614.13 | BV101: 821126.36 | BW101: 308434.58 | BX101: 915398.68 | BY101: 1043346.5
B102: INSTRUMENTOS FINANCIEROS A COSTO AMORTIZADO | D102: 7.1054212e+08 | E102: 6.8742971e+08 | F102: 4.9599011e+08 | G102: 1.914396e+08 | H102: 20067953 | I102: 3044455 | J102: 6.8662181e+08 | K102: 6.6655386e+08 | L102: 4.7723086e+08 | M102: 1.8932301e+08 | N102: 20067953 | O102: 4.9729881e+08 | P102: 11401603 | Q102: 11401603 | R102: 11259713 | S102: 141890.69 | T102: 9474242.5 | U102: 7499536.3 | V102: 1974706.1 | W102: 9474242.5 | X102: 9474242.5 | Y102: 7499536.3 | Z102: 1974706.1 | AA102: 3044455 | AB102: 81661796 | AC102: 27501224 | AD102: 20273390 | AE102: 1.7382891e+08 | AF102: 11302592 | AG102: 31034669 | AH102: 75067976 | AI102: 42973108 | AJ102: 16698493 | AK102: 1.003292e+08 | AL102: 34608503 | AM102: 20067953 | AN102: 16649479 | AO102: 1814979.7 | AP102: 904846.43 | AQ102: 1249379.9 | AR102: 4169712.6 | AS102: 2470807.5 | AT102: 5730878.9 | AU102: 1868661.1 | AV102: 904345.59 | AW102: 6141139.2 | AX102: 1992232.5 | AY102: 1356314.7 | AZ102: 2037510.3 | BA102: 3111457 | BB102: 26247.8 | BC102: 183738.55 | BD102: 662267.25 | BE102: 11259713 | BF102: 0 | BG102: 141890.69 | BH102: 0 | BI102: 0 | BJ102: 4179747.6 | BK102: 470576.39 | BL102: 1143161.5 | BM102: 491529.94 | BN102: 519753.45 | BO102: 100726.44 | BP102: 183882.75 | BQ102: 1165343.9 | BR102: 1218559.8 | BS102: 960.81 | BT102: 0 | BU102: 393235.81 | BV102: 680761.77 | BW102: 255165.19 | BX102: 853883.96 | BY102: 861408.32
C103: DEPÓSITOS EN CUENTA CORRIENTE | D103: 80607581 | E103: 78996669 | F103: 58550074 | G103: 20446596 | H103: 1610912.1 | I103: 0 | J103: 80607581 | K103: 78996669 | L103: 58550074 | M103: 20446596 | N103: 1610912.1 | O103: 60160986 | P103: 0 | Q103: 0 | R103: 0 | S103: 0 | T103: 0 | U103: 0 | V103: 0 | W103: 0 | X103: 0 | Y103: 0 | Z103: 0 | AA103: 0 | AB103: 15523635 | AC103: 1104012.2 | AD103: 2080960.1 | AE103: 22401304 | AF103: 4627367.5 | AG103: 1765360.2 | AH103: 9022094.7 | AI103: 6617031.9 | AJ103: 1513379.7 | AK103: 9590870.8 | AL103: 2045952.2 | AM103: 1610912.1 | AN103: 1481641.4 | AO103: 2041.66 | AP103: 0 | AQ103: 0 | AR103: 197429.71 | AS103: 11.19 | AT103: 32274.84 | AU103: 148353.52 | AV103: 98432.46 | AW103: 271795.33 | AX103: 0 | AY103: 40.36 | AZ103: 20243.83 | BA103: 309193.49 | BB103: 0 | BC103: 143243.7 | BD103: 0 | BE103: 0 | BF103: 0 | BG103: 0 | BH103: 0 | BI103: 0 | BJ103: 0 | BK103: 0 | BL103: 0 | BM103: 0 | BN103: 0 | BO103: 0 | BP103: 0 | BQ103: 0 | BR103: 0 | BS103: 0 | BT103: 0 | BU103: 0 | BV103: 0 | BW103: 0 | BX103: 0 | BY103: 0
C104: DEPÓSITOS SIMPLES | D104: 1614.77 | E104: 1614.77 | F104: 0 | G104: 1614.77 | H104: 0 | I104: 0 | J104: 1614.77 | K104: 1614.77 | L104: 0 | M104: 1614.77 | N104: 0 | O104: 0 | P104: 0 | Q104: 0 | R104: 0 | S104: 0 | T104: 0 | U104: 0 | V104: 0 | W104: 0 | X104: 0 | Y104: 0 | Z104: 0 | AA104: 0 | AB104: 0 | AC104: 0 | AD104: 0 | AE104: 0 | AF104: 0 | AG104: 0 | AH104: 1614.77 | AI104: 0 | AJ104: 0 | AK104: 0 | AL104: 0 | AM104: 0 | AN104: 0 | AO104: 0 | AP104: 0 | AQ104: 0 | AR104: 0 | AS104: 0 | AT104: 0 | AU104: 0 | AV104: 0 | AW104: 0 | AX104: 0 | AY104: 0 | AZ104: 0 | BA104: 0 | BB104: 0 | BC104: 0 | BD104: 0 | BE104: 0 | BF104: 0 | BG104: 0 | BH104: 0 | BI104: 0 | BJ104: 0 | BK104: 0 | BL104: 0 | BM104: 0 | BN104: 0 | BO104: 0 | BP104: 0 | BQ104: 0 | BR104: 0 | BS104: 0 | BT104: 0 | BU104: 0 | BV104: 0 | BW104: 0 | BX104: 0 | BY104: 0
C105: CERTIFICADOS DE DEPÓSITO A TERMINO | D105: 2.224414e+08 | E105: 2.1891713e+08 | F105: 1.5569257e+08 | G105: 63224561 | H105: 1287375.6 | I105: 2236900.1 | J105: 2.0685534e+08 | K105: 2.0556797e+08 | L105: 1.4392168e+08 | M105: 61646287 | N105: 1287375.6 | O105: 1.4520906e+08 | P105: 5142820.3 | Q105: 5142820.3 | R105: 5142820.3 | S105: 0 | T105: 8206338 | U105: 6628064.1 | V105: 1578274 | W105: 8206338 | X105: 8206338 | Y105: 6628064.1 | Z105: 1578274 | AA105: 2236900.1 | AB105: 24354667 | AC105: 10793002 | AD105: 7546645.8 | AE105: 44506484 | AF105: 1015.71 | AG105: 4411901.7 | AH105: 28550967 | AI105: 10549742 | AJ105: 5954643.1 | AK105: 31907142 | AL105: 13645216 | AM105: 1287375.6 | AN105: 4198082.5 | AO105: 1727292.5 | AP105: 596747.23 | AQ105: 546959.39 | AR105: 2145037.3 | AS105: 1966672.2 | AT105: 4419380.8 | AU105: 1141332.8 | AV105: 429295.96 | AW105: 1849178.5 | AX105: 1435276.3 | AY105: 1046242.7 | AZ105: 1304224.2 | BA105: 40153.34 | BB105: 0 | BC105: 40494.85 | BD105: 460171.17 | BE105: 5142820.3 | BF105: 0 | BG105: 0 | BH105: 0 | BI105: 0 | BJ105: 4055482.9 | BK105: 305870.54 | BL105: 986823.05 | BM105: 455127.21 | BN105: 174098.79 | BO105: 99903.02 | BP105: 143728.03 | BQ105: 956532.09 | BR105: 1028772.4 | BS105: 0 | BT105: 0 | BU105: 232717.97 | BV105: 612441.19 | BW105: 201762.36 | BX105: 659651.37 | BY105: 530327.23
C106: DEPÓSITOS DE AHORRO | D106: 2.9501673e+08 | E106: 2.8734911e+08 | F106: 2.1478685e+08 | G106: 72562260 | H106: 6943437 | I106: 724174.33 | J106: 2.9268336e+08 | K106: 2.8573992e+08 | L106: 2.1320863e+08 | M106: 72531288 | N106: 6943437 | O106: 2.2015207e+08 | P106: 1240104.9 | Q106: 1240104.9 | R106: 1209594.9 | S106: 30509.97 | T106: 369086.79 | U106: 368624.25 | V106: 462.54 | W106: 369086.79 | X106: 369086.79 | Y106: 368624.25 | Z106: 462.54 | AA106: 724174.33 | AB106: 29364301 | AC106: 12419228 | AD106: 6251258.8 | AE106: 85032599 | AF106: 2620649.3 | AG106: 12864628 | AH106: 29667049 | AI106: 21195085 | AJ106: 8205749 | AK106: 44756737 | AL106: 16367514 | AM106: 6943437 | AN106: 9076218.9 | AO106: 14086.47 | AP106: 155463.15 | AQ106: 356405.99 | AR106: 1235322.4 | AS106: 122012.53 | AT106: 1018934.8 | AU106: 517212.63 | AV106: 371131.16 | AW106: 3224041.7 | AX106: 269411.59 | AY106: 187914.61 | AZ106: 219923.15 | BA106: 0 | BB106: 26247.8 | BC106: 0 | BD106: 200798.22 | BE106: 1209594.9 | BF106: 0 | BG106: 30509.97 | BH106: 0 | BI106: 0 | BJ106: 0 | BK106: 0 | BL106: 126367.77 | BM106: 36402.73 | BN106: 44.77 | BO106: 462.54 | BP106: 0 | BQ106: 205808.98 | BR106: 0 | BS106: 0 | BT106: 0 | BU106: 130596.94 | BV106: 68320.58 | BW106: 51194.07 | BX106: 172746.62 | BY106: 301316.12
C107: CUENTAS DE AHORRO ESPECIAL | D107: 1729273.4 | E107: 1714828.3 | F107: 1171044.4 | G107: 543783.9 | H107: 0 | I107: 14445.14 | J107: 1714828.3 | K107: 1714828.3 | L107: 1171044.4 | M107: 543783.9 | N107: 0 | O107: 1171044.4 | P107: 0 | Q107: 0 | R107: 0 | S107: 0 | T107: 0 | U107: 0 | V107: 0 | W107: 0 | X107: 0 | Y107: 0 | Z107: 0 | AA107: 14445.14 | AB107: 84444.7 | AC107: 0 | AD107: 0 | AE107: 742031.01 | AF107: 0 | AG107: 0 | AH107: 329708.93 | AI107: 21245.01 | AJ107: 137395.77 | AK107: 77341.03 | AL107: 214074.97 | AM107: 0 | AN107: 76687.99 | AO107: 0 | AP107: 0 | AQ107: 0 | AR107: 31898.86 | AS107: 0 | AT107: 0 | AU107: 0 | AV107: 0 | AW107: 0 | AX107: 0 | AY107: 0 | AZ107: 0 | BA107: 0 | BB107: 0 | BC107: 0 | BD107: 0 | BE107: 0 | BF107: 0 | BG107: 0 | BH107: 0 | BI107: 0 | BJ107: 0 | BK107: 0 | BL107: 0 | BM107: 0 | BN107: 0 | BO107: 0 | BP107: 0 | BQ107: 0 | BR107: 0 | BS107: 0 | BT107: 0 | BU107: 0 | BV107: 0 | BW107: 1747.74 | BX107: 12697.4 | BY107: 0
C108: CERTIFICADOS DE AHORRO DE VALOR REAL | D108: 1003757.4 | E108: 1003757.4 | F108: 992028.7 | G108: 11728.73 | H108: 0 | I108: 0 | J108: 1003757.4 | K108: 1003757.4 | L108: 992028.7 | M108: 11728.73 | N108: 0 | O108: 992028.7 | P108: 0 | Q108: 0 | R108: 0 | S108: 0 | T108: 0 | U108: 0 | V108: 0 | W108: 0 | X108: 0 | Y108: 0 | Z108: 0 | AA108: 0 | AB108: 0 | AC108: 0 | AD108: 0 | AE108: 0 | AF108: 0 | AG108: 0 | AH108: 11728.73 | AI108: 0 | AJ108: 9427.55 | AK108: 982601.15 | AL108: 0 | AM108: 0 | AN108: 0 | AO108: 0 | AP108: 0 | AQ108: 0 | AR108: 0 | AS108: 0 | AT108: 0 | AU108: 0 | AV108: 0 | AW108: 0 | AX108: 0 | AY108: 0 | AZ108: 0 | BA108: 0 | BB108: 0 | BC108: 0 | BD108: 0 | BE108: 0 | BF108: 0 | BG108: 0 | BH108: 0 | BI108: 0 | BJ108: 0 | BK108: 0 | BL108: 0 | BM108: 0 | BN108: 0 | BO108: 0 | BP108: 0 | BQ108: 0 | BR108: 0 | BS108: 0 | BT108: 0 | BU108: 0 | BV108: 0 | BW108: 0 | BX108: 0 | BY108: 0
C109: DOCUMENTOS POR PAGAR | D109: 1277.8 | E109: 1277.8 | F109: 0 | G109: 1277.8 | H109: 0 | I109: 0 | J109: 1277.8 | K109: 1277.8 | L109: 0 | M109: 1277.8 | N109: 0 | O109: 0 | P109: 0 | Q109: 0 | R109: 0 | S109: 0 | T109: 0 | U109: 0 | V109: 0 | W109: 0 | X109: 0 | Y109: 0 | Z109: 0 | AA109: 0 | AB109: 0 | AC109: 0 | AD109: 0 | AE109: 0 | AF109: 0 | AG109: 0 | AH109: 0 | AI109: 0 | AJ109: 0 | AK109: 0 | AL109: 1277.8 | AM109: 0 | AN109: 0 | AO109: 0 | AP109: 0 | AQ109: 0 | AR109: 0 | AS109: 0 | AT109: 0 | AU109: 0 | AV109: 0 | AW109: 0 | AX109: 0 | AY109: 0 | AZ109: 0 | BA109: 0 | BB109: 0 | BC109: 0 | BD109: 0 | BE109: 0 | BF109: 0 | BG109: 0 | BH109: 0 | BI109: 0 | BJ109: 0 | BK109: 0 | BL109: 0 | BM109: 0 | BN109: 0 | BO109: 0 | BP109: 0 | BQ109: 0 | BR109: 0 | BS109: 0 | BT109: 0 | BU109: 0 | BV109: 0 | BW109: 0 | BX109: 0 | BY109: 0
C110: FONDOS EN FIDEICOMISO Y CUENTAS ESPECIALES | D110: 500.64 | E110: 500.64 | F110: 500.64 | G110: 0 | H110: 0 | I110: 0 | J110: 500.64 | K110: 500.64 | L110: 500.64 | M110: 0 | N110: 0 | O110: 500.64 | P110: 0 | Q110: 0 | R110: 0 | S110: 0 | T110: 0 | U110: 0 | V110: 0 | W110: 0 | X110: 0 | Y110: 0 | Z110: 0 | AA110: 0 | AB110: 499.42 | AC110: 0 | AD110: 0 | AE110: 0 | AF110: 0 | AG110: 0 | AH110: 0 | AI110: 1.22 | AJ110: 0 | AK110: 0 | AL110: 0 | AM110: 0 | AN110: 0 | AO110: 0 | AP110: 0 | AQ110: 0 | AR110: 0 | AS110: 0 | AT110: 0 | AU110: 0 | AV110: 0 | AW110: 0 | AX110: 0 | AY110: 0 | AZ110: 0 | BA110: 0 | BB110: 0 | BC110: 0 | BD110: 0 | BE110: 0 | BF110: 0 | BG110: 0 | BH110: 0 | BI110: 0 | BJ110: 0 | BK110: 0 | BL110: 0 | BM110: 0 | BN110: 0 | BO110: 0 | BP110: 0 | BQ110: 0 | BR110: 0 | BS110: 0 | BT110: 0 | BU110: 0 | BV110: 0 | BW110: 0 | BX110: 0 | BY110: 0
C111: BANCOS Y CORRESPONSALES | D111: 45190.15 | E111: 42363.15 | F111: 21142.17 | G111: 21220.98 | H111: 2827 | I111: 0 | J111: 45190.15 | K111: 42363.15 | L111: 21142.17 | M111: 21220.98 | N111: 2827 | O111: 23969.17 | P111: 0 | Q111: 0 | R111: 0 | S111: 0 | T111: 0 | U111: 0 | V111: 0 | W111: 0 | X111: 0 | Y111: 0 | Z111: 0 | AA111: 0 | AB111: 8165.64 | AC111: 7926.36 | AD111: 756.77 | AE111: 0 | AF111: 5915.26 | AG111: 0 | AH111: 1794.03 | AI111: 1156.57 | AJ111: 0 | AK111: 3633.94 | AL111: 0 | AM111: 2827 | AN111: 0 | AO111: 0 | AP111: 0 | AQ111: 0 | AR111: 0 | AS111: 0 | AT111: 0 | AU111: 0 | AV111: 0 | AW111: 12754.92 | AX111: 0 | AY111: 0 | AZ111: 259.66 | BA111: 0 | BB111: 0 | BC111: 0 | BD111: 0 | BE111: 0 | BF111: 0 | BG111: 0 | BH111: 0 | BI111: 0 | BJ111: 0 | BK111: 0 | BL111: 0 | BM111: 0 | BN111: 0 | BO111: 0 | BP111: 0 | BQ111: 0 | BR111: 0 | BS111: 0 | BT111: 0 | BU111: 0 | BV111: 0 | BW111: 0 | BX111: 0 | BY111: 0
C112: DEPÓSITOS ESPECIALES | D112: 12145579 | E112: 3591891.2 | F112: 2011098 | G112: 1580793.2 | H112: 8487832.2 | I112: 65855.26 | J112: 11803581 | K112: 3315748.6 | L112: 1734955.4 | M112: 1580793.2 | N112: 8487832.2 | O112: 10222788 | P112: 276142.61 | Q112: 276142.61 | R112: 276142.61 | S112: 0 | T112: 0 | U112: 0 | V112: 0 | W112: 0 | X112: 0 | Y112: 0 | Z112: 0 | AA112: 65855.26 | AB112: 384352.73 | AC112: 12013.14 | AD112: 23561.88 | AE112: 915864.78 | AF112: 1408.4 | AG112: 10845.12 | AH112: 1174119 | AI112: 90322.32 | AJ112: 11652.74 | AK112: 284437.1 | AL112: 310108.54 | AM112: 8487832.2 | AN112: 32465.43 | AO112: 0 | AP112: 0 | AQ112: 0 | AR112: 0 | AS112: 4.77 | AT112: 0 | AU112: 0 | AV112: 0 | AW112: 60750.25 | AX112: 3842.43 | AY112: 0 | AZ112: 0 | BA112: 0 | BB112: 0 | BC112: 0 | BD112: 0 | BE112: 276142.61 | BF112: 0 | BG112: 0 | BH112: 0 | BI112: 0 | BJ112: 0 | BK112: 0 | BL112: 0 | BM112: 0 | BN112: 0 | BO112: 0 | BP112: 0 | BQ112: 0 | BR112: 0 | BS112: 0 | BT112: 0 | BU112: 27892.6 | BV112: 0 | BW112: 0 | BX112: 8576.13 | BY112: 29386.53
C113: EXIGIBILIDADES POR SERVICIOS | D113: 4483079.4 | E113: 4350901 | F113: 3257398.5 | G113: 1093502.5 | H113: 132178.42 | I113: 0 | J113: 4476427.1 | K113: 4344248.7 | L113: 3255114.8 | M113: 1089133.9 | N113: 132178.42 | O113: 3387293.3 | P113: 5548.05 | Q113: 5548.05 | R113: 1179.46 | S113: 4368.59 | T113: 1104.24 | U113: 1104.24 | V113: 0 | W113: 1104.24 | X113: 1104.24 | Y113: 1104.24 | Z113: 0 | AA113: 0 | AB113: 324578.91 | AC113: 57860.25 | AD113: 170959.48 | AE113: 1406307.1 | AF113: 139425.88 | AG113: 61507.84 | AH113: 417957.69 | AI113: 316128.17 | AJ113: 139961.16 | AK113: 807428.18 | AL113: 240395.35 | AM113: 132178.42 | AN113: 68058.03 | AO113: 509.61 | AP113: 9635.49 | AQ113: 27404.7 | AR113: 47839.39 | AS113: 9676.2 | AT113: 20363.1 | AU113: 24280.01 | AV113: 291.78 | AW113: 14244.52 | AX113: 0 | AY113: 8963.28 | AZ113: 29175.15 | BA113: 0 | BB113: 0 | BC113: 0 | BD113: 1297.41 | BE113: 1179.46 | BF113: 0 | BG113: 4368.59 | BH113: 0 | BI113: 0 | BJ113: 0 | BK113: 0 | BL113: 1104.24 | BM113: 0 | BN113: 0 | BO113: 0 | BP113: 0 | BQ113: 0 | BR113: 0 | BS113: 0 | BT113: 0 | BU113: 0 | BV113: 0 | BW113: 0 | BX113: 0 | BY113: 0
C114: SERVICIOS DE RECAUDO | D114: 97420.37 | E114: 94434.09 | F114: 90282.2 | G114: 4151.89 | H114: 0 | I114: 2986.28 | J114: 94434.09 | K114: 94434.09 | L114: 90282.2 | M114: 4151.89 | N114: 0 | O114: 90282.2 | P114: 0 | Q114: 0 | R114: 0 | S114: 0 | T114: 0 | U114: 0 | V114: 0 | W114: 0 | X114: 0 | Y114: 0 | Z114: 0 | AA114: 2986.28 | AB114: 71126.46 | AC114: 140.38 | AD114: 0 | AE114: 0 | AF114: 4151.89 | AG114: 0 | AH114: 0 | AI114: 2134.07 | AJ114: 0 | AK114: 0 | AL114: 0 | AM114: 0 | AN114: 16881.29 | AO114: 0 | AP114: 0 | AQ114: 0 | AR114: 0 | AS114: 0 | AT114: 0 | AU114: 0 | AV114: 0 | AW114: 0 | AX114: 0 | AY114: 0 | AZ114: 0 | BA114: 0 | BB114: 0 | BC114: 0 | BD114: 0 | BE114: 0 | BF114: 0 | BG114: 0 | BH114: 0 | BI114: 0 | BJ114: 0 | BK114: 0 | BL114: 0 | BM114: 0 | BN114: 0 | BO114: 0 | BP114: 0 | BQ114: 0 | BR114: 0 | BS114: 0 | BT114: 0 | BU114: 1935.18 | BV114: 0 | BW114: 461.02 | BX114: 211.64 | BY114: 378.44
... C124: OPERACIONES REPO DE CONTRACCIÓN MONETARIA | D124: 0 | E124: 0 | F124: 0 | G124: 0 | H124: 0 | I124: 0 | J124: 0 | K124: 0 | L124: 0 | M124: 0 | N124: 0 | O124: 0 | P124: 0 | Q124: 0 | R124: 0 | S124: 0 | T124: 0 | U124: 0 | V124: 0 | W124: 0 | X124: 0 | Y124: 0 | Z124: 0 | AA124: 0 | AB124: 0 | AC124: 0 | AD124: 0 | AE124: 0 | AF124: 0 | AG124: 0 | AH124: 0 | AI124: 0 | AJ124: 0 | AK124: 0 | AL124: 0 | AM124: 0 | AN124: 0 | AO124: 0 | AP124: 0 | AQ124: 0 | AR124: 0 | AS124: 0 | AT124: 0 | AU124: 0 | AV124: 0 | AW124: 0 | AX124: 0 | AY124: 0 | AZ124: 0 | BA124: 0 | BB124: 0 | BC124: 0 | BD124: 0 | BE124: 0 | BF124: 0 | BG124: 0 | BH124: 0 | BI124: 0 | BJ124: 0 | BK124: 0 | BL124: 0 | BM124: 0 | BN124: 0 | BO124: 0 | BP124: 0 | BQ124: 0 | BR124: 0 | BS124: 0 | BT124: 0 | BU124: 0 | BV124: 0 | BW124: 0 | BX124: 0 | BY124: 0
B125: INSTRUMENTOS FINANCIEROS A VALOR RAZONABLE | D125: 21844972 | E125: 21842741 | F125: 9205431.2 | G125: 12637310 | H125: 2230.87 | I125: 0 | J125: 21351274 | K125: 21349043 | L125: 8714971.2 | M125: 12634072 | N125: 2230.87 | O125: 8717202 | P125: 493023.11 | Q125: 493023.11 | R125: 489785.36 | S125: 3237.75 | T125: 674.73 | U125: 674.73 | V125: 0 | W125: 674.73 | X125: 674.73 | Y125: 674.73 | Z125: 0 | AA125: 0 | AB125: 630892.65 | AC125: 18968.4 | AD125: 979743.02 | AE125: 4717940.8 | AF125: 251035.05 | AG125: 23263.26 | AH125: 10191286 | AI125: 930746.37 | AJ125: 0 | AK125: 2350561.7 | AL125: 967636.4 | AM125: 2230.87 | AN125: 2106.54 | AO125: 0 | AP125: 0 | AQ125: 418.8 | AR125: 0 | AS125: 0 | AT125: 649.06 | AU125: 2153.78 | AV125: 0 | AW125: 153752.7 | AX125: 0 | AY125: 0 | AZ125: 0 | BA125: 64553.5 | BB125: 0 | BC125: 0 | BD125: 63335.9 | BE125: 473844.64 | BF125: 0 | BG125: 3237.75 | BH125: 15940.72 | BI125: 0 | BJ125: 0 | BK125: 0 | BL125: 674.73 | BM125: 0 | BN125: 0 | BO125: 0 | BP125: 0 | BQ125: 0 | BR125: 0 | BS125: 0 | BT125: 0 | BU125: 0 | BV125: 0 | BW125: 0 | BX125: 0 | BY125: 0
C126: CONTRATOS FORWARD - DE NEGOCIACIÓN | D126: 6993746.4 | E126: 6993625.1 | F126: 3319048.9 | G126: 3674576.2 | H126: 121.33 | I126: 0 | J126: 6621082.5 | K126: 6620961.2 | L126: 2949609.7 | M126: 3671351.5 | N126: 121.33 | O126: 2949731 | P126: 372663.87 | Q126: 372663.87 | R126: 369439.23 | S126: 3224.64 | T126: 0 | U126: 0 | V126: 0 | W126: 0 | X126: 0 | Y126: 0 | Z126: 0 | AA126: 0 | AB126: 291506.19 | AC126: 18968.4 | AD126: 147841.02 | AE126: 1714402.6 | AF126: 196110.3 | AG126: 3912.52 | AH126: 2918593.8 | AI126: 448366.93 | AJ126: 0 | AK126: 476365.56 | AL126: 208587.63 | AM126: 121.33 | AN126: 0 | AO126: 0 | AP126: 0 | AQ126: 0 | AR126: 0 | AS126: 0 | AT126: 348.77 | AU126: 0 | AV126: 0 | AW126: 141272.15 | AX126: 0 | AY126: 0 | AZ126: 0 | BA126: 54685.37 | BB126: 0 | BC126: 0 | BD126: 0 | BE126: 363728.14 | BF126: 0 | BG126: 3224.64 | BH126: 5711.09 | BI126: 0 | BJ126: 0 | BK126: 0 | BL126: 0 | BM126: 0 | BN126: 0 | BO126: 0 | BP126: 0 | BQ126: 0 | BR126: 0 | BS126: 0 | BT126: 0 | BU126: 0 | BV126: 0 | BW126: 0 | BX126: 0 | BY126: 0
C127: CONTRATOS DE FUTUROS – DE NEGOCIACIÓN | D127: 11930.83 | E127: 11930.83 | F127: 2106.54 | G127: 9824.29 | H127: 0 | I127: 0 | J127: 11930.83 | K127: 11930.83 | L127: 2106.54 | M127: 9824.29 | N127: 0 | O127: 2106.54 | P127: 0 | Q127: 0 | R127: 0 | S127: 0 | T127: 0 | U127: 0 | V127: 0 | W127: 0 | X127: 0 | Y127: 0 | Z127: 0 | AA127: 0 | AB127: 0 | AC127: 0 | AD127: 0 | AE127: 0 | AF127: 0 | AG127: 0 | AH127: 0 | AI127: 0 | AJ127: 0 | AK127: 0 | AL127: 0 | AM127: 0 | AN127: 2106.54 | AO127: 0 | AP127: 0 | AQ127: 0 | AR127: 0 | AS127: 0 | AT127: 0 | AU127: 0 | AV127: 0 | AW127: 0 | AX127: 0 | AY127: 0 | AZ127: 0 | BA127: 9824.29 | BB127: 0 | BC127: 0 | BD127: 0 | BE127: 0 | BF127: 0 | BG127: 0 | BH127: 0 | BI127: 0 | BJ127: 0 | BK127: 0 | BL127: 0 | BM127: 0 | BN127: 0 | BO127: 0 | BP127: 0 | BQ127: 0 | BR127: 0 | BS127: 0 | BT127: 0 | BU127: 0 | BV127: 0 | BW127: 0 | BX127: 0 | BY127: 0
C128: SWAPS – DE NEGOCIACIÓN | D128: 14289315 | E128: 14287205 | F128: 5539653.3 | G128: 8747551.8 | H128: 2109.54 | I128: 0 | J128: 14216990 | K128: 14214881 | L128: 5467328.8 | M128: 8747551.8 | N128: 2109.54 | O128: 5469438.4 | P128: 72324.42 | Q128: 72324.42 | R128: 72324.42 | S128: 0 | T128: 0 | U128: 0 | V128: 0 | W128: 0 | X128: 0 | Y128: 0 | Z128: 0 | AA128: 0 | AB128: 262180.1 | AC128: 0 | AD128: 734283.53 | AE128: 2910096.9 | AF128: 44701.92 | AG128: 860.44 | AH128: 7223045.4 | AI128: 452703.88 | AJ128: 0 | AK128: 1842348 | AL128: 732377.12 | AM128: 2109.54 | AN128: 0 | AO128: 0 | AP128: 0 | AQ128: 0 | AR128: 0 | AS128: 0 | AT128: 300.29 | AU128: 0 | AV128: 0 | AW128: 11983.07 | AX128: 0 | AY128: 0 | AZ128: 0 | BA128: 0 | BB128: 0 | BC128: 0 | BD128: 0 | BE128: 72324.42 | BF128: 0 | BG128: 0 | BH128: 0 | BI128: 0 | BJ128: 0 | BK128: 0 | BL128: 0 | BM128: 0 | BN128: 0 | BO128: 0 | BP128: 0 | BQ128: 0 | BR128: 0 | BS128: 0 | BT128: 0 | BU128: 0 | BV128: 0 | BW128: 0 | BX128: 0 | BY128: 0
C129: OPCIONES DE NEGOCIACIÓN | D129: 342254.64 | E129: 342254.64 | F129: 267921.14 | G129: 74333.5 | H129: 0 | I129: 0 | J129: 304462.56 | K129: 304462.56 | L129: 230129.06 | M129: 74333.5 | N129: 0 | O129: 230129.06 | P129: 37792.08 | Q129: 37792.08 | R129: 37792.08 | S129: 0 | T129: 0 | U129: 0 | V129: 0 | W129: 0 | X129: 0 | Y129: 0 | Z129: 0 | AA129: 0 | AB129: 75961.91 | AC129: 0 | AD129: 219.32 | AE129: 92908.04 | AF129: 9056.05 | AG129: 0 | AH129: 49178.95 | AI129: 29675.56 | AJ129: 0 | AK129: 31583.55 | AL129: 15879.18 | AM129: 0 | AN129: 0 | AO129: 0 | AP129: 0 | AQ129: 0 | AR129: 0 | AS129: 0 | AT129: 0 | AU129: 0 | AV129: 0 | AW129: 0 | AX129: 0 | AY129: 0 | AZ129: 0 | BA129: 0 | BB129: 0 | BC129: 0 | BD129: 0 | BE129: 37792.08 | BF129: 0 | BG129: 0 | BH129: 0 | BI129: 0 | BJ129: 0 | BK129: 0 | BL129: 0 | BM129: 0 | BN129: 0 | BO129: 0 | BP129: 0 | BQ129: 0 | BR129: 0 | BS129: 0 | BT129: 0 | BU129: 0 | BV129: 0 | BW129: 0 | BX129: 0 | BY129: 0
C130: CONTRATOS FORWARD - DE COBERTURA | D130: 34851.07 | E130: 34851.07 | F130: 10732.11 | G130: 24118.96 | H130: 0 | I130: 0 | J130: 24118.96 | K130: 24118.96 | L130: 0 | M130: 24118.96 | N130: 0 | O130: 0 | P130: 10229.63 | Q130: 10229.63 | R130: 10229.63 | S130: 0 | T130: 502.48 | U130: 502.48 | V130: 0 | W130: 502.48 | X130: 502.48 | Y130: 502.48 | Z130: 0 | AA130: 0 | AB130: 0 | AC130: 0 | AD130: 21965.18 | AE130: 0 | AF130: 0 | AG130: 0 | AH130: 0 | AI130: 0 | AJ130: 0 | AK130: 0 | AL130: 0 | AM130: 0 | AN130: 0 | AO130: 0 | AP130: 0 | AQ130: 0 | AR130: 0 | AS130: 0 | AT130: 0 | AU130: 2153.78 | AV130: 0 | AW130: 0 | AX130: 0 | AY130: 0 | AZ130: 0 | BA130: 0 | BB130: 0 | BC130: 0 | BD130: 0 | BE130: 0 | BF130: 0 | BG130: 0 | BH130: 10229.63 | BI130: 0 | BJ130: 0 | BK130: 0 | BL130: 502.48 | BM130: 0 | BN130: 0 | BO130: 0 | BP130: 0 | BQ130: 0 | BR130: 0 | BS130: 0 | BT130: 0 | BU130: 0 | BV130: 0 | BW130: 0 | BX130: 0 | BY130: 0
C131: CONTRATOS DE FUTUROS – DE COBERTURA | D131: 0 | E131: 0 | F131: 0 | G131: 0 | H131: 0 | I131: 0 | J131: 0 | K131: 0 | L131: 0 | M131: 0 | N131: 0 | O131: 0 | P131: 0 | Q131: 0 | R131: 0 | S131: 0 | T131: 0 | U131: 0 | V131: 0 | W131: 0 | X131: 0 | Y131: 0 | Z131: 0 | AA131: 0 | AB131: 0 | AC131: 0 | AD131: 0 | AE131: 0 | AF131: 0 | AG131: 0 | AH131: 0 | AI131: 0 | AJ131: 0 | AK131: 0 | AL131: 0 | AM131: 0 | AN131: 0 | AO131: 0 | AP131: 0 | AQ131: 0 | AR131: 0 | AS131: 0 | AT131: 0 | AU131: 0 | AV131: 0 | AW131: 0 | AX131: 0 | AY131: 0 | AZ131: 0 | BA131: 0 | BB131: 0 | BC131: 0 | BD131: 0 | BE131: 0 | BF131: 0 | BG131: 0 | BH131: 0 | BI131: 0 | BJ131: 0 | BK131: 0 | BL131: 0 | BM131: 0 | BN131: 0 | BO131: 0 | BP131: 0 | BQ131: 0 | BR131: 0 | BS131: 0 | BT131: 0 | BU131: 0 | BV131: 0 | BW131: 0 | BX131: 0 | BY131: 0
C132: SWAPS – DE COBERTURA | D132: 86633.37 | E132: 86633.37 | F132: 1228.47 | G132: 85404.9 | H132: 0 | I132: 0 | J132: 86633.37 | K132: 86633.37 | L132: 1228.47 | M132: 85404.9 | N132: 0 | O132: 1228.47 | P132: 0 | Q132: 0 | R132: 0 | S132: 0 | T132: 0 | U132: 0 | V132: 0 | W132: 0 | X132: 0 | Y132: 0 | Z132: 0 | AA132: 0 | AB132: 1228.47 | AC132: 0 | AD132: 75381.29 | AE132: 0 | AF132: 0 | AG132: 0 | AH132: 0 | AI132: 0 | AJ132: 0 | AK132: 0 | AL132: 10023.61 | AM132: 0 | AN132: 0 | AO132: 0 | AP132: 0 | AQ132: 0 | AR132: 0 | AS132: 0 | AT132: 0 | AU132: 0 | AV132: 0 | AW132: 0 | AX132: 0 | AY132: 0 | AZ132: 0 | BA132: 0 | BB132: 0 | BC132: 0 | BD132: 0 | BE132: 0 | BF132: 0 | BG132: 0 | BH132: 0 | BI132: 0 | BJ132: 0 | BK132: 0 | BL132: 0 | BM132: 0 | BN132: 0 | BO132: 0 | BP132: 0 | BQ132: 0 | BR132: 0 | BS132: 0 | BT132: 0 | BU132: 0 | BV132: 0 | BW132: 0 | BX132: 0 | BY132: 0
C133: OPCIONES DE COBERTURA | D133: 0 | E133: 0 | F133: 0 | G133: 0 | H133: 0 | I133: 0 | J133: 0 | K133: 0 | L133: 0 | M133: 0 | N133: 0 | O133: 0 | P133: 0 | Q133: 0 | R133: 0 | S133: 0 | T133: 0 | U133: 0 | V133: 0 | W133: 0 | X133: 0 | Y133: 0 | Z133: 0 | AA133: 0 | AB133: 0 | AC133: 0 | AD133: 0 | AE133: 0 | AF133: 0 | AG133: 0 | AH133: 0 | AI133: 0 | AJ133: 0 | AK133: 0 | AL133: 0 | AM133: 0 | AN133: 0 | AO133: 0 | AP133: 0 | AQ133: 0 | AR133: 0 | AS133: 0 | AT133: 0 | AU133: 0 | AV133: 0 | AW133: 0 | AX133: 0 | AY133: 0 | AZ133: 0 | BA133: 0 | BB133: 0 | BC133: 0 | BD133: 0 | BE133: 0 | BF133: 0 | BG133: 0 | BH133: 0 | BI133: 0 | BJ133: 0 | BK133: 0 | BL133: 0 | BM133: 0 | BN133: 0 | BO133: 0 | BP133: 0 | BQ133: 0 | BR133: 0 | BS133: 0 | BT133: 0 | BU133: 0 | BV133: 0 | BW133: 0 | BX133: 0 | BY133: 0
C134: TÍTULOS DE INVERSIÓN EN CIRCULACIÓN | D134: 0 | E134: 0 | F134: 0 | G134: 0 | H134: 0 | I134: 0 | J134: 0 | K134: 0 | L134: 0 | M134: 0 | N134: 0 | O134: 0 | P134: 0 | Q134: 0 | R134: 0 | S134: 0 | T134: 0 | U134: 0 | V134: 0 | W134: 0 | X134: 0 | Y134: 0 | Z134: 0 | AA134: 0 | AB134: 0 | AC134: 0 | AD134: 0 | AE134: 0 | AF134: 0 | AG134: 0 | AH134: 0 | AI134: 0 | AJ134: 0 | AK134: 0 | AL134: 0 | AM134: 0 | AN134: 0 | AO134: 0 | AP134: 0 | AQ134: 0 | AR134: 0 | AS134: 0 | AT134: 0 | AU134: 0 | AV134: 0 | AW134: 0 | AX134: 0 | AY134: 0 | AZ134: 0 | BA134: 0 | BB134: 0 | BC134: 0 | BD134: 0 | BE134: 0 | BF134: 0 | BG134: 0 | BH134: 0 | BI134: 0 | BJ134: 0 | BK134: 0 | BL134: 0 | BM134: 0 | BN134: 0 | BO134: 0 | BP134: 0 | BQ134: 0 | BR134: 0 | BS134: 0 | BT134: 0 | BU134: 0 | BV134: 0 | BW134: 0 | BX134: 0 | BY134: 0
C135: OPERACIONES DE CONTADO | D135: 86241.25 | E135: 86241.25 | F135: 64740.82 | G135: 21500.43 | H135: 0 | I135: 0 | J135: 86055.89 | K135: 86055.89 | L135: 64568.57 | M135: 21487.32 | N135: 0 | O135: 64568.57 | P135: 13.11 | Q135: 13.11 | R135: 0 | S135: 13.11 | T135: 172.25 | U135: 172.25 | V135: 0 | W135: 172.25 | X135: 172.25 | Y135: 172.25 | Z135: 0 | AA135: 0 | AB135: 15.98 | AC135: 0 | AD135: 52.68 | AE135: 533.29 | AF135: 1166.78 | AG135: 18490.3 | AH135: 467.38 | AI135: 0 | AJ135: 0 | AK135: 264.6 | AL135: 768.86 | AM135: 0 | AN135: 0 | AO135: 0 | AP135: 0 | AQ135: 418.8 | AR135: 0 | AS135: 0 | AT135: 0 | AU135: 0 | AV135: 0 | AW135: 497.48 | AX135: 0 | AY135: 0 | AZ135: 0 | BA135: 43.84 | BB135: 0 | BC135: 0 | BD135: 63335.9 | BE135: 0 | BF135: 0 | BG135: 13.11 | BH135: 0 | BI135: 0 | BJ135: 0 | BK135: 0 | BL135: 172.25 | BM135: 0 | BN135: 0 | BO135: 0 | BP135: 0 | BQ135: 0 | BR135: 0 | BS135: 0 | BT135: 0 | BU135: 0 | BV135: 0 | BW135: 0 | BX135: 0 | BY135: 0
B136: APORTES DE CAPITAL | D136: 23085.94 | E136: 16299.87 | F136: 16299.87 | G136: 0 | H136: 0 | I136: 6786.07 | J136: 16299.87 | K136: 16299.87 | L136: 16299.87 | M136: 0 | N136: 0 | O136: 16299.87 | P136: 0 | Q136: 0 | R136: 0 | S136: 0 | T136: 0 | U136: 0 | V136: 0 | W136: 0 | X136: 0 | Y136: 0 | Z136: 0 | AA136: 6786.07 | AB136: 0 | AC136: 0 | AD136: 0 | AE136: 0 | AF136: 0 | AG136: 0 | AH136: 0 | AI136: 0 | AJ136: 0 | AK136: 0 | AL136: 0 | AM136: 0 | AN136: 0 | AO136: 0 | AP136: 0 | AQ136: 0 | AR136: 0 | AS136: 0 | AT136: 0 | AU136: 0 | AV136: 16299.87 | AW136: 0 | AX136: 0 | AY136: 0 | AZ136: 0 | BA136: 0 | BB136: 0 | BC136: 0 | BD136: 0 | BE136: 0 | BF136: 0 | BG136: 0 | BH136: 0 | BI136: 0 | BJ136: 0 | BK136: 0 | BL136: 0 | BM136: 0 | BN136: 0 | BO136: 0 | BP136: 0 | BQ136: 0 | BR136: 0 | BS136: 0 | BT136: 0 | BU136: 0 | BV136: 0 | BW136: 760 | BX136: 6026.07 | BY136: 0
B137: CRÉDITOS DE BANCOS Y OTRAS OBLIGACIONES FINANCIERAS | D137: 80031376 | E137: 69379358 | F137: 48020104 | G137: 21359253 | H137: 10416154 | I137: 235864.4 | J137: 75030827 | K137: 64614674 | L137: 47463161 | M137: 17151513 | N137: 10416154 | O137: 57879314 | P137: 356948.24 | Q137: 356948.24 | R137: 356948.24 | S137: 0 | T137: 4407735.6 | U137: 199995.27 | V137: 4207740.3 | W137: 4407735.6 | X137: 4407735.6 | Y137: 199995.27 | Z137: 4207740.3 | AA137: 235864.4 | AB137: 8941058.7 | AC137: 1005946.8 | AD137: 3664203.1 | AE137: 14161087 | AF137: 0 | AG137: 2333690.2 | AH137: 5370684.1 | AI137: 4591138.8 | AJ137: 80770.73 | AK137: 15288992 | AL137: 3689495.5 | AM137: 10416154 | AN137: 568446.47 | AO137: 106238.88 | AP137: 725526.04 | AQ137: 151378.04 | AR137: 109647.28 | AS137: 695097.26 | AT137: 763861.27 | AU137: 776663.76 | AV137: 180689.56 | AW137: 460294.33 | AX137: 510604.91 | AY137: 213146.37 | AZ137: 128243.56 | BA137: 0 | BB137: 0 | BC137: 92620.72 | BD137: 5148.05 | BE137: 230814.11 | BF137: 0 | BG137: 0 | BH137: 126134.13 | BI137: 0 | BJ137: 101491.8 | BK137: 1774187.8 | BL137: 0 | BM137: 11520.1 | BN137: 38830.67 | BO137: 149165.73 | BP137: 148763.96 | BQ137: 48152.7 | BR137: 2135619.1 | BS137: 3.77 | BT137: 0 | BU137: 19207.06 | BV137: 0 | BW137: 44315.41 | BX137: 19539.62 | BY137: 152802.31
C138: BANCO DE LA REPÚBLICA | D138: 0 | E138: 0 | F138: 0 | G138: 0 | H138: 0 | I138: 0 | J138: 0 | K138: 0 | L138: 0 | M138: 0 | N138: 0 | O138: 0 | P138: 0 | Q138: 0 | R138: 0 | S138: 0 | T138: 0 | U138: 0 | V138: 0 | W138: 0 | X138: 0 | Y138: 0 | Z138: 0 | AA138: 0 | AB138: 0 | AC138: 0 | AD138: 0 | AE138: 0 | AF138: 0 | AG138: 0 | AH138: 0 | AI138: 0 | AJ138: 0 | AK138: 0 | AL138: 0 | AM138: 0 | AN138: 0 | AO138: 0 | AP138: 0 | AQ138: 0 | AR138: 0 | AS138: 0 | AT138: 0 | AU138: 0 | AV138: 0 | AW138: 0 | AX138: 0 | AY138: 0 | AZ138: 0 | BA138: 0 | BB138: 0 | BC138: 0 | BD138: 0 | BE138: 0 | BF138: 0 | BG138: 0 | BH138: 0 | BI138: 0 | BJ138: 0 | BK138: 0 | BL138: 0 | BM138: 0 | BN138: 0 | BO138: 0 | BP138: 0 | BQ138: 0 | BR138: 0 | BS138: 0 | BT138: 0 | BU138: 0 | BV138: 0 | BW138: 0 | BX138: 0 | BY138: 0
C139: BANCO DE COMERCIO EXTERIOR (BANCOLDEX) | D139: 6231367.7 | E139: 6045343.3 | F139: 4725942.9 | G139: 1319400.4 | H139: 54716.02 | I139: 131308.3 | J139: 5988561.1 | K139: 5933845.1 | L139: 4680217.5 | M139: 1253627.6 | N139: 54716.02 | O139: 4734933.5 | P139: 0 | Q139: 0 | R139: 0 | S139: 0 | T139: 111498.24 | U139: 45725.44 | V139: 65772.8 | W139: 111498.24 | X139: 111498.24 | Y139: 45725.44 | Z139: 65772.8 | AA139: 131308.3 | AB139: 757358.16 | AC139: 214808.4 | AD139: 94374.04 | AE139: 902036.22 | AF139: 0 | AG139: 401337.71 | AH139: 574031.84 | AI139: 361686 | AJ139: 80770.38 | AK139: 601993.19 | AL139: 112013.26 | AM139: 54716.02 | AN139: 298910.56 | AO139: 355.48 | AP139: 196423.9 | AQ139: 81054.28 | AR139: 67520.66 | AS139: 565620.26 | AT139: 0 | AU139: 64455.21 | AV139: 171093.63 | AW139: 7415.57 | AX139: 178507.02 | AY139: 161509.22 | AZ139: 40570.11 | BA139: 0 | BB139: 0 | BC139: 0 | BD139: 0 | BE139: 0 | BF139: 0 | BG139: 0 | BH139: 0 | BI139: 0 | BJ139: 0 | BK139: 0 | BL139: 0 | BM139: 7760.85 | BN139: 1466.28 | BO139: 65772.8 | BP139: 0 | BQ139: 36498.31 | BR139: 0 | BS139: 0 | BT139: 0 | BU139: 498.62 | BV139: 0 | BW139: 23305.1 | BX139: 0 | BY139: 107504.58
C140: FONDOS DE GARANTÍAS | D140: 0 | E140: 0 | F140: 0 | G140: 0 | H140: 0 | I140: 0 | J140: 0 | K140: 0 | L140: 0 | M140: 0 | N140: 0 | O140: 0 | P140: 0 | Q140: 0 | R140: 0 | S140: 0 | T140: 0 | U140: 0 | V140: 0 | W140: 0 | X140: 0 | Y140: 0 | Z140: 0 | AA140: 0 | AB140: 0 | AC140: 0 | AD140: 0 | AE140: 0 | AF140: 0 | AG140: 0 | AH140: 0 | AI140: 0 | AJ140: 0 | AK140: 0 | AL140: 0 | AM140: 0 | AN140: 0 | AO140: 0 | AP140: 0 | AQ140: 0 | AR140: 0 | AS140: 0 | AT140: 0 | AU140: 0 | AV140: 0 | AW140: 0 | AX140: 0 | AY140: 0 | AZ140: 0 | BA140: 0 | BB140: 0 | BC140: 0 | BD140: 0 | BE140: 0 | BF140: 0 | BG140: 0 | BH140: 0 | BI140: 0 | BJ140: 0 | BK140: 0 | BL140: 0 | BM140: 0 | BN140: 0 | BO140: 0 | BP140: 0 | BQ140: 0 | BR140: 0 | BS140: 0 | BT140: 0 | BU140: 0 | BV140: 0 | BW140: 0 | BX140: 0 | BY140: 0
